Workbook

Sheet Portada
B2: YPF Sociedad Anónima
B3: Estados contables trimestrales — en dólares
B5: Emisor | C5: YPF S.A. (NYSE: YPF), CIK 0000904851
B6: Fuente | C6: SEC EDGAR: estados contables adjuntos a los 6-K y a los 20-F
B7: Moneda y unidad | C7: Dólares estadounidenses, cifras completas. La compañía reporta redondeada al millón, así que en la era dólar los últimos seis dígitos son cero: es el redondeo de la fuente, no una precisión falsa. Los trimestres traducidos desde pesos no terminan en ceros porque el redondeo de origen es al millón de pesos, que son unos pocos miles de dólares.
B8: Split | C8: En 2026 el valor nominal pasó de $10 a $1: por cada acción vieja hay diez nuevas. El ADR de NYSE pasó a representar diez acciones, así que la cantidad de ADR y su precio no cambiaron. La valuación razona en ADR por eso. El resultado por acción de los estados, en cambio, cambia de base con el split.
B9: Norma contable | C9: NIIF (IFRS) tal como las emite el IASB
B10: Cobertura trimestral | C10: 2020Q1 a 2026Q2 (26 trimestres)
B11: Cobertura anual | C11: FY2019 a FY2025
B12: Presentaciones usadas | C12: 39 entre 6-K y 20-F, listadas al pie
B13: Generado | C13: 2026-09-10T19:12:59Z
B15: Cómo se arma cada trimestre
B16: Resultados | C16: El interino publica el trimestre explícito para el 1T, 2T y 3T. El 4T sale del ejercicio menos los nueve meses.
B17: Balance | C17: Es un stock: se toma tal cual a la fecha de cierre de cada trimestre.
B18: Flujo de efectivo | C18: Se publica acumulado. 1T tal cual; 2T = 6M menos 3M; 3T = 9M menos 6M; 4T = ejercicio menos 9M.
B19: Saldos de caja | C19: El saldo al cierre no se resta: es el saldo del acumulado que termina en ese trimestre. La apertura del trimestre es el cierre del anterior.
B20: Resultado por acción | C20: Solo cuando la compañía lo publica para el trimestre. Restar acumulados de un ratio por acción no da el ratio del período.
B21: Traducción de pesos | C21: Saldos al tipo de cambio de cierre; flujos al promedio del período. La resta de acumulados se hace en pesos y se convierte después.
B23: Lo que hay que saber antes de usar un número
B24: El cuarto trimestre no lo publica nadie | C24: YPF no emite un reporte de 4T: emite el ejercicio completo. El 4T de resultados y de flujo de efectivo de este libro sale del ejercicio menos los nueve meses. Es aritmética exacta, no una estimación, pero hereda cualquier reexpresión que la compañía haya hecho entre el 3T y el cierre: si algo se reclasificó, el ajuste cae entero en el 4T.
B25: El flujo de efectivo trimestral es una diferencia | C25: El estado de flujo de efectivo se publica siempre acumulado desde el 1 de enero. Cada trimestre que no sea el primero es la resta de dos acumulados, y esos dos acumulados vienen de dos presentaciones distintas.
B26: El balance empieza en el 4T23 | C26: Los estados en dólares arrancan con el 6-K del 1T24, que trae 2023 como comparativo. Del estado de situación patrimonial, un interino solo muestra dos fechas: el cierre del trimestre y el diciembre anterior. Por eso hay resultados y flujo de todo 2023 pero no balance del 1T, 2T y 3T de ese año: en dólares, esas tres fechas no existen publicadas.
B27: Hasta 2022 los estados venían en pesos, y acá están traducidos | C27: La moneda funcional de YPF es el dólar: los estados en pesos de esos años son esa misma contabilidad traducida según la NIC 21, con tipo de cambio de cierre para los saldos y promedio del período para los flujos. No son pesos reexpresados por inflación —se nota en que los comparativos no cambian de una presentación a la otra—, así que deshacer la traducción es dividir por el mismo tipo de cambio. Esos números van en marrón. El chequeo de que el camino de vuelta funciona está en la hoja Chequeos: el activo de diciembre de 2022 vuelve a dar los 25.912 millones que la compañía publicó en dólares, y el resultado neto de cada trimestre de 2020 a 2022 vuelve con menos de un millón de diferencia contra el que anunció en su earnings release.
B28: El residuo de la traducción está en los ingresos de 2022 | C28: La compañía traduce transacción por transacción y acá se usa el promedio de la cotización diaria del período. Cuando el tipo de cambio se mueve rápido, las dos cosas dejan de ser lo mismo: en 2022, con el peso perdiendo 72%, los ingresos trimestrales quedan entre 4 y 6% por encima de los del release. En 2020 y 2021 la diferencia es menor a 2%.
B29: Restar en pesos, convertir después | C29: El trimestre que sale de restar dos acumulados se arma antes de convertir. Restar dos números ya pasados a dólares con tipos de cambio distintos —el del semestre y el del trimestre— metería esa diferencia adentro del resultado.
B30: Cuando un acumulado tiene dos versiones, se usan las que convivieron | C30: Un acumulado aparece en varias presentaciones y entre 2021 y 2023 la compañía reexpresó algunos comparativos. Restar un ejercicio reexpresado de un acumulado que no lo fue cargaba trece puntos de ingresos en el cuarto trimestre de 2020. Las dos puntas de cada resta se toman de las presentaciones más cercanas entre sí.
B31: Cuando un número cambia, gana el último | C31: Un mismo período aparece en varias presentaciones: primero como período titular y después como comparativo, a veces reexpresado. Este libro toma la versión más reciente. La hoja Datos deja registrada la presentación de la que salió cada número.
B32: EBITDA no es el de la compañía | C32: El EBITDA de la hoja Análisis es resultado operativo más depreciaciones y amortizaciones del estado de flujo. El 'EBITDA ajustado' que YPF publica en su earnings release además excluye partidas que la compañía considera no recurrentes. Los dos números están cruzados en la hoja Chequeos: la diferencia es el ajuste, no un error.
B34: Hojas
B35: Resultados | C35: Estado de resultados integrales, trimestral y anual.
B36: Balance | C36: Estado de situación patrimonial.
B37: Flujo de efectivo | C37: Estado de flujo de efectivo.
B38: Tablero | C38: El trimestre en una pantalla: tarjetas y gráficos sobre fondo oscuro, con botones a cada hoja.
B39: Resumen | C39: Seis números y cinco gráficos: el trimestre y la serie, sin abrir ninguna otra hoja.
B40: Segmentos | C40: Ingresos, resultado operativo, capex y activos por negocio, con el margen de cada uno.
B41: Operativo | C41: Producción, precios de realización y las métricas por barril que salen de cruzarlos con los estados.
B42: Análisis | C42: Márgenes, retornos, estructura de capital, liquidez, capital de trabajo y caja. Todo con fórmulas.
B43: Valuación | C43: Cuatro métodos —descontado, múltiplo, reservas y valor libro— sobre supuestos editables.
B44: Comparables | C44: YPF contra Vista y Pampa: márgenes, apalancamiento y múltiplos, del XBRL de sus 20-F.
B45: Deuda | C45: La escalera de vencimientos y el detalle instrumento por instrumento.
B46: Chequeos | C46: Identidades contables y cruce contra el earnings release de la compañía.
B47: Datos | C47: Tabla larga: cada número con su derivación y la presentación de la que salió.
B49: Presentaciones usadas
B50: Accession de EDGAR | C50: Se consulta en sec.gov/cgi-bin/browse-edgar?action=getcompany&CIK=0000904851
B51: 0001193125-19-077142 | C51: 6-K, presentada el 2019-03-18
B52: 0001193125-19-096821 | C52: 20-F, presentada el 2019-04-04
B53: 0001193125-19-150596 | C53: 6-K, presentada el 2019-05-17
B54: 0001193125-19-223505 | C54: 6-K, presentada el 2019-08-16
B55: 0001193125-20-073084 | C55: 6-K, presentada el 2020-03-13
B56: 0001193125-20-119222 | C56: 20-F, presentada el 2020-04-24
B57: 0001193125-20-145071 | C57: 6-K, presentada el 2020-05-18
B58: 0001193125-20-220670 | C58: 6-K, presentada el 2020-08-17
B59: 0001193125-20-294756 | C59: 6-K, presentada el 2020-11-16
B60: 0001193125-21-079603 | C60: 6-K, presentada el 2021-03-12
B61: 0001193125-21-125294 | C61: 20-F, presentada el 2021-04-22
... B89: 0001193125-26-354159 | C89: 6-K, presentada el 2026-08-17
B91: Este libro se genera con pipeline/export/excel_estados.py. No editar a mano: la próxima corrida lo pisa.

Sheet Tablero
AU4: 2T26 | BE4: Consolidado
AG8: Ingresos | BR8: Año anterior
B93: Datos del tablero
B94: Todo lo que muestra el tablero sale de estas celdas. Son fórmulas INDEX contra las hojas de estados, Análisis, Segmentos y Valuación, desplazadas según el trimestre elegido arriba. No hay números escritos a mano.
B96: Listas
N97: Período | T97: Trimestres a elegir | Z97: Métricas | AF97: Segmentos | AL97: Comparación
B98: 1T20 | N98: 2020Q1 | T98: 2T26 | Z98: Ingresos | AF98: Consolidado | AL98: Año anterior
B99: 2T20 | N99: 2020Q2 | T99: 1T26 | Z99: EBITDA ajustado | AF99: Upstream | AL99: Trimestre anterior
B100: 3T20 | N100: 2020Q3 | T100: 4T25 | Z100: Resultado operativo | AF100: Downstream y gas
B101: 4T20 | N101: 2020Q4 | T101: 3T25 | Z101: Capex
B102: 1T21 | N102: 2021Q1 | T102: 2T25 | Z102: Flujo operativo
B103: 2T21 | N103: 2021Q2 | T103: 1T25 | Z103: Flujo de caja libre
B104: 3T21 | N104: 2021Q3 | T104: 4T24 | Z104: Resultado neto
B105: 4T21 | N105: 2021Q4 | T105: 3T24
B106: 1T22 | N106: 2022Q1 | T106: 2T24
B107: 2T22 | N107: 2022Q2 | T107: 1T24
B108: 3T22 | N108: 2022Q3 | T108: 4T23
B109: 4T22 | N109: 2022Q4 | T109: 3T23
B110: 1T23 | N110: 2023Q1 | T110: 2T23
B111: 2T23 | N111: 2023Q2 | T111: 1T23
B112: 3T23 | N112: 2023Q3 | T112: 4T22
B113: 4T23 | N113: 2023Q4
B114: 1T24 | N114: 2024Q1
B115: 2T24 | N115: 2024Q2
B116: 3T24 | N116: 2024Q3
B117: 4T24 | N117: 2024Q4
B118: 1T25 | N118: 2025Q1
B119: 2T25 | N119: 2025Q2
B120: 3T25 | N120: 2025Q3
B121: 4T25 | N121: 2025Q4
B122: 1T26 | N122: 2026Q1
B123: 2T26 | N123: 2026Q2
B125: Selección
N126: Valor
B127: Posición del trimestre elegido | N127: =MATCH($AU$4,$B$98:$B$123,0)
B128: Código | N128: =INDEX($N$98:$N$123,$N$127)
B129: Columna en las hojas de estados | N129: =MATCH($N$128,'Resultados'!$4:$4,0)
B130: Trimestres hacia atrás de la comparación | N130: =IF($BR$8="Trimestre anterior",1,4)
B131: Trimestre de comparación | N131: =INDEX($B$98:$B$123,$N$127-$N$130)
B132: Trimestre del año | N132: =VALUE(RIGHT($N$128,1))
B133: Año | N133: =VALUE(LEFT($N$128,4))
B134: Segmento (1 = consolidado) | N134: =MATCH($BE$4,$AF$98:$AF$100,0)
B135: Métrica | N135: =MATCH($AG$8,$Z$98:$Z$104,0)
B136: Acumulado del año | N136: =CHOOSE($N$132,"1T","1S","9M","FY")&RIGHT($N$133,2)
B137: Acumulado del año anterior | N137: =CHOOSE($N$132,"1T","1S","9M","FY")&RIGHT($N$133-1,2)
B138: Último ejercicio cerrado | N138: =$N$133-IF($N$132=4,0,1)
B139: Sufijo de segmento | N139: =IF($N$134>1," · "&$BE$4,"")
B140: Texto: cabecera | N140: ="Trimestre "&$AU$4&" · "&$BE$4
B141: Texto: heroe | N141: =IF($N$134=1,"EBITDA ajustado · ","EBITDA · ")&$AU$4&$N$139
B142: Texto: heroe_cmp | N142: ="EBITDA contra "&$N$131
B143: Texto: heroe_contable | N143: =IF($N$134=1,"De los estados (res. operativo + D&A)","")
B144: Texto: aviso_ebitda | N144: =IF($N$134>1,"● Sin ajustes: resultado operativo + depreciación","")
B145: Texto: aviso_operativo | N145: =IF($N$134>1,"● Solo consolidado","")
B146: Texto: mapa | N146: ="Shale operado por YPF · "&$AU$4&" contra "&$N$131&" · boe/d, bruto"
B147: Texto: operativo_sub | N147: ="Producción y precio del crudo, doce trimestres hasta "&$AU$4
B148: Texto: comparacion | N148: ="contra "&$N$131
B149: Texto: capex_serie | N149: =IF($N$134>1,"Capex devengado del segmento","")
B150: Texto: serie | N150: =IF($N$134>1,SUBSTITUTE($AG$8,"ajustado","del segmento"),$AG$8)&$N$139&" · doce trimestres hasta "&$AU$4&", en millones de US$"
B151: Texto: radar | N151: =$AU$4&" contra "&$N$131&", sobre ingresos"
B152: Texto: radar_sel | N152: ="■ "&$AU$4
B153: Texto: radar_cmp | N153: ="■ "&$N$131
B154: Texto: semestre | N154: =$N$136&" contra "&$N$137
B155: Texto: semestre_sub | N155: ="Lo que va del año"&$N$139&"; la barra llena es el doble"
B156: Texto: destino | N156: =$AU$4&", en millones de US$"
B157: Texto: capex | N157: =$AU$4&": capex devengado por negocio, en millones de US$"
B158: Texto: lineas | N158: ="Doce trimestres hasta "&$AU$4&$N$139
B159: Texto: ejercicios | N159: =IF($N$134=1,"EBITDA ajustado contra capex pagado","EBITDA contra capex devengado")&$N$139
B160: Texto: aviso | N160: =IF($N$134>1,"● Solo consolidado","")
B161: Texto: aviso_serie | N161: =IF(AND($N$134>1,$N$135>4),"● "&$AG$8&" solo existe consolidado","")
B162: Texto: aviso_flujo | N162: =IF($N$134>1,"● El flujo operativo no se abre por segmento","")
B164: Indicadores del trimestre elegido
N165: Valor
B166: EBITDA ajustado | N166: =IF($N$134=1,N(INDEX('Análisis'!$73:$73,$N$129)),CHOOSE($N$134-1,(N(INDEX('Segmentos'!$98:$98,$N$129))+N(INDEX('Segmentos'!$113:$113,$N$129))),(N(INDEX('Segmentos'!$99:$99,$N$129))+N(INDEX('Segmentos'!$114:$114,$N$129)))))
B167: EBITDA de los estados (consolidado) | N167: =IF($N$134=1,N(INDEX('Análisis'!$13:$13,$N$129)),"")
B168: Ingresos | N168: =IF($N$134=1,N(INDEX('Resultados'!$5:$5,$N$129)),CHOOSE($N$134-1,N(INDEX('Segmentos'!$90:$90,$N$129)),N(INDEX('Segmentos'!$91:$91,$N$129))))
B169: Texto: aviso_segmento | N169: =IF(AND($N$134>1,$N$168=0),"● "&$BE$4&" no se reportaba en "&$AU$4,$N$144)
B170: Margen EBITDA | N170: =IFERROR($N$166/$N$168,0)
B171: Resto hasta 100% (para la torta) | N171: =MAX(0,1-MAX(0,$N$170))
B172: EBITDA contra la comparación | N172: =IFERROR(IF(N(IF($N$134=1,N(INDEX('Análisis'!$73:$73,$N$129-$N$130)),CHOOSE($N$134-1,(N(INDEX('Segmentos'!$98:$98,$N$129-$N$130))+N(INDEX('Segmentos'!$113:$113,$N$129-$N$130))),(N(INDEX('Segmentos'!$99:$99,$N$129-$N$130))+N(INDEX('Segmentos'!$114:$114,$N$129-$N$130))))))=0,"",($N$166-IF($N$134=1,N(INDEX('Análisis'!$73:$73,$N$129-$N$130)),CHOOSE($N$134-1,(N(INDEX('Segmentos'!$98:$98,$N$129-$N$130))+N(INDEX('Segmentos'!$113:$113,$N$129-$N$130))),(N(INDEX('Segmentos'!$99:$99,$N$129-$N$130))+N(INDEX('Segmentos'!$114:$114,$N$129-$N$130))))))/ABS(IF($N$134=1,N(INDEX('Análisis'!$73:$73,$N$129-$N$130)),CHOOSE($N$134-1,(N(INDEX('Segmentos'!$98:$98,$N$129-$N$130))+N(INDEX('Segmentos'!$113:$113,$N$129-$N$130))),(N(INDEX('Segmentos'!$99:$99,$N$129-$N$130))+N(INDEX('Segmentos'!$114:$114,$N$129-$N$130))))))),"")
B173: Deuda neta / EBITDA UDM | N173: =IFERROR(INDEX('Análisis'!$38:$38,$N$129)*1,"")
B174: EV / EBITDA UDM | N174: =IFERROR(INDEX('Valuación'!$32:$32,$N$129)*1,"")
B176: Serie trimestral
N177: Ingresos | T177: EBITDA ajustado | Z177: Resultado operativo | AF177: Capex | AL177: Flujo operativo | AR177: Flujo de caja libre | AX177: Resultado neto | BD177: Métrica elegida
B178: =INDEX($B$98:$B$123,$N$127-11) | N178: =IF($N$134=1,N(INDEX('Resultados'!$5:$5,$N$129-11)),CHOOSE($N$134-1,N(INDEX('Segmentos'!$90:$90,$N$129-11)),N(INDEX('Segmentos'!$91:$91,$N$129-11)))) | T178: =IF($N$134=1,N(INDEX('Análisis'!$73:$73,$N$129-11)),CHOOSE($N$134-1,(N(INDEX('Segmentos'!$98:$98,$N$129-11))+N(INDEX('Segmentos'!$113:$113,$N$129-11))),(N(INDEX('Segmentos'!$99:$99,$N$129-11))+N(INDEX('Segmentos'!$114:$114,$N$129-11))))) | Z178: =IF($N$134=1,N(INDEX('Resultados'!$13:$13,$N$129-11)),CHOOSE($N$134-1,N(INDEX('Segmentos'!$98:$98,$N$129-11)),N(INDEX('Segmentos'!$99:$99,$N$129-11)))) | AF178: =IF($N$134=1,(-N(INDEX('Flujo de efectivo'!$34:$34,$N$129-11))),CHOOSE($N$134-1,N(INDEX('Segmentos'!$106:$106,$N$129-11)),N(INDEX('Segmentos'!$107:$107,$N$129-11)))) | AL178: =IF($N$134=1,N(INDEX('Flujo de efectivo'!$33:$33,$N$129-11)),NA()) | AR178: =IF($N$134=1,N(INDEX('Análisis'!$15:$15,$N$129-11)),NA()) | AX178: =IF($N$134=1,N(INDEX('Resultados'!$21:$21,$N$129-11)),NA()) | BD178: =CHOOSE($N$135,$N$178,$T$178,$Z$178,$AF$178,$AL$178,$AR$178,$AX$178)
B179: =INDEX($B$98:$B$123,$N$127-10) | N179: =IF($N$134=1,N(INDEX('Resultados'!$5:$5,$N$129-10)),CHOOSE($N$134-1,N(INDEX('Segmentos'!$90:$90,$N$129-10)),N(INDEX('Segmentos'!$91:$91,$N$129-10)))) | T179: =IF($N$134=1,N(INDEX('Análisis'!$73:$73,$N$129-10)),CHOOSE($N$134-1,(N(INDEX('Segmentos'!$98:$98,$N$129-10))+N(INDEX('Segmentos'!$113:$113,$N$129-10))),(N(INDEX('Segmentos'!$99:$99,$N$129-10))+N(INDEX('Segmentos'!$114:$114,$N$129-10))))) | Z179: =IF($N$134=1,N(INDEX('Resultados'!$13:$13,$N$129-10)),CHOOSE($N$134-1,N(INDEX('Segmentos'!$98:$98,$N$129-10)),N(INDEX('Segmentos'!$99:$99,$N$129-10)))) | AF179: =IF($N$134=1,(-N(INDEX('Flujo de efectivo'!$34:$34,$N$129-10))),CHOOSE($N$134-1,N(INDEX('Segmentos'!$106:$106,$N$129-10)),N(INDEX('Segmentos'!$107:$107,$N$129-10)))) | AL179: =IF($N$134=1,N(INDEX('Flujo de efectivo'!$33:$33,$N$129-10)),NA()) | AR179: =IF($N$134=1,N(INDEX('Análisis'!$15:$15,$N$129-10)),NA()) | AX179: =IF($N$134=1,N(INDEX('Resultados'!$21:$21,$N$129-10)),NA()) | BD179: =CHOOSE($N$135,$N$179,$T$179,$Z$179,$AF$179,$AL$179,$AR$179,$AX$179)
B180: =INDEX($B$98:$B$123,$N$127-9) | N180: =IF($N$134=1,N(INDEX('Resultados'!$5:$5,$N$129-9)),CHOOSE($N$134-1,N(INDEX('Segmentos'!$90:$90,$N$129-9)),N(INDEX('Segmentos'!$91:$91,$N$129-9)))) | T180: =IF($N$134=1,N(INDEX('Análisis'!$73:$73,$N$129-9)),CHOOSE($N$134-1,(N(INDEX('Segmentos'!$98:$98,$N$129-9))+N(INDEX('Segmentos'!$113:$113,$N$129-9))),(N(INDEX('Segmentos'!$99:$99,$N$129-9))+N(INDEX('Segmentos'!$114:$114,$N$129-9))))) | Z180: =IF($N$134=1,N(INDEX('Resultados'!$13:$13,$N$129-9)),CHOOSE($N$134-1,N(INDEX('Segmentos'!$98:$98,$N$129-9)),N(INDEX('Segmentos'!$99:$99,$N$129-9)))) | AF180: =IF($N$134=1,(-N(INDEX('Flujo de efectivo'!$34:$34,$N$129-9))),CHOOSE($N$134-1,N(INDEX('Segmentos'!$106:$106,$N$129-9)),N(INDEX('Segmentos'!$107:$107,$N$129-9)))) | AL180: =IF($N$134=1,N(INDEX('Flujo de efectivo'!$33:$33,$N$129-9)),NA()) | AR180: =IF($N$134=1,N(INDEX('Análisis'!$15:$15,$N$129-9)),NA()) | AX180: =IF($N$134=1,N(INDEX('Resultados'!$21:$21,$N$129-9)),NA()) | BD180: =CHOOSE($N$135,$N$180,$T$180,$Z$180,$AF$180,$AL$180,$AR$180,$AX$180)
B181: =INDEX($B$98:$B$123,$N$127-8) | N181: =IF($N$134=1,N(INDEX('Resultados'!$5:$5,$N$129-8)),CHOOSE($N$134-1,N(INDEX('Segmentos'!$90:$90,$N$129-8)),N(INDEX('Segmentos'!$91:$91,$N$129-8)))) | T181: =IF($N$134=1,N(INDEX('Análisis'!$73:$73,$N$129-8)),CHOOSE($N$134-1,(N(INDEX('Segmentos'!$98:$98,$N$129-8))+N(INDEX('Segmentos'!$113:$113,$N$129-8))),(N(INDEX('Segmentos'!$99:$99,$N$129-8))+N(INDEX('Segmentos'!$114:$114,$N$129-8))))) | Z181: =IF($N$134=1,N(INDEX('Resultados'!$13:$13,$N$129-8)),CHOOSE($N$134-1,N(INDEX('Segmentos'!$98:$98,$N$129-8)),N(INDEX('Segmentos'!$99:$99,$N$129-8)))) | AF181: =IF($N$134=1,(-N(INDEX('Flujo de efectivo'!$34:$34,$N$129-8))),CHOOSE($N$134-1,N(INDEX('Segmentos'!$106:$106,$N$129-8)),N(INDEX('Segmentos'!$107:$107,$N$129-8)))) | AL181: =IF($N$134=1,N(INDEX('Flujo de efectivo'!$33:$33,$N$129-8)),NA()) | AR181: =IF($N$134=1,N(INDEX('Análisis'!$15:$15,$N$129-8)),NA()) | AX181: =IF($N$134=1,N(INDEX('Resultados'!$21:$21,$N$129-8)),NA()) | BD181: =CHOOSE($N$135,$N$181,$T$181,$Z$181,$AF$181,$AL$181,$AR$181,$AX$181)
B182: =INDEX($B$98:$B$123,$N$127-7) | N182: =IF($N$134=1,N(INDEX('Resultados'!$5:$5,$N$129-7)),CHOOSE($N$134-1,N(INDEX('Segmentos'!$90:$90,$N$129-7)),N(INDEX('Segmentos'!$91:$91,$N$129-7)))) | T182: =IF($N$134=1,N(INDEX('Análisis'!$73:$73,$N$129-7)),CHOOSE($N$134-1,(N(INDEX('Segmentos'!$98:$98,$N$129-7))+N(INDEX('Segmentos'!$113:$113,$N$129-7))),(N(INDEX('Segmentos'!$99:$99,$N$129-7))+N(INDEX('Segmentos'!$114:$114,$N$129-7))))) | Z182: =IF($N$134=1,N(INDEX('Resultados'!$13:$13,$N$129-7)),CHOOSE($N$134-1,N(INDEX('Segmentos'!$98:$98,$N$129-7)),N(INDEX('Segmentos'!$99:$99,$N$129-7)))) | AF182: =IF($N$134=1,(-N(INDEX('Flujo de efectivo'!$34:$34,$N$129-7))),CHOOSE($N$134-1,N(INDEX('Segmentos'!$106:$106,$N$129-7)),N(INDEX('Segmentos'!$107:$107,$N$129-7)))) | AL182: =IF($N$134=1,N(INDEX('Flujo de efectivo'!$33:$33,$N$129-7)),NA()) | AR182: =IF($N$134=1,N(INDEX('Análisis'!$15:$15,$N$129-7)),NA()) | AX182: =IF($N$134=1,N(INDEX('Resultados'!$21:$21,$N$129-7)),NA()) | BD182: =CHOOSE($N$135,$N$182,$T$182,$Z$182,$AF$182,$AL$182,$AR$182,$AX$182)
B183: =INDEX($B$98:$B$123,$N$127-6) | N183: =IF($N$134=1,N(INDEX('Resultados'!$5:$5,$N$129-6)),CHOOSE($N$134-1,N(INDEX('Segmentos'!$90:$90,$N$129-6)),N(INDEX('Segmentos'!$91:$91,$N$129-6)))) | T183: =IF($N$134=1,N(INDEX('Análisis'!$73:$73,$N$129-6)),CHOOSE($N$134-1,(N(INDEX('Segmentos'!$98:$98,$N$129-6))+N(INDEX('Segmentos'!$113:$113,$N$129-6))),(N(INDEX('Segmentos'!$99:$99,$N$129-6))+N(INDEX('Segmentos'!$114:$114,$N$129-6))))) | Z183: =IF($N$134=1,N(INDEX('Resultados'!$13:$13,$N$129-6)),CHOOSE($N$134-1,N(INDEX('Segmentos'!$98:$98,$N$129-6)),N(INDEX('Segmentos'!$99:$99,$N$129-6)))) | AF183: =IF($N$134=1,(-N(INDEX('Flujo de efectivo'!$34:$34,$N$129-6))),CHOOSE($N$134-1,N(INDEX('Segmentos'!$106:$106,$N$129-6)),N(INDEX('Segmentos'!$107:$107,$N$129-6)))) | AL183: =IF($N$134=1,N(INDEX('Flujo de efectivo'!$33:$33,$N$129-6)),NA()) | AR183: =IF($N$134=1,N(INDEX('Análisis'!$15:$15,$N$129-6)),NA()) | AX183: =IF($N$134=1,N(INDEX('Resultados'!$21:$21,$N$129-6)),NA()) | BD183: =CHOOSE($N$135,$N$183,$T$183,$Z$183,$AF$183,$AL$183,$AR$183,$AX$183)
B184: =INDEX($B$98:$B$123,$N$127-5) | N184: =IF($N$134=1,N(INDEX('Resultados'!$5:$5,$N$129-5)),CHOOSE($N$134-1,N(INDEX('Segmentos'!$90:$90,$N$129-5)),N(INDEX('Segmentos'!$91:$91,$N$129-5)))) | T184: =IF($N$134=1,N(INDEX('Análisis'!$73:$73,$N$129-5)),CHOOSE($N$134-1,(N(INDEX('Segmentos'!$98:$98,$N$129-5))+N(INDEX('Segmentos'!$113:$113,$N$129-5))),(N(INDEX('Segmentos'!$99:$99,$N$129-5))+N(INDEX('Segmentos'!$114:$114,$N$129-5))))) | Z184: =IF($N$134=1,N(INDEX('Resultados'!$13:$13,$N$129-5)),CHOOSE($N$134-1,N(INDEX('Segmentos'!$98:$98,$N$129-5)),N(INDEX('Segmentos'!$99:$99,$N$129-5)))) | AF184: =IF($N$134=1,(-N(INDEX('Flujo de efectivo'!$34:$34,$N$129-5))),CHOOSE($N$134-1,N(INDEX('Segmentos'!$106:$106,$N$129-5)),N(INDEX('Segmentos'!$107:$107,$N$129-5)))) | AL184: =IF($N$134=1,N(INDEX('Flujo de efectivo'!$33:$33,$N$129-5)),NA()) | AR184: =IF($N$134=1,N(INDEX('Análisis'!$15:$15,$N$129-5)),NA()) | AX184: =IF($N$134=1,N(INDEX('Resultados'!$21:$21,$N$129-5)),NA()) | BD184: =CHOOSE($N$135,$N$184,$T$184,$Z$184,$AF$184,$AL$184,$AR$184,$AX$184)
B185: =INDEX($B$98:$B$123,$N$127-4) | N185: =IF($N$134=1,N(INDEX('Resultados'!$5:$5,$N$129-4)),CHOOSE($N$134-1,N(INDEX('Segmentos'!$90:$90,$N$129-4)),N(INDEX('Segmentos'!$91:$91,$N$129-4)))) | T185: =IF($N$134=1,N(INDEX('Análisis'!$73:$73,$N$129-4)),CHOOSE($N$134-1,(N(INDEX('Segmentos'!$98:$98,$N$129-4))+N(INDEX('Segmentos'!$113:$113,$N$129-4))),(N(INDEX('Segmentos'!$99:$99,$N$129-4))+N(INDEX('Segmentos'!$114:$114,$N$129-4))))) | Z185: =IF($N$134=1,N(INDEX('Resultados'!$13:$13,$N$129-4)),CHOOSE($N$134-1,N(INDEX('Segmentos'!$98:$98,$N$129-4)),N(INDEX('Segmentos'!$99:$99,$N$129-4)))) | AF185: =IF($N$134=1,(-N(INDEX('Flujo de efectivo'!$34:$34,$N$129-4))),CHOOSE($N$134-1,N(INDEX('Segmentos'!$106:$106,$N$129-4)),N(INDEX('Segmentos'!$107:$107,$N$129-4)))) | AL185: =IF($N$134=1,N(INDEX('Flujo de efectivo'!$33:$33,$N$129-4)),NA()) | AR185: =IF($N$134=1,N(INDEX('Análisis'!$15:$15,$N$129-4)),NA()) | AX185: =IF($N$134=1,N(INDEX('Resultados'!$21:$21,$N$129-4)),NA()) | BD185: =CHOOSE($N$135,$N$185,$T$185,$Z$185,$AF$185,$AL$185,$AR$185,$AX$185)
B186: =INDEX($B$98:$B$123,$N$127-3) | N186: =IF($N$134=1,N(INDEX('Resultados'!$5:$5,$N$129-3)),CHOOSE($N$134-1,N(INDEX('Segmentos'!$90:$90,$N$129-3)),N(INDEX('Segmentos'!$91:$91,$N$129-3)))) | T186: =IF($N$134=1,N(INDEX('Análisis'!$73:$73,$N$129-3)),CHOOSE($N$134-1,(N(INDEX('Segmentos'!$98:$98,$N$129-3))+N(INDEX('Segmentos'!$113:$113,$N$129-3))),(N(INDEX('Segmentos'!$99:$99,$N$129-3))+N(INDEX('Segmentos'!$114:$114,$N$129-3))))) | Z186: =IF($N$134=1,N(INDEX('Resultados'!$13:$13,$N$129-3)),CHOOSE($N$134-1,N(INDEX('Segmentos'!$98:$98,$N$129-3)),N(INDEX('Segmentos'!$99:$99,$N$129-3)))) | AF186: =IF($N$134=1,(-N(INDEX('Flujo de efectivo'!$34:$34,$N$129-3))),CHOOSE($N$134-1,N(INDEX('Segmentos'!$106:$106,$N$129-3)),N(INDEX('Segmentos'!$107:$107,$N$129-3)))) | AL186: =IF($N$134=1,N(INDEX('Flujo de efectivo'!$33:$33,$N$129-3)),NA()) | AR186: =IF($N$134=1,N(INDEX('Análisis'!$15:$15,$N$129-3)),NA()) | AX186: =IF($N$134=1,N(INDEX('Resultados'!$21:$21,$N$129-3)),NA()) | BD186: =CHOOSE($N$135,$N$186,$T$186,$Z$186,$AF$186,$AL$186,$AR$186,$AX$186)
B187: =INDEX($B$98:$B$123,$N$127-2) | N187: =IF($N$134=1,N(INDEX('Resultados'!$5:$5,$N$129-2)),CHOOSE($N$134-1,N(INDEX('Segmentos'!$90:$90,$N$129-2)),N(INDEX('Segmentos'!$91:$91,$N$129-2)))) | T187: =IF($N$134=1,N(INDEX('Análisis'!$73:$73,$N$129-2)),CHOOSE($N$134-1,(N(INDEX('Segmentos'!$98:$98,$N$129-2))+N(INDEX('Segmentos'!$113:$113,$N$129-2))),(N(INDEX('Segmentos'!$99:$99,$N$129-2))+N(INDEX('Segmentos'!$114:$114,$N$129-2))))) | Z187: =IF($N$134=1,N(INDEX('Resultados'!$13:$13,$N$129-2)),CHOOSE($N$134-1,N(INDEX('Segmentos'!$98:$98,$N$129-2)),N(INDEX('Segmentos'!$99:$99,$N$129-2)))) | AF187: =IF($N$134=1,(-N(INDEX('Flujo de efectivo'!$34:$34,$N$129-2))),CHOOSE($N$134-1,N(INDEX('Segmentos'!$106:$106,$N$129-2)),N(INDEX('Segmentos'!$107:$107,$N$129-2)))) | AL187: =IF($N$134=1,N(INDEX('Flujo de efectivo'!$33:$33,$N$129-2)),NA()) | AR187: =IF($N$134=1,N(INDEX('Análisis'!$15:$15,$N$129-2)),NA()) | AX187: =IF($N$134=1,N(INDEX('Resultados'!$21:$21,$N$129-2)),NA()) | BD187: =CHOOSE($N$135,$N$187,$T$187,$Z$187,$AF$187,$AL$187,$AR$187,$AX$187)
B188: =INDEX($B$98:$B$123,$N$127-1) | N188: =IF($N$134=1,N(INDEX('Resultados'!$5:$5,$N$129-1)),CHOOSE($N$134-1,N(INDEX('Segmentos'!$90:$90,$N$129-1)),N(INDEX('Segmentos'!$91:$91,$N$129-1)))) | T188: =IF($N$134=1,N(INDEX('Análisis'!$73:$73,$N$129-1)),CHOOSE($N$134-1,(N(INDEX('Segmentos'!$98:$98,$N$129-1))+N(INDEX('Segmentos'!$113:$113,$N$129-1))),(N(INDEX('Segmentos'!$99:$99,$N$129-1))+N(INDEX('Segmentos'!$114:$114,$N$129-1))))) | Z188: =IF($N$134=1,N(INDEX('Resultados'!$13:$13,$N$129-1)),CHOOSE($N$134-1,N(INDEX('Segmentos'!$98:$98,$N$129-1)),N(INDEX('Segmentos'!$99:$99,$N$129-1)))) | AF188: =IF($N$134=1,(-N(INDEX('Flujo de efectivo'!$34:$34,$N$129-1))),CHOOSE($N$134-1,N(INDEX('Segmentos'!$106:$106,$N$129-1)),N(INDEX('Segmentos'!$107:$107,$N$129-1)))) | AL188: =IF($N$134=1,N(INDEX('Flujo de efectivo'!$33:$33,$N$129-1)),NA()) | AR188: =IF($N$134=1,N(INDEX('Análisis'!$15:$15,$N$129-1)),NA()) | AX188: =IF($N$134=1,N(INDEX('Resultados'!$21:$21,$N$129-1)),NA()) | BD188: =CHOOSE($N$135,$N$188,$T$188,$Z$188,$AF$188,$AL$188,$AR$188,$AX$188)
B189: =INDEX($B$98:$B$123,$N$127-0) | N189: =IF($N$134=1,N(INDEX('Resultados'!$5:$5,$N$129)),CHOOSE($N$134-1,N(INDEX('Segmentos'!$90:$90,$N$129)),N(INDEX('Segmentos'!$91:$91,$N$129)))) | T189: =IF($N$134=1,N(INDEX('Análisis'!$73:$73,$N$129)),CHOOSE($N$134-1,(N(INDEX('Segmentos'!$98:$98,$N$129))+N(INDEX('Segmentos'!$113:$113,$N$129))),(N(INDEX('Segmentos'!$99:$99,$N$129))+N(INDEX('Segmentos'!$114:$114,$N$129))))) | Z189: =IF($N$134=1,N(INDEX('Resultados'!$13:$13,$N$129)),CHOOSE($N$134-1,N(INDEX('Segmentos'!$98:$98,$N$129)),N(INDEX('Segmentos'!$99:$99,$N$129)))) | AF189: =IF($N$134=1,(-N(INDEX('Flujo de efectivo'!$34:$34,$N$129))),CHOOSE($N$134-1,N(INDEX('Segmentos'!$106:$106,$N$129)),N(INDEX('Segmentos'!$107:$107,$N$129)))) | AL189: =IF($N$134=1,N(INDEX('Flujo de efectivo'!$33:$33,$N$129)),NA()) | AR189: =IF($N$134=1,N(INDEX('Análisis'!$15:$15,$N$129)),NA()) | AX189: =IF($N$134=1,N(INDEX('Resultados'!$21:$21,$N$129)),NA()) | BD189: =CHOOSE($N$135,$N$189,$T$189,$Z$189,$AF$189,$AL$189,$AR$189,$AX$189)
B190: Métrica elegida, últimos doce meses | N190: =IFERROR(SUM($BD$186:$BD$189),"")
B192: Márgenes consolidados
N193: =$AU$4 | T193: =$N$131 | Z193: Gráfico: elegido | AF193: Gráfico: comparación
B194: Bruto | N194: =IFERROR(N(INDEX('Resultados'!$7:$7,$N$129))/N(INDEX('Resultados'!$5:$5,$N$129)),"") | T194: =IFERROR(N(INDEX('Resultados'!$7:$7,$N$129-$N$130))/N(INDEX('Resultados'!$5:$5,$N$129-$N$130)),"") | Z194: =IFERROR(MAX(0,$N$194),0) | AF194: =IFERROR(MAX(0,$T$194),0)
B195: Operativo | N195: =IFERROR(N(INDEX('Resultados'!$13:$13,$N$129))/N(INDEX('Resultados'!$5:$5,$N$129)),"") | T195: =IFERROR(N(INDEX('Resultados'!$13:$13,$N$129-$N$130))/N(INDEX('Resultados'!$5:$5,$N$129-$N$130)),"") | Z195: =IFERROR(MAX(0,$N$195),0) | AF195: =IFERROR(MAX(0,$T$195),0)
...

Sheet Resumen
B2: YPF de un vistazo
B3: Al cierre de 2026Q2, contra el mismo trimestre del año anterior. Todo referenciado a las hojas de estados.
B5: Ingresos del trimestre | E5: EBITDA del trimestre | H5: Resultado neto
B6: ='Resultados'!AA5 | E6: ='Análisis'!AA13 | H6: ='Resultados'!AA21
B7: =IFERROR('Resultados'!AA5/'Resultados'!W5-1,"") | C7: contra un año antes | E7: =IFERROR('Análisis'!AA13/'Análisis'!W13-1,"") | F7: contra un año antes | H7: =IFERROR('Resultados'!AA21/'Resultados'!W21-1,"") | I7: contra un año antes
B9: Flujo de caja libre | E9: Deuda neta / EBITDA UDM | H9: Margen EBITDA
B10: ='Análisis'!AA15 | E10: ='Análisis'!AA38 | H10: ='Análisis'!AA8
B11: =IFERROR('Análisis'!AA15/'Análisis'!W15-1,"") | C11: contra un año antes
B56: Los gráficos leen las hojas de estados: no hay datos copiados acá. La serie de trimestres arranca en 2020 y los anteriores a 2023 están traducidos desde pesos (ver Portada).

Sheet Resultados
A1: Estado de resultados integrales
A2: Consolidado, en dólares (la compañía reporta redondeado al millón)
A4: En dólares | B4: 2020Q1 | C4: 2020Q2 | D4: 2020Q3 | E4: 2020Q4 | F4: 2021Q1 | G4: 2021Q2 | H4: 2021Q3 | I4: 2021Q4 | J4: 2022Q1 | K4: 2022Q2 | L4: 2022Q3 | M4: 2022Q4 | N4: 2023Q1 | O4: 2023Q2 | P4: 2023Q3 | Q4: 2023Q4 | R4: 2024Q1 | S4: 2024Q2 | T4: 2024Q3 | U4: 2024Q4 | V4: 2025Q1 | W4: 2025Q2 | X4: 2025Q3 | Y4: 2025Q4 | Z4: 2026Q1 | AA4: 2026Q2 | AC4: FY19 | AD4: FY20 | AE4: FY21 | AF4: FY22 | AG4: FY23 | AH4: FY24 | AI4: FY25
A5: Revenues | B5: 2.8440769e+09 | C5: 1.9782046e+09 | D5: 2.3689528e+09 | E5: 2.3436098e+09 | F5: 2.6534915e+09 | G5: 3.3621325e+09 | H5: 3.637745e+09 | I5: 3.6532618e+09 | J5: 3.7655069e+09 | K5: 5.0522633e+09 | L5: 5.4773226e+09 | M5: 4.8542887e+09 | N5: 4238000000 | O5: 4375000000 | P5: 4504000000 | Q5: 4194000000 | R5: 4310000000 | S5: 4935000000 | T5: 5297000000 | U5: 4751000000 | V5: 4608000000 | W5: 4641000000 | X5: 4643000000 | Y5: 4556000000 | Z5: 4946000000 | AA5: 6574000000 | AC5: 1.4097402e+10 | AD5: 9690000000 | AE5: 13682000000 | AF5: 18757000000 | AG5: 17311000000 | AH5: 19293000000 | AI5: 18448000000
A6: Costs | B6: -2.3758552e+09 | C6: -2.1746653e+09 | D6: -2.2169443e+09 | E6: -2.1392176e+09 | F6: -2.2427533e+09 | G6: -2.6497019e+09 | H6: -2.833107e+09 | I6: -3.0395488e+09 | J6: -2.8433938e+09 | K6: -3.481032e+09 | L6: -3.8898364e+09 | M6: -3.9538518e+09 | N6: -3299000000 | O6: -3509000000 | P6: -3689000000 | Q6: -3356000000 | R6: -3019000000 | S6: -3457000000 | T6: -3678000000 | U6: -3756000000 | V6: -3308000000 | W6: -3448000000 | X6: -3319000000 | Y6: -3232000000 | Z6: -3188000000 | AA6: -3609000000 | AC6: -1.1957909e+10 | AD6: -8663000000 | AE6: -10629000000 | AF6: -13684000000 | AG6: -13853000000 | AH6: -13910000000 | AI6: -13348000000
A7: Gross profit | B7: 4.6822164e+08 | C7: -1.9646076e+08 | D7: 1.5200843e+08 | E7: 2.0439221e+08 | F7: 4.107382e+08 | G7: 7.1243068e+08 | H7: 8.0463802e+08 | I7: 6.1371302e+08 | J7: 9.2211308e+08 | K7: 1.5712312e+09 | L7: 1.5874862e+09 | M7: 9.004369e+08 | N7: 939000000 | O7: 866000000 | P7: 815000000 | Q7: 838000000 | R7: 1291000000 | S7: 1478000000 | T7: 1619000000 | U7: 995000000 | V7: 1300000000 | W7: 1193000000 | X7: 1324000000 | Y7: 1324000000 | Z7: 1758000000 | AA7: 2965000000 | AC7: 2.1394929e+09 | AD7: 1027000000 | AE7: 3053000000 | AF7: 5073000000 | AG7: 3458000000 | AH7: 5383000000 | AI7: 5100000000
A8: Selling expenses | B8: -2.2593697e+08 | C8: -3.4315461e+08 | D8: -2.2336991e+08 | E8: -2.304319e+08 | F8: -2.253135e+08 | G8: -2.769659e+08 | H8: -2.8159861e+08 | I8: -2.8502707e+08 | J8: -3.7993584e+08 | K8: -5.3277781e+08 | L8: -5.6240972e+08 | M8: -4.8219902e+08 | N8: -420000000 | O8: -482000000 | P8: -483000000 | Q8: -419000000 | R8: -467000000 | S8: -577000000 | T8: -552000000 | U8: -536000000 | V8: -497000000 | W8: -510000000 | X8: -495000000 | Y8: -530000000 | Z8: -489000000 | AA8: -601000000 | AC8: -1.0366009e+09 | AD8: -1324000000 | AE8: -1507000000 | AF8: -1896000000 | AG8: -1804000000 | AH8: -2132000000 | AI8: -2088000000
A9: Administrative expenses | B9: -1.0989108e+08 | C9: -1.0935387e+08 | D9: -1.2486211e+08 | E9: -1.401868e+08 | F9: -1.0308276e+08 | G9: -1.1614665e+08 | H9: -1.1854942e+08 | I9: -1.4271262e+08 | J9: -1.3857631e+08 | K9: -1.6291826e+08 | L9: -1.7981326e+08 | M9: -2.0885045e+08 | N9: -157000000 | O9: -167000000 | P9: -194000000 | Q9: -187000000 | R9: -141000000 | S9: -210000000 | T9: -224000000 | U9: -261000000 | V9: -258000000 | W9: -233000000 | X9: -207000000 | Y9: -229000000 | Z9: -291000000 | AA9: -323000000 | AC9: -5.131484e+08 | AD9: -467000000 | AE9: -470000000 | AF9: -657000000 | AG9: -705000000 | AH9: -836000000 | AI9: -830000000
A10: Exploration expenses | B10: -11658322 | C10: -2073620.8 | D10: -57597157 | E10: -9650812.5 | F10: -1796181.8 | G10: -8557725.9 | H10: -9908270.8 | I10: -6748912.1 | J10: -10533450 | K10: -13165369 | L10: -19126873 | M10: -23811840 | N10: -18000000 | O10: -8000000 | P10: -16000000 | Q10: -19000000 | R10: -23000000 | S10: -88000000 | T10: -20000000 | U10: -108000000 | V10: -30000000 | W10: -21000000 | X10: -17000000 | Y10: -48000000 | Z10: -20000000 | AA10: -17000000 | AC10: -1.4211765e+08 | AD10: -80000000 | AE10: -30000000 | AF10: -65000000 | AG10: -61000000 | AH10: -239000000 | AI10: -116000000
A11: Inventories write-down and reversal of impairment losses of property, plant and equipment | C11: -8.5061405e+08 | L11: -1.0406553e+08 | M11: -26657164 | P11: -506000000 | Q11: -1782000000 | S11: -5000000 | T11: -21000000 | U11: -61000000 | W11: 9000000 | X11: -5000000 | Y11: 0 | AA11: -8000000 | AF11: -123000000 | AG11: -2288000000 | AH11: -87000000 | AI11: 4000000
A12: Other net operating results | B12: 1.2021423e+08 | C12: 1.1760392e+08 | D12: -47738184 | E12: -98483291 | F12: -3117900.5 | G12: -585416.57 | H12: 33809531 | I12: -2.608783e+08 | J12: -13666284 | K12: -11614009 | L12: -18278593 | M12: 2.2004041e+08 | N12: -9000000 | O12: 12000000 | P12: -3000000 | Q12: 152000000 | R12: 6000000 | S12: -8000000 | T12: -48000000 | U12: -559000000 | V12: -323000000 | W12: -26000000 | X12: -48000000 | Y12: 67000000 | Z12: -80000000 | AA12: -203000000 | AC12: -23475069 | AD12: 93000000 | AE12: -232000000 | AF12: 150000000 | AG12: 152000000 | AH12: -609000000 | AI12: -330000000
A13: Operating profit | B13: 2.409495e+08 | C13: -1.384053e+09 | D13: -3.2074434e+08 | E13: 5.4677103e+08 | F13: 77427862 | G13: 3.1017499e+08 | H13: 4.2839124e+08 | I13: -1.9371767e+08 | J13: 3.7940119e+08 | K13: 8.507558e+08 | L13: 7.037922e+08 | M13: 3.7895883e+08 | N13: 335000000 | O13: 221000000 | P13: -387000000 | Q13: -1417000000 | R13: 666000000 | S13: 590000000 | T13: 754000000 | U13: -530000000 | V13: 192000000 | W13: 412000000 | X13: 552000000 | Y13: 584000000 | Z13: 878000000 | AA13: 1813000000 | AC13: -4.3651164e+08 | AD13: -804000000 | AE13: 699000000 | AF13: 2482000000 | AG13: -1248000000 | AH13: 1480000000 | AI13: 1740000000
A14: Income from equity interests in associates and joint ventures | B14: 23121252 | C14: 34066627 | D14: 61857544 | E14: 62755283 | F14: 57794126 | G14: 15316626 | H14: 44839298 | I14: 1.5990343e+08 | J14: 1.1470487e+08 | K14: 1.3110266e+08 | L14: 1.4043093e+08 | M14: 70052977 | N14: 89000000 | O14: 94000000 | P14: 44000000 | Q14: -133000000 | R14: 129000000 | S14: 27000000 | T14: 107000000 | U14: 133000000 | V14: 81000000 | W14: -6000000 | X14: 32000000 | Y14: 15000000 | Z14: 101000000 | AA14: 115000000 | AC14: 1.655304e+08 | AD14: 188000000 | AE14: 287000000 | AF14: 446000000 | AG14: 94000000 | AH14: 396000000 | AI14: 122000000
A15: Financial income | B15: 3.3877519e+08 | C15: 4.5644837e+08 | D15: 3.0383934e+08 | E15: 4.21648e+08 | F15: 2.5244827e+08 | G15: 2.0557701e+08 | H15: 1.5818251e+08 | I15: 3.0052567e+08 | J15: 3.0118352e+08 | K15: 4.5554041e+08 | L15: 6.4385199e+08 | M15: 8.3124801e+08 | N15: 45000000 | O15: 81000000 | P15: 104000000 | Q15: 104000000 | R15: 36000000 | S15: 32000000 | T15: 19000000 | U15: 47000000 | V15: 16000000 | W15: 28000000 | X15: 28000000 | Y15: 33000000 | Z15: 32000000 | AA15: 63000000 | AC15: 1.9404326e+09 | AD15: 1492000000 | AE15: 904000000 | AF15: 320000000 | AG15: 334000000 | AH15: 134000000 | AI15: 105000000
A16: Financial costs | J16: -4.0367597e+08 | K16: -5.1678099e+08 | L16: -6.3455779e+08 | M16: -7.9393168e+08 | N16: -279000000 | O16: -295000000 | P16: -319000000 | Q16: -256000000 | R16: -336000000 | S16: -308000000 | T16: -267000000 | U16: -258000000 | V16: -285000000 | W16: -279000000 | X16: -257000000 | Y16: -266000000 | Z16: -304000000 | AA16: -312000000 | AD16: -1966000000 | AE16: -1408000000 | AF16: -988000000 | AG16: -1149000000 | AH16: -1169000000 | AI16: -1087000000
A17: Other financial results | B17: -21053366 | C17: 1.7884979e+08 | D17: 50318995 | E17: 67280664 | F17: 64221972 | G17: 56008400 | H17: 67238369 | I17: 65478384 | J17: 59392528 | K17: 59485765 | L17: 1.1417113e+08 | M17: 1.5736306e+08 | N17: 236000000 | O17: 354000000 | P17: 421000000 | Q17: 701000000 | R17: 41000000 | S17: 115000000 | T17: 38000000 | U17: 108000000 | V17: 24000000 | W17: -5000000 | X17: -16000000 | Y17: 27000000 | Z17: -55000000 | AA17: 119000000 | AC17: 86463043 | AD17: 253000000 | AE17: 233000000 | AF17: 796000000 | AG17: 311000000 | AH17: 179000000 | AI17: 30000000
A18: Net financial results | B18: -1.729372e+08 | C18: 77197939 | D18: -1.017304e+08 | E18: 19476640 | F18: -48474315 | G18: -1.1572089e+08 | H18: -81828118 | I18: 15628012 | J18: -43099915 | K18: -1754817.4 | L18: 1.2346533e+08 | M18: 1.9467938e+08 | N18: 2000000 | O18: 140000000 | P18: 206000000 | Q18: 549000000 | R18: -259000000 | S18: -161000000 | T18: -210000000 | U18: -103000000 | V18: -245000000 | W18: -256000000 | X18: -245000000 | Y18: -206000000 | Z18: -327000000 | AA18: -130000000 | AC18: 1.2535272e+08 | AD18: -221000000 | AE18: -271000000 | AF18: 128000000 | AG18: -504000000 | AH18: -856000000 | AI18: -952000000
A19: Net profit before income tax | B19: 91133556 | C19: -1.2727884e+09 | D19: -3.6061719e+08 | E19: 6.2900295e+08 | F19: 86747673 | G19: 2.0977072e+08 | H19: 3.9140242e+08 | I19: -18186228 | J19: 4.5100614e+08 | K19: 9.8010364e+08 | L19: 9.6768846e+08 | M19: 6.4369119e+08 | N19: 426000000 | O19: 455000000 | P19: -137000000 | Q19: -1001000000 | R19: 536000000 | S19: 456000000 | T19: 651000000 | U19: -500000000 | V19: 28000000 | W19: 150000000 | X19: 339000000 | Y19: 393000000 | Z19: 652000000 | AA19: 1798000000 | AC19: -1.4562853e+08 | AD19: -837000000 | AE19: 715000000 | AF19: 3056000000 | AG19: -1658000000 | AH19: 1020000000 | AI19: 910000000
A20: Income tax | B20: 12277059 | C20: 13093434 | D20: -1.2184434e+08 | E20: -91307687 | F20: -1.1213145e+08 | G20: -7.0218057e+08 | H20: -1.5505466e+08 | I20: 2.643523e+08 | J20: -2.0322149e+08 | K20: -1.8269598e+08 | L20: -2.8772186e+08 | M20: -1.6472634e+08 | N20: -85000000 | O20: -75000000 | P20: 0 | Q20: -860000000 | R20: 121000000 | S20: 79000000 | T20: 834000000 | U20: 216000000 | V20: -38000000 | W20: -92000000 | X20: -537000000 | Y20: -1042000000 | Z20: -243000000 | AA20: -593000000 | AC20: -5.4780009e+08 | AD20: -184000000 | AE20: -699000000 | AF20: -822000000 | AG20: 381000000 | AH20: 1373000000 | AI20: -1709000000
A21: Net profit for the period | B21: 1.0341061e+08 | D21: -4.8246153e+08 | E21: 5.3769527e+08 | F21: -25383777 | G21: -4.9240985e+08 | H21: 2.3634776e+08 | I21: 2.4616607e+08 | J21: 2.4778465e+08 | K21: 7.9740766e+08 | L21: 6.7996659e+08 | M21: 4.7896486e+08 | N21: 341000000 | O21: 380000000 | P21: -137000000 | Q21: -1861000000 | R21: 657000000 | S21: 535000000 | T21: 1485000000 | U21: -284000000 | V21: -10000000 | W21: 58000000 | X21: -198000000 | Y21: -649000000 | Z21: 409000000 | AA21: 1205000000 | AC21: -6.9342862e+08 | AD21: -1021000000 | AE21: 16000000 | AF21: 2234000000 | AG21: -1277000000 | AH21: 2393000000 | AI21: -799000000
A22: Translation effect from subsidiaries, associates and joint ventures | J22: -35971311 | K22: -58324364 | L22: -78779406 | M22: -82588448 | N22: -85000000 | O22: -106000000 | P22: -97000000 | Q22: -154000000 | R22: -27000000 | S22: -29000000 | T22: -22000000 | U22: -25000000 | V22: -38000000 | W22: -84000000 | X22: -99000000 | Y22: -37000000 | Z22: 51000000 | AA22: -67000000 | AD22: -111000000 | AE22: -62000000 | AF22: -194000000 | AG22: -442000000 | AH22: -103000000 | AI22: -258000000
A23: Result from net monetary position in subsidiaries, associates and joint ventures (1) | B23: 35723963 | C23: 23224553 | D23: 33864616 | E23: 48904117 | F23: 53128572 | G23: 53805105 | H23: 48296390 | I23: 50497391 | J23: 78583480 | K23: 91759145 | L23: 1.295877e+08 | M23: 1.1012822e+08 | N23: 101000000 | O23: 100000000 | P23: 73000000 | Q23: -53000000 | R23: 285000000 | S23: 131000000 | T23: 69000000 | U23: 42000000 | V23: 84000000 | W23: 39000000 | X23: 12000000 | Y23: 55000000 | Z23: 128000000 | AA23: 45000000 | AC23: 1.8599318e+08 | AD23: 96000000 | AE23: 177000000 | AF23: 276000000 | AG23: 221000000 | AH23: 527000000 | AI23: 190000000
A24: Other comprehensive income for the period | B24: 7.0461202e+08 | C24: 8.2565654e+08 | D24: 6.3057826e+08 | E24: 7.6635202e+08 | F24: 7.4172141e+08 | G24: 3.71516e+08 | H24: 2.755487e+08 | I24: 3.7894445e+08 | J24: 7.1238204e+08 | K24: 1.1166742e+09 | L24: 1.6380805e+09 | M24: 1.8786233e+09 | N24: 16000000 | O24: -6000000 | P24: -24000000 | Q24: -207000000 | R24: 258000000 | S24: 102000000 | T24: 47000000 | U24: 17000000 | V24: 46000000 | W24: -45000000 | X24: -87000000 | Y24: 64000000 | Z24: 179000000 | AA24: -22000000 | AC24: 4.5987661e+09 | AD24: -15000000 | AE24: 115000000 | AF24: 82000000 | AG24: -221000000 | AH24: 424000000 | AI24: -22000000
A25: Total comprehensive income for the period | B25: 8.0802264e+08 | C25: -4.3403845e+08 | D25: 1.4811673e+08 | E25: 1.3040473e+09 | F25: 7.1633763e+08 | G25: -1.2089384e+08 | H25: 5.1189646e+08 | I25: 6.2511052e+08 | J25: 9.6016669e+08 | K25: 1.9140819e+09 | L25: 2.3180471e+09 | M25: 2.3575882e+09 | N25: 357000000 | O25: 374000000 | P25: -161000000 | Q25: -2068000000 | R25: 915000000 | S25: 637000000 | T25: 1532000000 | U25: -267000000 | V25: 36000000 | W25: 13000000 | X25: -285000000 | Y25: -585000000 | Z25: 588000000 | AA25: 1183000000 | AC25: 3.9053375e+09 | AD25: -1036000000 | AE25: 131000000 | AF25: 2316000000 | AG25: -1498000000 | AH25: 2817000000 | AI25: -821000000
A26: Shareholders of the parent company (del resultado) | B26: 1.0114734e+08 | C26: -1.2535038e+09 | D26: -4.8429131e+08 | E26: 5.5298405e+08 | F26: -23339067 | G26: -4.7915814e+08 | H26: 2.3150165e+08 | I26: 2.4726103e+08 | J26: 2.4952928e+08 | K26: 7.8913373e+08 | L26: 6.7785696e+08 | M26: 4.7815632e+08 | N26: 341000000 | O26: 335000000 | P26: -128000000 | Q26: -1860000000 | R26: 649000000 | S26: 519000000 | T26: 1470000000 | U26: -290000000 | V26: -16000000 | W26: 50000000 | X26: -206000000 | Y26: -654000000 | Z26: 404000000 | AA26: 1201000000 | AC26: -7.078045e+08 | AD26: -1004000000 | AE26: 26000000 | AF26: 2228000000 | AG26: -1312000000 | AH26: 2348000000 | AI26: -826000000
A27: Non-controlling interest (del resultado) | B27: 2263277.5 | C27: -6191239.2 | D27: 1829781.6 | E27: -15288787 | F27: -2044710.1 | G27: -13251702 | H27: 4846101.3 | I27: -1094956.2 | J27: -1744632.1 | K27: 8273921.4 | L27: 2109635.8 | M27: 808540.97 | N27: 177025.01 | O27: 45000000 | P27: -9000000 | Q27: -1000000 | R27: 8000000 | S27: 16000000 | T27: 15000000 | U27: 6000000 | V27: 6000000 | W27: 8000000 | X27: 8000000 | Y27: 5000000 | Z27: 5000000 | AA27: 4000000 | AC27: 14375883 | AD27: -17000000 | AE27: -10000000 | AF27: 6000000 | AG27: 35000000 | AH27: 45000000 | AI27: 27000000
A28: Shareholders of the parent company (de otro resultado integral) | B28: 6.9767565e+08 | C28: 8.209909e+08 | D28: 6.2383265e+08 | E28: 7.5700123e+08 | F28: 7.3281958e+08 | G28: 3.6324566e+08 | H28: 2.683773e+08 | I28: 3.7034407e+08 | J28: 7.0015086e+08 | K28: 1.1023644e+09 | L28: 1.6195438e+09 | M28: 1.8642054e+09 | N28: 14000000 | O28: -7000000 | P28: -24000000 | Q28: -173000000 | R28: 214000000 | S28: 85000000 | T28: 40000000 | U28: 14000000 | V28: 37000000 | W28: -34000000 | X28: -71000000 | Y28: 61000000 | Z28: 145000000 | AA28: -18000000 | AC28: 4.5634288e+09 | AD28: -13000000 | AE28: 98000000 | AF28: 70000000 | AG28: -190000000 | AH28: 353000000 | AI28: -7000000
A29: Non-controlling interest (de otro resultado integral) | B29: 6936375.7 | C29: 4665646.7 | D29: 6745612.9 | E29: 9350787.2 | F29: 8901831.8 | G29: 8270339.6 | H29: 7171406.8 | I29: 8600383.6 | J29: 12231184 | K29: 14309815 | L29: 18536765 | M29: 14417952 | N29: 2000000 | O29: 1000000 | P29: 0 | Q29: -34000000 | R29: 44000000 | S29: 17000000 | T29: 7000000 | U29: 3000000 | V29: 9000000 | W29: -11000000 | X29: -16000000 | Y29: 3000000 | Z29: 34000000 | AA29: -4000000 | AC29: 35337250 | AD29: -2000000 | AE29: 17000000 | AF29: 12000000 | AG29: -31000000 | AH29: 71000000 | AI29: -15000000
A30: Shareholders of the parent company (del resultado integral) | B30: 7.9882298e+08 | C30: -4.3251286e+08 | D30: 1.3954133e+08 | E30: 1.3099853e+09 | F30: 7.0948051e+08 | G30: -1.1591248e+08 | H30: 4.9987895e+08 | I30: 6.1760509e+08 | J30: 9.4968014e+08 | K30: 1.8914981e+09 | L30: 2.2974007e+09 | M30: 2.3423617e+09 | N30: 355000000 | O30: 328000000 | P30: -152000000 | Q30: -2033000000 | R30: 863000000 | S30: 604000000 | T30: 1510000000 | U30: -276000000 | V30: 21000000 | W30: 16000000 | X30: -277000000 | Y30: -593000000 | Z30: 549000000 | AA30: 1183000000 | AC30: 3.8556243e+09 | AD30: -1017000000 | AE30: 124000000 | AF30: 2298000000 | AG30: -1502000000 | AH30: 2701000000 | AI30: -833000000
A31: Non-controlling interest (del resultado integral) | B31: 9199653.2 | C31: -1525592.4 | D31: 8575394.6 | E31: -5937999.9 | F31: 6857121.7 | G31: -4981362.8 | H31: 12017508 | I31: 7505427.4 | J31: 10486552 | K31: 22583736 | L31: 20646401 | M31: 15226493 | N31: 2000000 | O31: 46000000 | P31: -9000000 | Q31: -35000000 | R31: 52000000 | S31: 33000000 | T31: 22000000 | U31: 9000000 | V31: 15000000 | W31: -3000000 | X31: -8000000 | Y31: 8000000 | Z31: 39000000 | AA31: 0 | AC31: 49713134 | AD31: -19000000 | AE31: 7000000 | AF31: 18000000 | AG31: 4000000 | AH31: 116000000 | AI31: 12000000
A32: Basic and diluted (2) | B32: 257753.12 | C32: -3194412.8 | D32: -1232917.8 | F32: -59420.857 | G32: -1220540.3 | H32: 589866.22 | J32: 634914.75 | K32: 2007782.3 | L32: 1724000.3 | N32: 870000 | O32: 860000 | P32: -330000 | R32: 1660000 | S32: 1320000 | T32: 3750000 | V32: -40000 | W32: 10000 | X32: -530000 | Z32: 1030000 | AA32: 310000 | AC32: -1804256.4 | AD32: -2560000 | AE32: 70000 | AF32: 5670000 | AG32: -3350000 | AH32: 5990000 | AI32: -2110000
A34: Líneas de presentaciones anteriores
A35: (Impairment) / Recovery of property, plant and equipment | AC35: -8.6066252e+08
A36: Recovery / (Impairment) of property, plant and equipment and intangible assets, net | AC36: -8.6066252e+08 | AD36: 97140482
A37: Impairment of property, plant and equipment and intangible assets | D37: -19185397 | AE37: -115000000 | AF37: -123000000 | AG37: -2288000000
A38: (Impairment) / Recovery of property, plant and equipment and intangible assets, net | AC38: -8.6066252e+08 | AD38: -53000000 | AE38: -115000000 | AF38: -123000000
A39: Financial loss | B39: -4.9065903e+08 | C39: -5.5810022e+08 | D39: -4.5588873e+08 | E39: -4.6945202e+08 | F39: -3.6514455e+08 | G39: -3.773063e+08 | H39: -3.07249e+08 | I39: -3.5037605e+08 | J39: -4.0367597e+08 | K39: -5.1678099e+08 | L39: -6.3455779e+08 | AC39: -1.9015429e+09 | AD39: -1.9673819e+09 | AE39: -1.3975448e+09
A40: Net loss for the year | C40: -1.259695e+09 | D40: -4.8246153e+08 | E40: 5.3769527e+08 | G40: -4.9240985e+08 | AC40: -6.9342862e+08 | AD40: -1.0069516e+09 | AE40: -8501085.8
A41: Translation differences from subsidiaries, associates and joint ventures | B41: -29520303 | C41: -33725961 | D41: -29890985 | E41: -34027865 | F41: -35754185 | G41: -14326740 | H41: -12871492 | I41: -17718383 | J41: -35971311 | K41: -58324364 | L41: -78779406 | AC41: -1.664237e+08 | AD41: -1.2762538e+08 | AE41: -79350481
A42: Translation differences from YPF (2) | B42: 6.9840836e+08 | C42: 8.3615795e+08 | D42: 6.2660463e+08 | E42: 7.5147576e+08 | F42: 7.2434702e+08 | G42: 3.3203764e+08 | H42: 2.401238e+08 | I42: 3.4616544e+08 | J42: 6.6976987e+08 | K42: 1.0832394e+09 | L42: 1.5872723e+09 | M42: 1.8510836e+09 | N42: 1.7937579e+09 | O42: 2.2692086e+09 | P42: 3.3811473e+09 | Q42: 1.1810036e+10 | AC42: 4.5791966e+09 | AD42: 2.9116197e+09 | AE42: 1.6142489e+09 | AF42: 5.470608e+09 | AG42: 2.4153373e+10 | AH42: 2.5635005e+09
A43: Gains / (losses) reclassified to profit or loss due to the acquisition and/or disposal of subsidiaries, associates and joint ventures | AI43: 46000000
A45: En bastardilla, los trimestres que la compañía no publica sueltos y salen por diferencia de acumulados. En marrón, los que la compañía presentó en pesos y acá vuelven a dólares por el tipo de cambio con el que se tradujeron. Ver Portada.

Sheet Balance
A1: Estado de situación patrimonial
A2: Consolidado, en dólares (la compañía reporta redondeado al millón)
A4: En dólares | B4: 2020Q1 | C4: 2020Q2 | D4: 2020Q3 | E4: 2020Q4 | F4: 2021Q1 | G4: 2021Q2 | H4: 2021Q3 | I4: 2021Q4 | J4: 2022Q1 | K4: 2022Q2 | L4: 2022Q3 | M4: 2022Q4 | N4: 2023Q1 | O4: 2023Q2 | P4: 2023Q3 | Q4: 2023Q4 | R4: 2024Q1 | S4: 2024Q2 | T4: 2024Q3 | U4: 2024Q4 | V4: 2025Q1 | W4: 2025Q2 | X4: 2025Q3 | Y4: 2025Q4 | Z4: 2026Q1 | AA4: 2026Q2 | AC4: FY19 | AD4: FY20 | AE4: FY21 | AF4: FY22 | AG4: FY23 | AH4: FY24 | AI4: FY25
A5: Intangible assets (no corriente) | E5: 465000000 | I5: 419000000 | J5: 4.1606046e+08 | K5: 4.1382772e+08 | L5: 4.1216981e+08 | M5: 384000000 | N5: 3.796527e+08 | O5: 3.7567428e+08 | P5: 3.7075011e+08 | Q5: 367000000 | R5: 377000000 | S5: 389000000 | T5: 407000000 | U5: 491000000 | V5: 594000000 | W5: 590000000 | X5: 1056000000 | Y5: 1068000000 | Z5: 1073000000 | AA5: 1079000000 | AC5: 6.2083371e+08 | AD5: 465000000 | AE5: 419000000 | AF5: 384000000 | AG5: 367000000 | AH5: 491000000 | AI5: 1068000000
A6: Property, plant and equipment (no corriente) | E6: 16413000000 | I6: 16003000000 | J6: 1.6101993e+10 | K6: 1.6312308e+10 | L6: 1.6643162e+10 | M6: 17510000000 | N6: 1.8061816e+10 | O6: 1.8581044e+10 | P6: 1.8640831e+10 | Q6: 17712000000 | R6: 16699000000 | S6: 17423000000 | T6: 18102000000 | U6: 18736000000 | V6: 18957000000 | W6: 19348000000 | X6: 19627000000 | Y6: 19085000000 | Z6: 19558000000 | AA6: 20433000000 | AC6: 1.7850885e+10 | AD6: 16413000000 | AE6: 16003000000 | AF6: 17510000000 | AG6: 17712000000 | AH6: 18736000000 | AI6: 19085000000
A7: Right-of-use assets (no corriente) | E7: 524000000 | I7: 519000000 | J7: 4.953697e+08 | K7: 5.2042334e+08 | L7: 5.0004796e+08 | M7: 541000000 | N7: 5.3983831e+08 | O7: 5.0854327e+08 | P7: 5.0333248e+08 | Q7: 631000000 | R7: 614000000 | S7: 565000000 | T7: 551000000 | U7: 743000000 | V7: 656000000 | W7: 672000000 | X7: 588000000 | Y7: 537000000 | Z7: 609000000 | AA7: 689000000 | AC7: 1.0251379e+09 | AD7: 524000000 | AE7: 519000000 | AF7: 541000000 | AG7: 631000000 | AH7: 743000000 | AI7: 537000000
A8: Investments in associates and joint ventures (no corriente) | E8: 1274000000 | I8: 1529000000 | J8: 1.6495386e+09 | K8: 1.714347e+09 | L8: 1.8678068e+09 | M8: 1905000000 | N8: 1.8054192e+09 | O8: 1.8093587e+09 | P8: 1.8355412e+09 | Q8: 1676000000 | R8: 1834000000 | S8: 1745000000 | T8: 1858000000 | U8: 1960000000 | V8: 2104000000 | W8: 1913000000 | X8: 1917000000 | Y8: 1610000000 | Z8: 1717000000 | AA8: 2056000000 | AC8: 1.1286519e+09 | AD8: 1274000000 | AE8: 1529000000 | AF8: 1905000000 | AG8: 1676000000 | AH8: 1960000000 | AI8: 1610000000
A9: Deferred income tax assets, net (no corriente) | E9: 33000000 | I9: 19000000 | J9: 14640182 | K9: 14455538 | L9: 6194923.5 | M9: 17000000 | N9: 16019041 | O9: 16019693 | P9: 16972394 | Q9: 18000000 | R9: 18000000 | S9: 19000000 | T9: 67000000 | U9: 330000000 | V9: 309000000 | W9: 231000000 | X9: 4000000 | Y9: 9000000 | Z9: 41000000 | AA9: 24000000 | AC9: 26433733 | AD9: 33000000 | AE9: 19000000 | AF9: 17000000 | AG9: 18000000 | AH9: 330000000 | AI9: 9000000
A10: Other receivables (no corriente) | E10: 175000000 | I10: 190000000 | J10: 54011010 | K10: 50147141 | L10: 45186900 | M10: 205000000 | N10: 2.0713996e+08 | O10: 2.1218676e+08 | P10: 2.0256314e+08 | Q10: 158000000 | R10: 177000000 | S10: 242000000 | T10: 290000000 | U10: 337000000 | V10: 438000000 | W10: 760000000 | X10: 774000000 | Y10: 648000000 | Z10: 636000000 | AA10: 797000000 | AC10: 1.9685867e+08 | AD10: 175000000 | AE10: 190000000 | AF10: 205000000 | AG10: 158000000 | AH10: 337000000 | AI10: 648000000
A11: Trade receivables (no corriente) | E11: 101000000 | I11: 43000000 | J11: 42397967 | K11: 40283832 | L11: 10050600 | M11: 6000000 | N11: 5278947.5 | O11: 4867582 | P11: 3245352.6 | Q11: 31000000 | R11: 31000000 | S11: 32000000 | T11: 31000000 | U11: 1000000 | V11: 2000000 | W11: 2000000 | X11: 1000000 | Y11: 5000000 | Z11: 6000000 | AA11: 6000000 | AC11: 2.5590459e+08 | AD11: 101000000 | AE11: 43000000 | AF11: 6000000 | AG11: 31000000 | AH11: 1000000 | AI11: 5000000
A12: Total non-current assets | E12: 18985000000 | I12: 18747000000 | J12: 1.8808832e+10 | K12: 1.9244602e+10 | L12: 1.9686012e+10 | M12: 20769000000 | N12: 2.118305e+10 | O12: 2.157262e+10 | P12: 2.1583963e+10 | Q12: 20601000000 | R12: 19757000000 | S12: 20422000000 | T12: 21306000000 | U12: 22598000000 | V12: 23060000000 | W12: 23516000000 | X12: 23967000000 | Y12: 22962000000 | Z12: 23640000000 | AA12: 25084000000 | AC12: 2.1104706e+10 | AD12: 18985000000 | AE12: 18747000000 | AF12: 20769000000 | AG12: 20601000000 | AH12: 22598000000 | AI12: 22962000000
A13: Assets held for sale | B13: 28346364 | E13: 6000000 | F13: 5870662.6 | H13: 1002632.2 | I13: 1000000 | J13: 1000037 | K13: 998310.66 | R13: 1858000000 | S13: 1940000000 | T13: 2072000000 | U13: 1537000000 | V13: 1534000000 | W13: 529000000 | X13: 489000000 | Y13: 1019000000 | Z13: 957000000 | AA13: 432000000 | AD13: 6000000 | AE13: 1000000 | AH13: 1537000000 | AI13: 1019000000
A14: Inventories | B14: 1.5213274e+09 | C14: 1.4388405e+09 | D14: 1.3689253e+09 | E14: 1191000000 | F14: 1.2104763e+09 | G14: 1.2977446e+09 | H14: 1.3975984e+09 | I14: 1500000000 | J14: 1.5090649e+09 | K14: 1.7217025e+09 | L14: 2.0027419e+09 | M14: 1738000000 | N14: 1.8669974e+09 | O14: 1.8944731e+09 | P14: 1.761338e+09 | Q14: 1683000000 | R14: 1574000000 | S14: 1577000000 | T14: 1713000000 | U14: 1546000000 | V14: 1617000000 | W14: 1482000000 | X14: 1529000000 | Y14: 1447000000 | Z14: 1460000000 | AA14: 1643000000 | AC14: 1.343879e+09 | AD14: 1191000000 | AE14: 1500000000 | AF14: 1738000000 | AG14: 1683000000 | AH14: 1546000000 | AI14: 1447000000
A15: Contract assets | B15: 11226591 | C15: 6279052 | D15: 5592701.7 | E15: 10000000 | F15: 4283409.4 | G15: 14639164 | H15: 10826402 | I15: 13000000 | J15: 15901490 | K15: 17314700 | L15: 1251224.9 | M15: 1000000 | N15: 8985238.6 | O15: 6335273.1 | P15: 7799130.9 | Q15: 10000000 | R15: 17000000 | S15: 21000000 | T15: 38000000 | U15: 30000000 | V15: 25000000 | W15: 21000000 | X15: 7000000 | Y15: 3000000 | Z15: 5000000 | AA15: 7000000 | AC15: 3389796.5 | AD15: 10000000 | AE15: 13000000 | AF15: 1000000 | AG15: 10000000 | AH15: 30000000 | AI15: 3000000
A16: Other receivables (corriente) | B16: 6.00436e+08 | C16: 4.6230586e+08 | D16: 3.8951985e+08 | E16: 409000000 | F16: 5.1552027e+08 | G16: 4.6243458e+08 | H16: 4.6194e+08 | I16: 616000000 | J16: 5.0628002e+08 | K16: 6.0316333e+08 | L16: 6.1433784e+08 | M16: 808000000 | N16: 6.4483231e+08 | O16: 7.3095312e+08 | P16: 4.8342327e+08 | Q16: 381000000 | R16: 444000000 | S16: 482000000 | T16: 498000000 | U16: 552000000 | V16: 634000000 | W16: 661000000 | X16: 671000000 | Y16: 1159000000 | Z16: 820000000 | AA16: 666000000 | AC16: 6.0435229e+08 | AD16: 409000000 | AE16: 616000000 | AF16: 808000000 | AG16: 381000000 | AH16: 552000000 | AI16: 1159000000
A17: Trade receivables (corriente) | B17: 1.7133923e+09 | C17: 1.4344935e+09 | D17: 1.461415e+09 | E17: 1287000000 | F17: 1.2914914e+09 | G17: 1.468096e+09 | H17: 1.6135492e+09 | I17: 1305000000 | J17: 1.3931147e+09 | K17: 1.5457283e+09 | L17: 1.6752066e+09 | M17: 1504000000 | N17: 1.3210219e+09 | O17: 1.3623257e+09 | P17: 1.4901654e+09 | Q17: 973000000 | R17: 1400000000 | S17: 1703000000 | T17: 1936000000 | U17: 1620000000 | V17: 1614000000 | W17: 1795000000 | X17: 1890000000 | Y17: 1654000000 | Z17: 1784000000 | AA17: 2087000000 | AC17: 1.9717094e+09 | AD17: 1287000000 | AE17: 1305000000 | AF17: 1504000000 | AG17: 973000000 | AH17: 1620000000 | AI17: 1654000000
A18: Investments in financial assets (corriente) | B18: 84836950 | C18: 1.1533851e+08 | D18: 2.2009775e+08 | E18: 344000000 | F18: 3.818866e+08 | G18: 3.9424387e+08 | H18: 4.0982338e+08 | I18: 497000000 | J18: 5.3319092e+08 | K18: 5.7508284e+08 | L18: 5.0100678e+08 | M18: 319000000 | N18: 2.8230143e+08 | O18: 3.0320703e+08 | P18: 1.8129694e+08 | Q18: 264000000 | R18: 290000000 | S18: 353000000 | T18: 318000000 | U18: 390000000 | V18: 292000000 | W18: 237000000 | X18: 217000000 | Y18: 262000000 | Z18: 366000000 | AA18: 1156000000 | AC18: 1.3976649e+08 | AD18: 344000000 | AE18: 497000000 | AF18: 319000000 | AG18: 264000000 | AH18: 390000000 | AI18: 262000000
A19: Cash and cash equivalents | B19: 1.0749538e+09 | C19: 1.1867834e+09 | D19: 7.8299136e+08 | E19: 650000000 | F19: 6.1181001e+08 | G19: 5.3989362e+08 | H19: 6.2282702e+08 | I19: 611000000 | J19: 7.9471413e+08 | K19: 6.6687951e+08 | L19: 8.3500904e+08 | M19: 773000000 | N19: 1.0160176e+09 | O19: 1.1678606e+09 | P19: 1.2934416e+09 | Q19: 1123000000 | R19: 1309000000 | S19: 1041000000 | T19: 877000000 | U19: 1118000000 | V19: 938000000 | W19: 774000000 | X19: 799000000 | Y19: 933000000 | Z19: 1326000000 | AA19: 1318000000 | AC19: 1.1037712e+09 | AD19: 650000000 | AE19: 611000000 | AF19: 773000000 | AG19: 1123000000 | AH19: 1118000000 | AI19: 933000000
A20: Total current assets | B20: 5.0345195e+09 | C20: 4.6440408e+09 | D20: 4.2285419e+09 | E20: 3897000000 | F20: 4.0213386e+09 | G20: 4.1770519e+09 | H20: 4.517567e+09 | I20: 4543000000 | J20: 4.7532662e+09 | K20: 5.1308695e+09 | L20: 5.6295534e+09 | M20: 5143000000 | N20: 5.1401558e+09 | O20: 5.4651548e+09 | P20: 5.2174643e+09 | Q20: 4434000000 | R20: 6892000000 | S20: 7117000000 | T20: 7452000000 | U20: 6793000000 | V20: 6654000000 | W20: 5499000000 | X20: 5602000000 | Y20: 6477000000 | Z20: 6718000000 | AA20: 7309000000 | AC20: 5.1668681e+09 | AD20: 3897000000 | AE20: 4543000000 | AF20: 5143000000 | AG20: 4434000000 | AH20: 6793000000 | AI20: 6477000000
A21: TOTAL ASSETS | B21: 2.582702e+10 | C21: 2.3824755e+10 | D21: 2.2878692e+10 | E21: 22882000000 | F21: 2.2670662e+10 | G21: 2.2598282e+10 | H21: 2.3023585e+10 | I21: 23290000000 | J21: 2.3562098e+10 | K21: 2.4375472e+10 | L21: 2.5315565e+10 | M21: 25912000000 | N21: 2.6323206e+10 | O21: 2.7037775e+10 | P21: 2.6801428e+10 | Q21: 25035000000 | R21: 26649000000 | S21: 27539000000 | T21: 28758000000 | U21: 29391000000 | V21: 29714000000 | W21: 29015000000 | X21: 29569000000 | Y21: 29439000000 | Z21: 30358000000 | AA21: 32393000000 | AC21: 2.6271574e+10 | AD21: 22882000000 | AE21: 23290000000 | AF21: 25912000000 | AG21: 25035000000 | AH21: 29391000000 | AI21: 29439000000
A22: Capital | Q22: 3919000000 | U22: 3922000000 | Y22: 3921000000 | Z22: 3921000000 | AA22: 3916000000 | AG22: 3919000000 | AH22: 3922000000 | AI22: 3921000000
A23: Treasury shares | Q23: 14000000 | U23: 11000000 | Y23: 12000000 | Z23: 12000000 | AA23: 17000000 | AG23: 14000000 | AH23: 11000000 | AI23: 12000000
A24: Share-based benefit plans | Q24: 1000000 | U24: 3000000 | Y24: 7000000 | Z24: 10000000 | AA24: 14000000 | AG24: 1000000 | AH24: 3000000 | AI24: 7000000
A25: Acquisition cost of treasury shares | Q25: -30000000 | U25: -28000000 | Y25: -35000000 | Z25: -35000000 | AA25: -62000000 | AG25: -30000000 | AH25: -28000000 | AI25: -35000000
A26: Share trading premiums | Q26: -40000000 | U26: -42000000 | Y26: -44000000 | Z26: -44000000 | AA26: -44000000 | AG26: -40000000 | AH26: -42000000 | AI26: -44000000
A27: Issuance premiums | Q27: 640000000 | U27: 640000000 | Y27: 640000000 | Z27: 640000000 | AA27: 640000000 | AG27: 640000000 | AH27: 640000000 | AI27: 640000000
A28: Legal reserve | Q28: 787000000 | U28: 787000000 | Y28: 787000000 | Z28: 787000000 | AA28: 787000000 | AG28: 787000000 | AH28: 787000000 | AI28: 787000000
A29: Reserve for investments | Q29: 5325000000 | U29: 4236000000 | Y29: 6587000000 | Z29: 6587000000 | AA29: 5802000000 | AG29: 5325000000 | AH29: 4236000000 | AI29: 6587000000
A30: Reserve for purchase of treasury shares | Q30: 35000000 | U30: 36000000 | Y30: 33000000 | Z30: 33000000 | AA30: 27000000 | AG30: 35000000 | AH30: 36000000 | AI30: 33000000
A31: Other comprehensive income | Q31: -684000000 | U31: -331000000 | Y31: -338000000 | Z31: -193000000 | AA31: -211000000 | AG31: -684000000 | AH31: -331000000 | AI31: -338000000
A32: Unappropriated retained earnings and losses | Q32: -1244000000 | U32: 2418000000 | Y32: -756000000 | Z32: -352000000 | AA32: 1640000000 | AG32: -1244000000 | AH32: 2418000000 | AI32: -756000000
A33: Shareholders' equity attributable to shareholders of the parent company | B33: 9.2013416e+09 | C33: 7.9936736e+09 | D33: 7.5202407e+09 | E33: 8057000000 | F33: 8.0462431e+09 | G33: 7.6210066e+09 | H33: 7.8772457e+09 | I33: 8184000000 | J33: 8.4795123e+09 | K33: 9.2989443e+09 | L33: 1.002867e+10 | M33: 10454000000 | N33: 1.0822931e+10 | O33: 1.1151228e+10 | P33: 1.0963978e+10 | Q33: 8949000000 | R33: 9813000000 | S33: 10418000000 | T33: 11926000000 | U33: 11652000000 | V33: 11675000000 | W33: 11694000000 | X33: 11412000000 | Y33: 10814000000 | Z33: 11366000000 | AA33: 12526000000 | AC33: 9.0597571e+09 | AD33: 8057000000 | AE33: 8184000000 | AF33: 10454000000 | AG33: 8949000000 | AH33: 11652000000 | AI33: 10814000000
A34: Non-controlling interest | B34: 95083935 | C34: 85406472 | D34: 87172627 | E34: 74000000 | F34: 73622457 | G34: 65871013 | H34: 75673412 | I34: 80000000 | J34: 84183299 | K34: 95901715 | L34: 1.0068961e+08 | M34: 98000000 | N34: 1.0067399e+08 | O34: 1.4681205e+08 | P34: 1.3620768e+08 | Q34: 102000000 | R34: 154000000 | S34: 187000000 | T34: 209000000 | U34: 218000000 | V34: 233000000 | W34: 230000000 | X34: 222000000 | Y34: 230000000 | Z34: 269000000 | AA34: 269000000 | AC34: 92676702 | AD34: 74000000 | AE34: 80000000 | AF34: 98000000 | AG34: 102000000 | AH34: 218000000 | AI34: 230000000
A35: TOTAL SHAREHOLDERS' EQUITY | B35: 9.2964256e+09 | C35: 8.0790801e+09 | D35: 7.6074133e+09 | E35: 8131000000 | F35: 8.1198656e+09 | G35: 7.6868777e+09 | H35: 7.9529191e+09 | I35: 8264000000 | J35: 8.5636956e+09 | K35: 9.394846e+09 | L35: 1.0129359e+10 | M35: 10552000000 | N35: 1.0923605e+10 | O35: 1.129804e+10 | P35: 1.1100186e+10 | Q35: 9051000000 | R35: 9967000000 | S35: 10605000000 | T35: 12135000000 | U35: 11870000000 | V35: 11908000000 | W35: 11924000000 | X35: 11634000000 | Y35: 11044000000 | Z35: 11635000000 | AA35: 12795000000 | AC35: 9.1524338e+09 | AD35: 8131000000 | AE35: 8264000000 | AF35: 10552000000 | AG35: 9051000000 | AH35: 11870000000 | AI35: 11044000000
A36: Provisions (no corriente) | E36: 2219000000 | I36: 2519000000 | J36: 2.4990295e+09 | K36: 2.5365077e+09 | L36: 2.5511388e+09 | M36: 2571000000 | N36: 2.165174e+09 | O36: 2.1596919e+09 | P36: 2.1788658e+09 | Q36: 2660000000 | R36: 686000000 | S36: 771000000 | T36: 756000000 | U36: 1084000000 | V36: 1079000000 | W36: 1093000000 | X36: 1123000000 | Y36: 610000000 | Z36: 639000000 | AA36: 661000000 | AC36: 2.4174092e+09 | AD36: 2219000000 | AE36: 2519000000 | AF36: 2571000000 | AG36: 2660000000 | AH36: 1084000000 | AI36: 610000000
A37: Contract liabilities (no corriente) | Q37: 34000000 | R37: 33000000 | S37: 32000000 | T37: 31000000 | U37: 114000000 | V37: 149000000 | W37: 167000000 | X37: 166000000 | Y37: 180000000 | Z37: 212000000 | AA37: 236000000 | AC37: 4909360.4 | AG37: 34000000 | AH37: 114000000 | AI37: 180000000
A38: Deferred income tax liabilities, net (no corriente) | E38: 1423000000 | I38: 1805000000 | J38: 1.6637553e+09 | K38: 1.3320739e+09 | L38: 7.9697588e+08 | M38: 1733000000 | N38: 1.5841733e+09 | O38: 1.3853053e+09 | P38: 1.0350304e+09 | Q38: 1242000000 | R38: 1066000000 | S38: 927000000 | T38: 92000000 | U38: 90000000 | V38: 95000000 | W38: 104000000 | X38: 389000000 | Y38: 373000000 | Z38: 511000000 | AA38: 446000000 | AC38: 1.6236123e+09 | AD38: 1423000000 | AE38: 1805000000 | AF38: 1733000000 | AG38: 1242000000 | AH38: 90000000 | AI38: 373000000
A39: Income tax liability (no corriente) | E39: 42000000 | I39: 29000000 | J39: 48632432 | K39: 40954696 | L39: 33035058 | M39: 26000000 | N39: 20703447 | O39: 15801100 | P39: 10793083 | Q39: 4000000 | R39: 4000000 | S39: 3000000 | T39: 3000000 | U39: 2000000 | V39: 2000000 | W39: 2000000 | X39: 1000000 | Y39: 830000000 | Z39: 865000000 | AA39: 801000000 | AC39: 56557836 | AD39: 42000000 | AE39: 29000000 | AF39: 26000000 | AG39: 4000000 | AH39: 2000000 | AI39: 830000000
A40: Taxes payable (no corriente) | E40: 3000000 | I40: 2000000 | J40: 1828896.6 | K40: 1613270 | L40: 1319226.3 | M40: 1000000 | N40: 848659.14 | O40: 636259.72 | P40: 462805.57 | Q40: 178222.63 | U40: 217269.99 | Y40: 18000000 | Z40: 19000000 | AA40: 12000000 | AC40: 23845465 | AD40: 3000000 | AE40: 2000000 | AF40: 1000000 | AG40: 178222.63 | AH40: 217269.99 | AI40: 18000000
A41: Salaries and social security (no corriente) | E41: 46000000 | I41: 32000000 | J41: 20712479 | K41: 13481187 | L41: 3780875.3 | M41: 1000000 | N41: 2095277.1 | O41: 11710.302 | P41: 1217007.2 | Q41: 457933.14 | S41: 4000000 | T41: 8000000 | U41: 34000000 | V41: 33000000 | W41: 34000000 | X41: 26000000 | Y41: 63000000 | Z41: 98000000 | AA41: 134000000 | AD41: 46000000 | AE41: 32000000 | AF41: 1000000 | AG41: 457933.14 | AH41: 34000000 | AI41: 63000000
A42: Lease liabilities (no corriente) | E42: 288000000 | I42: 276000000 | J42: 2.4062153e+08 | K42: 2.5892185e+08 | L42: 2.4695372e+08 | M42: 272000000 | N42: 2.6778312e+08 | O42: 2.4500683e+08 | P42: 2.446356e+08 | Q42: 325000000 | R42: 312000000 | S42: 292000000 | T42: 290000000 | U42: 406000000 | V42: 344000000 | W42: 364000000 | X42: 314000000 | Y42: 273000000 | Z42: 332000000 | AA42: 410000000 | AC42: 6.7446931e+08 | AD42: 288000000 | AE42: 276000000 | AF42: 272000000 | AG42: 325000000 | AH42: 406000000 | AI42: 273000000
A43: Loans (no corriente) | E43: 6277000000 | I43: 6534000000 | J43: 6.7136451e+09 | K43: 6.315433e+09 | L43: 6.1397064e+09 | M43: 5948000000 | N43: 6.2388386e+09 | O43: 6.3065907e+09 | P43: 6.5961193e+09 | Q43: 6682000000 | R43: 7240000000 | S43: 7200000000 | T43: 6869000000 | U43: 7035000000 | V43: 7543000000 | W43: 7592000000 | X43: 7958000000 | Y43: 8226000000 | Z43: 8526000000 | AA43: 8521000000 | AC43: 7.0075443e+09 | AD43: 6277000000 | AE43: 6534000000 | AF43: 5948000000 | AG43: 6682000000 | AH43: 7035000000 | AI43: 8226000000
A44: Other liabilities (no corriente) | E44: 35000000 | I44: 9000000 | J44: 8414726.2 | K44: 8417755.5 | L44: 8425367.9 | M44: 19000000 | N44: 99427371 | O44: 1.0399919e+08 | P44: 1.0755659e+08 | Q44: 112000000 | R44: 74000000 | S44: 76000000 | T44: 71000000 | U44: 74000000 | V44: 136000000 | W44: 384000000 | X44: 452000000 | Y44: 373000000 | Z44: 347000000 | AA44: 547000000 | AC44: 11739049 | AD44: 35000000 | AE44: 9000000 | AF44: 19000000 | AG44: 112000000 | AH44: 74000000 | AI44: 373000000
A45: Accounts payable (no corriente) | E45: 8000000 | I45: 9000000 | J45: 8315623.4 | K45: 7890647.4 | L45: 8058160.6 | M45: 6000000 | N45: 7153669.1 | O45: 6717809.7 | P45: 5250843.5 | Q45: 5000000 | R45: 5000000 | S45: 5000000 | T45: 6000000 | U45: 6000000 | V45: 6000000 | W45: 5000000 | X45: 6000000 | Y45: 6000000 | Z45: 6000000 | AA45: 5000000 | AC45: 41161814 | AD45: 8000000 | AE45: 9000000 | AF45: 6000000 | AG45: 5000000 | AH45: 6000000 | AI45: 6000000
A46: Total non-current liabilities | E46: 10341000000 | I46: 11215000000 | J46: 1.1204956e+10 | K46: 1.0515294e+10 | L46: 9.7893935e+09 | M46: 10577000000 | N46: 1.0386197e+10 | O46: 1.0223761e+10 | P46: 1.0179931e+10 | Q46: 11064000000 | R46: 9420000000 | S46: 9310000000 | T46: 8126000000 | U46: 8845000000 | V46: 9387000000 | W46: 9745000000 | X46: 10435000000 | Y46: 10952000000 | Z46: 11555000000 | AA46: 11773000000 | AC46: 1.1861249e+10 | AD46: 10341000000 | AE46: 11215000000 | AF46: 10577000000 | AG46: 11064000000 | AH46: 8845000000 | AI46: 10952000000
A47: Liabilities directly associated with assets held for sale | R47: 2039000000 | S47: 2085000000 | T47: 2204000000 | U47: 2136000000 | V47: 2087000000 | W47: 945000000 | X47: 914000000 | Y47: 1181000000 | Z47: 1060000000 | AA47: 981000000 | AH47: 2136000000 | AI47: 1181000000
A48: Provisions (corriente) | B48: 89284049 | C48: 88787500 | D48: 86476821 | E48: 73000000 | F48: 72317865 | G48: 77542638 | H48: 87269511 | I48: 188000000 | J48: 1.7354697e+08 | K48: 1.8091785e+08 | L48: 1.7817035e+08 | M48: 199000000 | N48: 4.9359358e+08 | O48: 4.956229e+08 | P48: 1.9170435e+08 | Q48: 181000000 | R48: 207000000 | S48: 201000000 | T48: 186000000 | U48: 116000000 | V48: 115000000 | W48: 116000000 | X48: 132000000 | Y48: 229000000 | Z48: 248000000 | AA48: 236000000 | AC48: 91173837 | AD48: 73000000 | AE48: 188000000 | AF48: 199000000 | AG48: 181000000 | AH48: 116000000 | AI48: 229000000
A49: Contract liabilities (corriente) | B49: 1.1924754e+08 | C49: 86443510 | D49: 1.1482105e+08 | E49: 81000000 | F49: 63044393 | G49: 77657578 | H49: 1.7647339e+08 | I49: 130000000 | J49: 2.8142484e+08 | K49: 2.3167196e+08 | L49: 2.5406666e+08 | M49: 77000000 | N49: 94373773 | O49: 1.6603256e+08 | P49: 1.3779322e+08 | Q49: 69000000 | R49: 54000000 | S49: 68000000 | T49: 77000000 | U49: 73000000 | V49: 83000000 | W49: 114000000 | X49: 117000000 | Y49: 117000000 | Z49: 145000000 | AA49: 192000000 | AC49: 1.2363573e+08 | AD49: 81000000 | AE49: 130000000 | AF49: 77000000 | AG49: 69000000 | AH49: 73000000 | AI49: 117000000
A50: Income tax liability (corriente) | B50: 31751659 | C50: 19092864 | D50: 13758571 | E50: 9000000 | F50: 10284531 | G50: 10114711 | H50: 16528240 | I50: 13000000 | J50: 1.0981488e+08 | K50: 4.1847586e+08 | L50: 9.6131476e+08 | M50: 27000000 | N50: 25776223 | O50: 30903486 | P50: 26854150 | Q50: 31000000 | R50: 45000000 | S50: 38000000 | T50: 93000000 | U50: 126000000 | V50: 138000000 | W50: 28000000 | X50: 20000000 | Y50: 73000000 | Z50: 194000000 | AA50: 781000000 | AC50: 32795864 | AD50: 9000000 | AE50: 13000000 | AF50: 27000000 | AG50: 31000000 | AH50: 126000000 | AI50: 73000000
A51: Taxes payable (corriente) | B51: 1.8825531e+08 | C51: 1.9676731e+08 | D51: 2.1015955e+08 | E51: 188000000 | F51: 2.6821318e+08 | G51: 2.0713215e+08 | H51: 1.911179e+08 | I51: 143000000 | J51: 3.1220076e+08 | K51: 2.3568917e+08 | L51: 2.4634171e+08 | M51: 173000000 | N51: 1.4694749e+08 | O51: 1.7965164e+08 | P51: 1.5872803e+08 | Q51: 139000000 | R51: 248000000 | S51: 279000000 | T51: 260000000 | U51: 247000000 | V51: 226000000 | W51: 282000000 | X51: 248000000 | Y51: 217000000 | Z51: 350000000 | AA51: 401000000 | AC51: 1.909808e+08 | AD51: 188000000 | AE51: 143000000 | AF51: 173000000 | AG51: 139000000 | AH51: 247000000 | AI51: 217000000
A52: Salaries and social security (corriente) | B52: 1.31065e+08 | C52: 1.321158e+08 | D52: 1.6306795e+08 | E52: 178000000 | F52: 1.4969102e+08 | G52: 1.7512662e+08 | H52: 1.9905794e+08 | I52: 229000000 | J52: 1.9795328e+08 | K52: 2.2174476e+08 | L52: 2.4562769e+08 | M52: 297000000 | N52: 2.1216479e+08 | O52: 2.1854155e+08 | P52: 2.5110916e+08 | Q52: 210000000 | R52: 175000000 | S52: 268000000 | T52: 389000000 | U52: 412000000 | V52: 428000000 | W52: 289000000 | X52: 326000000 | Y52: 336000000 | Z52: 371000000 | AA52: 300000000 | AC52: 1.7039154e+08 | AD52: 178000000 | AE52: 229000000 | AF52: 297000000 | AG52: 210000000 | AH52: 412000000 | AI52: 336000000
A53: Lease liabilities (corriente) | B53: 3.4762003e+08 | C53: 3.5408455e+08 | D53: 3.5253713e+08 | E53: 263000000 | F53: 2.5020981e+08 | G53: 2.3381911e+08 | H53: 2.2885333e+08 | I53: 266000000 | J53: 2.7892925e+08 | K53: 2.8537309e+08 | L53: 2.7509268e+08 | M53: 294000000 | N53: 2.9835403e+08 | O53: 2.9117665e+08 | P53: 2.9000197e+08 | Q53: 341000000 | R53: 336000000 | S53: 311000000 | T53: 296000000 | U53: 370000000 | V53: 349000000 | W53: 345000000 | X53: 311000000 | Y53: 298000000 | Z53: 308000000 | AA53: 304000000 | AC53: 3.5716432e+08 | AD53: 263000000 | AE53: 266000000 | AF53: 294000000 | AG53: 341000000 | AH53: 370000000 | AI53: 298000000
A54: Loans (corriente) | B54: 2.7996038e+09 | C54: 2.7818757e+09 | D54: 1.8903069e+09 | E54: 1793000000 | F54: 1.1859282e+09 | G54: 1.2733042e+09 | H54: 1.0910866e+09 | I54: 845000000 | J54: 5.2210943e+08 | K54: 7.6541676e+08 | L54: 8.5754469e+08 | M54: 1140000000 | N54: 1.1098688e+09 | O54: 1.4849599e+09 | P54: 1.5430452e+09 | Q54: 1508000000 | R54: 1559000000 | S54: 1651000000 | T54: 1832000000 | U54: 1907000000 | V54: 2023000000 | W54: 2252000000 | X54: 2653000000 | Y54: 2355000000 | Z54: 1591000000 | AA54: 1607000000 | AC54: 1.7885602e+09 | AD54: 1793000000 | AE54: 845000000 | AF54: 1140000000 | AG54: 1508000000 | AH54: 1907000000 | AI54: 2355000000
A55: Other liabilities (corriente) | B55: 21395829 | C55: 21237970 | D55: 20322775 | E55: 108000000 | F55: 98790205 | G55: 87061752 | H55: 52045726 | I55: 34000000 | J55: 15793378 | K55: 11620336 | L55: 10145802 | M55: 12000000 | N55: 56303979 | O55: 91086629 | P55: 1.1542999e+08 | Q55: 122000000 | R55: 117000000 | S55: 123000000 | T55: 181000000 | U55: 410000000 | V55: 260000000 | W55: 321000000 | X55: 372000000 | Y55: 399000000 | Z55: 534000000 | AA55: 737000000 | AC55: 21875041 | AD55: 108000000 | AE55: 34000000 | AF55: 12000000 | AG55: 122000000 | AH55: 410000000 | AI55: 399000000
A56: Accounts payable (corriente) | B56: 2.1052812e+09 | C56: 1.6584511e+09 | D56: 1.5654051e+09 | E56: 1717000000 | F56: 1.8366259e+09 | G56: 1.8925586e+09 | H56: 1.8365183e+09 | I56: 1963000000 | J56: 1.9016741e+09 | K56: 2.114422e+09 | L56: 2.3685076e+09 | M56: 2564000000 | N56: 2.5760209e+09 | O56: 2.5579983e+09 | P56: 2.8066444e+09 | Q56: 2319000000 | R56: 2482000000 | S56: 2600000000 | T56: 2979000000 | U56: 2879000000 | V56: 2710000000 | W56: 2654000000 | X56: 2407000000 | Y56: 2238000000 | Z56: 2367000000 | AA56: 2286000000 | AC56: 2.4813143e+09 | AD56: 1717000000 | AE56: 1963000000 | AF56: 2564000000 | AG56: 2319000000 | AH56: 2879000000 | AI56: 2238000000
A57: Total current liabilities | B57: 5.8335044e+09 | C57: 5.3388563e+09 | D57: 4.4168558e+09 | E57: 4410000000 | F57: 3.9351051e+09 | G57: 4.0343174e+09 | H57: 3.878951e+09 | I57: 3811000000 | J57: 3.7934468e+09 | K57: 4.4653318e+09 | L57: 5.3968119e+09 | M57: 4783000000 | N57: 5.0134035e+09 | O57: 5.5159736e+09 | P57: 5.5213105e+09 | Q57: 4920000000 | R57: 7262000000 | S57: 7624000000 | T57: 8497000000 | U57: 8676000000 | V57: 8419000000 | W57: 7346000000 | X57: 7500000000 | Y57: 7443000000 | Z57: 7168000000 | AA57: 7825000000 | AC57: 5.2578916e+09 | AD57: 4410000000 | AE57: 3811000000 | AF57: 4783000000 | AG57: 4920000000 | AH57: 8676000000 | AI57: 7443000000
A58: TOTAL LIABILITIES | B58: 1.6530595e+10 | C58: 1.5745675e+10 | D58: 1.5271279e+10 | E58: 14751000000 | F58: 1.4550796e+10 | G58: 1.4911404e+10 | H58: 1.5070666e+10 | I58: 15026000000 | J58: 1.4998402e+10 | K58: 1.4980626e+10 | L58: 1.5186205e+10 | M58: 15360000000 | N58: 1.5399601e+10 | O58: 1.5739734e+10 | P58: 1.5701242e+10 | Q58: 15984000000 | R58: 16682000000 | S58: 16934000000 | T58: 16623000000 | U58: 17521000000 | V58: 17806000000 | W58: 17091000000 | X58: 17935000000 | Y58: 18395000000 | Z58: 18723000000 | AA58: 19598000000 | AC58: 1.711914e+10 | AD58: 14751000000 | AE58: 15026000000 | AF58: 15360000000 | AG58: 15984000000 | AH58: 17521000000 | AI58: 18395000000
A59: TOTAL LIABILITIES AND SHAREHOLDERS' EQUITY | B59: 2.582702e+10 | C59: 2.3824755e+10 | D59: 2.2878692e+10 | E59: 22882000000 | F59: 2.2670662e+10 | G59: 2.2598282e+10 | H59: 2.3023585e+10 | I59: 23290000000 | J59: 2.3562098e+10 | K59: 2.4375472e+10 | L59: 2.5315565e+10 | M59: 25912000000 | N59: 2.6323206e+10 | O59: 2.7037775e+10 | P59: 2.6801428e+10 | Q59: 25035000000 | R59: 26649000000 | S59: 27539000000 | T59: 28758000000 | U59: 29391000000 | V59: 29714000000 | W59: 29015000000 | X59: 29569000000 | Y59: 29439000000 | Z59: 30358000000 | AA59: 32393000000 | AC59: 2.6271574e+10 | AD59: 22882000000 | AE59: 23290000000 | AF59: 25912000000 | AG59: 25035000000 | AH59: 29391000000 | AI59: 29439000000
A61: Líneas de presentaciones anteriores
A62: Intangible assets | B62: 6.115382e+08 | C62: 6.0898281e+08 | D62: 5.8064321e+08 | E62: 4.6492784e+08 | F62: 4.5949893e+08 | G62: 4.5765934e+08 | H62: 4.3748185e+08 | AC62: 6.2083371e+08 | AD62: 4.6492784e+08
A63: Property, plant and equipment | B63: 1.7656333e+10 | C63: 1.6264464e+10 | D63: 1.573949e+10 | E63: 1.6395626e+10 | F63: 1.6114719e+10 | G63: 1.5871936e+10 | H63: 1.5825243e+10 | AC63: 1.7850885e+10 | AD63: 1.6395626e+10
A64: Right-of-use assets | B64: 9.674771e+08 | C64: 8.8545998e+08 | D64: 8.0630741e+08 | E64: 5.2390103e+08 | F64: 5.2601137e+08 | G64: 4.8793034e+08 | H64: 4.6636576e+08 | AC64: 1.0251379e+09 | AD64: 5.2390103e+08
A65: Investments in associates and joint ventures | B65: 1.1538354e+09 | C65: 1.1533851e+09 | D65: 1.2097696e+09 | E65: 1.2730221e+09 | F65: 1.3009932e+09 | G65: 1.3117673e+09 | H65: 1.3687043e+09 | AC65: 1.1286519e+09 | AD65: 1.2730221e+09
A66: Deferred income tax assets, net | B66: 28595152 | C66: 33128392 | D66: 35131619 | E66: 31245566 | F66: 29244597 | G66: 26457076 | H66: 21419870 | AC66: 26433733 | AD66: 31245566
A67: Other receivables | B67: 1.9848674e+08 | C67: 1.6059883e+08 | D67: 1.6757099e+08 | E67: 1.7419789e+08 | F67: 1.6255212e+08 | G67: 1.7433248e+08 | H67: 2.0049606e+08 | AC67: 1.9685867e+08 | AD67: 1.7419789e+08
A68: Trade receivables | B68: 1.762357e+08 | C68: 74695148 | D68: 1.11237e+08 | E68: 1.0139061e+08 | F68: 56304003 | G68: 55129357 | H68: 42616932 | AC68: 2.5590459e+08 | AD68: 1.0139061e+08
A69: Investments in financial assets (no corriente) | I69: 25000000 | J69: 34821110 | K69: 1.7880942e+08 | L69: 2.0139281e+08 | M69: 201000000 | N69: 1.6788587e+08 | O69: 64925815 | P69: 10727376 | Q69: 8000000 | R69: 7000000 | S69: 7000000 | AE69: 25000000 | AF69: 201000000 | AG69: 8000000
A70: Investment in financial assets | G70: 36017986 | H70: 1.4369036e+08
A71: Total noncurrent assets | B71: 2.0792501e+10 | C71: 1.9180714e+10 | D71: 1.865015e+10 | E71: 1.8964311e+10 | F71: 1.8649323e+10 | G71: 1.842123e+10 | H71: 1.8506018e+10 | AC71: 2.1104706e+10 | AD71: 1.8964311e+10
A72: Shareholders' contributions | B72: 1.6662624e+08 | C72: 1.5429137e+08 | D72: 1.4135356e+08 | E72: 4532000000 | F72: 1.1379301e+08 | G72: 1.1063488e+08 | H72: 1.0590429e+08 | I72: 4535000000 | J72: 95093613 | K72: 84465068 | L72: 65016096 | M72: 4507000000 | N72: 30738722 | O72: 25505037 | P72: 13769894 | Q72: 4504000000 | R72: 4505000000 | S72: 4506000000 | T72: 4504000000 | U72: 4506000000 | V72: 4508000000 | W72: 4511000000 | X72: 4506000000 | AC72: 1.7653659e+08 | AD72: 4532000000 | AE72: 4535000000 | AF72: 4507000000 | AG72: 4504000000 | AH72: 4506000000
A73: Retained earnings | E73: 3525000000 | I73: 3649000000 | M73: 5947000000 | N73: 1.0792192e+10 | O73: 1.1125723e+10 | P73: 1.0950208e+10 | Q73: 4445000000 | R73: 5308000000 | S73: 5912000000 | T73: 7422000000 | U73: 7146000000 | V73: 7167000000 | W73: 7183000000 | X73: 6906000000 | AD73: 3525000000 | AE73: 3649000000 | AF73: 5947000000 | AG73: 4445000000 | AH73: 7146000000
A74: Reserves, other comprehensive income and retained earnings | B74: 9.0347154e+09 | C74: 7.8393822e+09 | D74: 7.3788872e+09 | E74: 7.9254277e+09 | F74: 7.9324501e+09 | G74: 7.5103718e+09 | H74: 7.7713414e+09 | I74: 8.0772249e+09 | J74: 8.3844187e+09 | K74: 9.2144793e+09 | L74: 9.9636538e+09 | AC74: 8.8832205e+09 | AD74: 7.9254277e+09 | AE74: 8.0772249e+09
A75: Reserve for future dividends | Q75: 226000000 | AG75: 226000000
A76: Provisions | B76: 2.4311011e+09 | C76: 2.4548536e+09 | D76: 2.5154029e+09 | E76: 2.2164029e+09 | F76: 2.2381031e+09 | G76: 2.2899477e+09 | H76: 2.3092442e+09 | AC76: 2.4174092e+09 | AD76: 2.2164029e+09
A77: Contract liabilities | AC77: 4909360.4
A78: Deferred income tax liabilities, net | B78: 1.5026372e+09 | C78: 1.3679526e+09 | D78: 1.388526e+09 | E78: 1.4215485e+09 | F78: 1.4148732e+09 | G78: 2.0526699e+09 | H78: 2.1368624e+09 | AC78: 1.6236123e+09 | AD78: 1.4215485e+09
A79: Income tax liability | B79: 49011376 | C79: 41438902 | D79: 35210389 | E79: 42441201 | F79: 37420038 | G79: 34617809 | H79: 32246272 | AC79: 56557836 | AD79: 42441201
A80: Taxes payable | B80: 14569689 | C80: 3395234 | D80: 262568.15 | E80: 2555266.9 | F80: 2185191.1 | G80: 2027121.9 | H80: 2076157.6 | AC80: 23845465 | AD80: 2555266.9
A81: Salaries and social security | D81: 38374336 | E81: 45875955 | F81: 45693324 | G81: 46331230 | H81: 36074504 | AD81: 45875955
A82: Lease liabilities | B82: 6.4537347e+08 | C82: 5.8970527e+08 | D82: 5.3486446e+08 | E82: 2.8728331e+08 | F82: 2.9774044e+08 | G82: 2.766499e+08 | H82: 2.6016786e+08 | AC82: 6.7446931e+08 | AD82: 2.8728331e+08
A83: Loans | B83: 6.0069257e+09 | C83: 5.9036727e+09 | D83: 6.3069789e+09 | E83: 6.270209e+09 | F83: 6.553725e+09 | G83: 6.1543421e+09 | H83: 6.3904636e+09 | AC83: 7.0075443e+09 | AD83: 6.270209e+09
A84: Other liabilities | B84: 10806760 | C84: 10753942 | D84: 10752166 | E84: 35191374 | F84: 15535513 | G84: 9435521.1 | H84: 9428793.6 | AC84: 11739049 | AD84: 35191374
A85: Accounts payable | B85: 36665236 | C85: 35046202 | D85: 24051243 | E85: 8438323.3 | F85: 10414990 | G85: 11065578 | H85: 15150886 | AC85: 41161814 | AD85: 8438323.3
A86: Total noncurrent liabilities | B86: 1.069709e+10 | C86: 1.0406818e+10 | D86: 1.0854423e+10 | E86: 1.0329946e+10 | F86: 1.0615691e+10 | G86: 1.0877087e+10 | H86: 1.1191715e+10 | AC86: 1.1861249e+10 | AD86: 1.0329946e+10
A88: En bastardilla, los trimestres que la compañía no publica sueltos y salen por diferencia de acumulados. En marrón, los que la compañía presentó en pesos y acá vuelven a dólares por el tipo de cambio con el que se tradujeron. Ver Portada.

Sheet Flujo de efectivo
A1: Estado de flujo de efectivo
A2: Consolidado, en dólares (la compañía reporta redondeado al millón)
A4: En dólares | B4: 2020Q1 | C4: 2020Q2 | D4: 2020Q3 | E4: 2020Q4 | F4: 2021Q1 | G4: 2021Q2 | H4: 2021Q3 | I4: 2021Q4 | J4: 2022Q1 | K4: 2022Q2 | L4: 2022Q3 | M4: 2022Q4 | N4: 2023Q1 | O4: 2023Q2 | P4: 2023Q3 | Q4: 2023Q4 | R4: 2024Q1 | S4: 2024Q2 | T4: 2024Q3 | U4: 2024Q4 | V4: 2025Q1 | W4: 2025Q2 | X4: 2025Q3 | Y4: 2025Q4 | Z4: 2026Q1 | AA4: 2026Q2 | AC4: FY19 | AD4: FY20 | AE4: FY21 | AF4: FY22 | AG4: FY23 | AH4: FY24 | AI4: FY25
A5: Net profit | B5: 1.0341061e+08 | I5: 2.4616607e+08 | J5: 2.4778465e+08 | K5: 7.9740766e+08 | L5: 6.7996659e+08 | M5: 4.7896486e+08 | N5: 341000000 | O5: 380000000 | P5: -137000000 | Q5: -1861000000 | R5: 657000000 | S5: 535000000 | T5: 1485000000 | U5: -284000000 | V5: -10000000 | W5: 58000000 | X5: -198000000 | Y5: -649000000 | Z5: 409000000 | AA5: 1205000000 | AE5: 16000000 | AF5: 2234000000 | AG5: -1277000000 | AH5: 2393000000 | AI5: -799000000
A6: Income from equity interests in associates and joint ventures | B6: -23121252 | C6: -34066627 | D6: -61857544 | E6: -62755283 | F6: -57794126 | G6: -15316626 | H6: -44839298 | I6: -1.5990343e+08 | J6: -1.1470487e+08 | K6: -1.3110266e+08 | L6: -1.4043093e+08 | M6: -70052977 | N6: -89000000 | O6: -94000000 | P6: -44000000 | Q6: 133000000 | R6: -129000000 | S6: -27000000 | T6: -107000000 | U6: -133000000 | V6: -81000000 | W6: 6000000 | X6: -32000000 | Y6: -15000000 | Z6: -101000000 | AA6: -115000000 | AC6: -1.655304e+08 | AD6: -188000000 | AE6: -287000000 | AF6: -446000000 | AG6: -94000000 | AH6: -396000000 | AI6: -122000000
A7: Depreciation of property, plant and equipment | B7: 7.1050631e+08 | C7: 6.3594987e+08 | D7: 6.4690974e+08 | E7: 4.6885197e+08 | F7: 6.876891e+08 | G7: 7.7223897e+08 | H7: 7.1557676e+08 | I7: 6.4414285e+08 | J7: 5.8913223e+08 | K7: 6.3207334e+08 | L7: 6.6069219e+08 | M7: 6.8559954e+08 | N7: 709000000 | O7: 791000000 | P7: 798000000 | Q7: 718000000 | R7: 576000000 | S7: 561000000 | T7: 595000000 | U7: 714000000 | V7: 718000000 | W7: 704000000 | X7: 750000000 | Y7: 685000000 | Z7: 653000000 | AA7: 788000000 | AC7: 3.03086e+09 | AD7: 2460000000 | AE7: 2816000000 | AF7: 2551000000 | AG7: 3016000000 | AH7: 2446000000 | AI7: 2857000000
A8: Amortization of intangible assets | B8: 10893041 | C8: 10960567 | D8: 13655087 | E8: 12738572 | F8: 11771204 | G8: 12740793 | H8: 12820047 | I8: 13418191 | J8: 11086855 | K8: 12648249 | L8: 11957062 | M8: 12078738 | N8: 10000000 | O8: 9000000 | P8: 11000000 | Q8: 7000000 | R8: 10000000 | S8: 10000000 | T8: 11000000 | U8: 12000000 | V8: 14000000 | W8: 17000000 | X8: 13000000 | Y8: 17000000 | Z8: 17000000 | AA8: 14000000 | AC8: 49318420 | AD8: 48000000 | AE8: 51000000 | AF8: 43000000 | AG8: 37000000 | AH8: 43000000 | AI8: 61000000
A9: Depreciation of right-of-use assets | B9: 77374782 | C9: 58165063 | D9: 64219874 | E9: 56142226 | F9: 47604466 | G9: 50750295 | H9: 52391397 | I9: 51024961 | J9: 50566190 | K9: 49965669 | L9: 56244660 | M9: 57955723 | N9: 56000000 | O9: 54000000 | P9: 55000000 | Q9: 55000000 | R9: 66000000 | S9: 67000000 | T9: 68000000 | U9: 69000000 | V9: 74000000 | W9: 67000000 | X9: 73000000 | Y9: 72000000 | Z9: 73000000 | AA9: 76000000 | AC9: 2.1831814e+08 | AD9: 254000000 | AE9: 201000000 | AF9: 214000000 | AG9: 220000000 | AH9: 270000000 | AI9: 286000000
A10: Retirement of property, plant and equipment and intangible assets and consumption of materials | B10: 77130544 | C10: 38850766 | D10: 1.3739748e+08 | E10: 86157253 | F10: 83245683 | G10: 87131274 | H10: 73576370 | I10: 95191515 | J10: 85383793 | K10: 99507469 | L10: 1.1119108e+08 | M10: 75200482 | N10: 84000000 | O10: 79000000 | P10: 108000000 | Q10: 112000000 | R10: 90000000 | S10: 153000000 | T10: 145000000 | U10: 232000000 | V10: 99000000 | W10: 100000000 | X10: 138000000 | Y10: 343000000 | Z10: 56000000 | AA10: 92000000 | AC10: 3.9728958e+08 | AD10: 339000000 | AE10: 342000000 | AF10: 375000000 | AG10: 383000000 | AH10: 620000000 | AI10: 680000000
A11: Charge on income tax | B11: -12277059 | C11: -13093434 | D11: 1.2184434e+08 | E11: 91307687 | F11: 1.1213145e+08 | G11: 7.0218057e+08 | H11: 1.5505466e+08 | I11: -2.643523e+08 | J11: 2.0322149e+08 | K11: 1.8269598e+08 | L11: 2.8772186e+08 | M11: 1.6472634e+08 | N11: 85000000 | O11: 75000000 | P11: 0 | Q11: 860000000 | R11: -121000000 | S11: -79000000 | T11: -787000000 | U11: -216000000 | V11: 38000000 | W11: 61000000 | X11: 579000000 | Y11: 1042000000 | Z11: 243000000 | AA11: 593000000 | AC11: 5.4780009e+08 | AD11: 184000000 | AE11: 699000000 | AF11: 822000000 | AG11: -381000000 | AH11: -1373000000 | AI11: 1709000000
A12: Net increase in provisions | B12: 62883293 | C12: 1.8222683e+08 | D12: 1.0280915e+08 | E12: 56067220 | F12: 64651248 | G12: 79350556 | H12: 49387020 | I12: 3.1653194e+08 | J12: 71783167 | K12: 1.0537382e+08 | L12: 82356935 | M12: -1.3400178e+08 | N12: 99000000 | O12: 98000000 | P12: 111000000 | Q12: 118000000 | R12: 163000000 | S12: 199000000 | T12: 160000000 | U12: 226000000 | V12: 261000000 | W12: 247000000 | X12: 88000000 | Y12: 221000000 | Z12: 102000000 | AA12: 75000000 | AC12: 2.7193686e+08 | AD12: 396000000 | AE12: 510000000 | AF12: 139000000 | AG12: 426000000 | AH12: 748000000 | AI12: 817000000
A13: Inventories write-down and reversal of impairment losses of property, plant and equipment | M13: 26657164 | Q13: 1782000000 | T13: 21000000 | U13: 61000000 | X13: 5000000 | Y13: 0 | AF13: 123000000 | AG13: 2288000000 | AH13: 87000000 | AI13: -4000000
A14: Effect of changes in exchange rates, interest and others | J14: 7175502.8 | K14: 1.1896305e+08 | L14: -1.4617711e+08 | M14: -1.1053557e+08 | N14: 29000000 | O14: -34000000 | P14: -130000000 | Q14: -557000000 | R14: 242000000 | S14: 71000000 | T14: 100000000 | U14: 30000000 | V14: 243000000 | W14: 299000000 | X14: 173000000 | Y14: 237000000 | Z14: 291000000 | AA14: 45000000 | AE14: 440000000 | AF14: -73000000 | AG14: 709000000 | AH14: 613000000 | AI14: 963000000
A15: Share-based benefit plans | B15: 2393538.1 | C15: 2266171.3 | D15: 928545.91 | E15: 2162682.1 | F15: 1344312.2 | G15: 1298560.4 | H15: 524737.08 | I15: 497707.39 | J15: 497126.34 | K15: 483210.58 | L15: 3422625.9 | M15: 2925560.5 | N15: 4000000 | O15: 8000000 | P15: 3000000 | Q15: -12000000 | R15: 1000000 | S15: 1000000 | T15: 3000000 | U15: 2000000 | V15: 2000000 | W15: 3000000 | X15: 4000000 | Y15: 6000000 | Z15: 3000000 | AA15: 4000000 | AC15: 10241778 | AD15: 7000000 | AE15: 6000000 | AF15: 8000000 | AG15: 3000000 | AH15: 7000000 | AI15: 15000000
A16: Result from sale of assets | I16: 0 | V16: -14000000 | W16: -168000000 | X16: -34000000 | Y16: -3000000 | Z16: -4000000 | AA16: 0 | AE16: -57000000 | AH16: -6000000 | AI16: -219000000
A17: Result from changes in fair value of assets held for sale | V17: 200000000 | W17: 44000000 | X17: -4000000 | Y17: 178000000 | Z17: -14000000 | AA17: 147000000 | AH17: 260000000 | AI17: 418000000
A18: Result from revaluation of companies | X18: 0 | Y18: 0 | AI18: -45000000
A19: Other insurance income | AC19: -10345650 | AD19: -52000000 | AE19: -15000000 | AH19: -5000000
A20: Trade receivables | B20: 2.5058878e+08 | C20: 1.7520614e+08 | D20: -1.1892215e+08 | E20: 2.0705493e+08 | F20: 20514881 | G20: -1.6234134e+08 | H20: -1.2260328e+08 | I20: 3.5340211e+08 | J20: -1.1324163e+08 | K20: -2.3057622e+08 | L20: -1.8159833e+08 | M20: 71225670 | N20: 144000000 | O20: -175000000 | P20: -233000000 | Q20: 86000000 | R20: -448000000 | S20: -352000000 | T20: -287000000 | U20: 279000000 | V20: -14000000 | W20: -271000000 | X20: -250000000 | Y20: 176000000 | Z20: -58000000 | AA20: -330000000 | AC20: -2.4582345e+08 | AD20: 414000000 | AE20: 117000000 | AF20: -397000000 | AG20: -178000000 | AH20: -808000000 | AI20: -359000000
A21: Other receivables | B21: -65048875 | C21: 1.6680798e+08 | D21: 25671563 | E21: -45816357 | F21: -93344970 | G21: 55369764 | H21: -29333832 | I21: -1.5935595e+08 | J21: 1.5614457e+08 | K21: -1.3480727e+08 | L21: -68931980 | M21: 944326.48 | N21: 41000000 | O21: -177000000 | P21: 143000000 | Q21: -185000000 | R21: -128000000 | S21: -155000000 | T21: -85000000 | U21: -172000000 | V21: -224000000 | W21: -20000000 | X21: -25000000 | Y21: -161000000 | Z21: 1000000 | AA21: 115000000 | AC21: -2.7164602e+08 | AD21: 89000000 | AE21: -241000000 | AF21: -94000000 | AG21: -178000000 | AH21: -540000000 | AI21: -430000000
A22: Inventories | B22: -1.7832673e+08 | C22: 82396802 | D22: 60901688 | E22: 1.7827751e+08 | F22: -25383777 | G22: -86237183 | H22: -94679032 | I22: -79722769 | J22: -2673226.5 | K22: -2.0945907e+08 | L22: -2.7125785e+08 | M22: 2.5775175e+08 | N22: -126000000 | O22: -25000000 | P22: 127000000 | Q22: 68000000 | R22: 125000000 | S22: 1000000 | T22: -156000000 | U22: 157000000 | V22: -69000000 | W22: 132000000 | X22: -54000000 | Y22: 85000000 | Z22: -5000000 | AA22: -200000000 | AC22: 1.397286e+08 | AD22: 162000000 | AE22: -303000000 | AF22: -232000000 | AG22: 44000000 | AH22: 127000000 | AI22: 94000000
A23: Accounts payable | B23: -55458440 | C23: -1.7738345e+08 | D23: -1.3615487e+08 | E23: 53929540 | F23: 1.9068899e+08 | G23: -63299498 | H23: -52823533 | I23: -56250889 | J23: -18215459 | K23: 79729745 | L23: 3.1215233e+08 | M23: 2.204848e+08 | N23: 27000000 | O23: 118000000 | P23: 330000000 | Q23: 261000000 | R23: 41000000 | S23: 196000000 | T23: 477000000 | U23: -12000000 | V23: -282000000 | W23: 196000000 | X23: -70000000 | Y23: -124000000 | Z23: 81000000 | AA23: -406000000 | AC23: 6.1149439e+08 | AD23: -490000000 | AE23: -91000000 | AF23: 600000000 | AG23: 736000000 | AH23: 702000000 | AI23: -280000000
A24: Taxes payable | B24: 5943138.8 | C24: 177738.92 | D24: 22735720 | E24: -14751242 | F24: 91130809 | G24: -56827983 | H24: -14949862 | I24: -48914682 | J24: 1.776148e+08 | K24: -58375228 | L24: 27108082 | M24: -56091758 | N24: -7000000 | O24: 61000000 | P24: -6000000 | Q24: 26000000 | R24: 107000000 | S24: 37000000 | T24: -14000000 | U24: 11000000 | V24: -12000000 | W24: 65000000 | X24: -23000000 | Y24: -15000000 | Z24: 123000000 | AA24: 59000000 | AC24: -23786685 | AD24: 27000000 | AE24: -33000000 | AF24: 112000000 | AG24: 74000000 | AH24: 141000000 | AI24: 15000000
A25: Salaries and social security | B25: -28901565 | C25: 13804390 | D25: 83473546 | E25: 41766016 | F25: -27665718 | G25: 13262346 | H25: 15505466 | I25: 16265077 | J25: -33335604 | K25: 16963234 | L25: 32138752 | M25: 71250359 | N25: -58000000 | O25: 21000000 | P25: 85000000 | Q25: 183000000 | R25: -48000000 | S25: 98000000 | T25: 130000000 | U25: 99000000 | V25: 27000000 | W25: -111000000 | X25: 27000000 | Y25: 54000000 | Z25: 64000000 | AA25: -24000000 | AC25: 94191119 | AD25: 90000000 | AE25: 10000000 | AF25: 80000000 | AG25: 231000000 | AH25: 279000000 | AI25: -3000000
A26: Other liabilities | B26: 2816885 | C26: -325854.69 | D26: 832960.3 | E26: 1.0970924e+08 | F26: -26852353 | G26: -16955793 | H26: -24374552 | I26: -18206136 | J26: -18984598 | K26: -4170870.2 | L26: -2397313.4 | M26: 14387092 | N26: -9000000 | O26: 35000000 | P26: 28000000 | Q26: 12000000 | R26: -49000000 | S26: 1000000 | T26: -1000000 | U26: 268000000 | V26: -104000000 | W26: -288000000 | X26: 87000000 | Y26: -87000000 | Z26: -80000000 | AA26: 56000000 | AC26: 16681841 | AD26: 109000000 | AE26: -92000000 | AF26: -14000000 | AG26: 66000000 | AH26: 219000000 | AI26: -392000000
A27: Decrease in provisions due to payment/use | M27: -57171870 | N27: -48000000 | O27: -57000000 | P27: -333000000 | Q27: -53000000 | R27: -36000000 | S27: -36000000 | T27: -47000000 | U27: -52000000 | V27: -59000000 | W27: -41000000 | X27: -34000000 | Y27: -32000000 | Z27: -26000000 | AA27: -32000000 | AE27: -81000000 | AF27: -159000000 | AG27: -491000000 | AH27: -171000000 | AI27: -166000000
A28: Contract assets | B28: -8418089.7 | C28: 3762140.5 | D28: 95585.608 | E28: -6225524.1 | F28: 5422435.6 | G28: -10941968 | H28: 2911776.4 | I28: -3971704.9 | J28: -3901972.8 | K28: -3738523.9 | L28: 14140461 | M28: 1623254 | N28: -9000000 | O28: 1000000 | P28: -3000000 | Q28: -1000000 | R28: -8000000 | S28: -5000000 | T28: -17000000 | U28: 7000000 | V28: 5000000 | W28: 0 | X28: 10000000 | Y28: 3000000 | Z28: -2000000 | AA28: -2000000 | AC28: 9244606.9 | AD28: -8000000 | AE28: -6000000 | AF28: 7000000 | AG28: -12000000 | AH28: -23000000 | AI28: 18000000
A29: Contract liabilities | B29: 1400301.2 | C29: -19329108 | D29: 42890628 | E29: -17451469 | F29: -6902308.7 | G29: 14124505 | H29: 1.0390823e+08 | I29: -39328838 | J29: 1.6772855e+08 | K29: -18913031 | L29: 61098298 | M29: -1.7007752e+08 | N29: 17000000 | O29: 75000000 | P29: -16000000 | Q29: -51000000 | R29: -16000000 | S29: 15000000 | T29: 9000000 | U29: 80000000 | V29: 45000000 | W29: 35000000 | X29: -9000000 | Y29: 13000000 | Z29: 63000000 | AA29: 71000000 | AC29: 16120933 | AD29: -22000000 | AE29: 56000000 | AF29: -29000000 | AG29: 25000000 | AH29: 88000000 | AI29: 84000000
A30: Dividends received | B30: 2116734.4 | C30: 29119560 | D30: 5434724.6 | E30: 1525128.4 | F30: 316308.74 | G30: 40085069 | H30: 0 | I30: 12731355 | L30: 1888345.3 | M30: 26916391 | N30: 198000000 | O30: 73000000 | P30: 0 | Q30: 5000000 | T30: 1000000 | U30: 37000000 | X30: 21000000 | Y30: 38000000 | AC30: 16848036 | AD30: 38000000 | AE30: 56000000 | AF30: 94000000 | AG30: 276000000 | AH30: 174000000 | AI30: 224000000
A31: Proceeds from collection of profit loss insurance | E31: 9025759.8 | F31: 135560.89 | G31: 5353900.7 | H31: 0 | I31: 13676999 | J31: 1088050.1 | K31: 0 | L31: 0 | M31: 0 | N31: 322810.3 | O31: 0 | P31: 0 | Q31: 0 | V31: 1000000 | W31: 4000000 | X31: 0 | Y31: 0 | AC31: 15746993 | AD31: 51000000 | AE31: 19000000 | AF31: 1000000 | AG31: 211612 | AI31: 5000000
A32: Income tax payments | B32: -7262027.1 | C32: -14959693 | D32: -9667801.5 | E32: -6775570.4 | F32: -1457279.6 | G32: -1373068 | H32: -1327276.2 | I32: -1274130.9 | J32: -2401214 | K32: -3925026.3 | L32: -1866216.3 | M32: -2.6376335e+08 | N32: -1000000 | O32: -7000000 | P32: -4000000 | Q32: 2000000 | R32: -6000000 | S32: -10000000 | T32: -9000000 | U32: -1000000 | V32: -8000000 | W32: -104000000 | X32: -10000000 | Y32: -11000000 | Z32: -24000000 | AA32: -10000000 | AC32: -1.4448594e+08 | AD32: -35000000 | AE32: -5000000 | AF32: -266000000 | AG32: -10000000 | AH32: -26000000 | AI32: -133000000
A33: Net cash flows from operating activities (1) (2) | B33: 9.5993903e+08 | C33: 4.9833551e+08 | D33: 6.6564452e+08 | E33: 8.4843393e+08 | F33: 1.0534211e+09 | G33: 1.0010836e+09 | H33: 1.0859382e+09 | I33: 1.0667661e+09 | J33: 1.4316394e+09 | K33: 1.3330508e+09 | L33: 1.5860699e+09 | M33: 1.3069972e+09 | N33: 1497000000 | O33: 1309000000 | P33: 1399000000 | Q33: 1708000000 | R33: 1089000000 | S33: 1422000000 | T33: 1695000000 | U33: 1663000000 | V33: 850000000 | W33: 1146000000 | X33: 1225000000 | Y33: 1738000000 | Z33: 1865000000 | AA33: 2372000000 | AC33: 4.5108904e+09 | AD33: 2915000000 | AE33: 4201000000 | AF33: 5693000000 | AG33: 5913000000 | AH33: 5869000000 | AI33: 4959000000
A34: Acquisition of property, plant and equipment and intangible assets | B34: -7.9035605e+08 | C34: -2.8654477e+08 | D34: -1.9108929e+08 | E34: -4.0923445e+08 | F34: -4.9298977e+08 | G34: -5.0000962e+08 | H34: -7.014603e+08 | I34: -7.5660481e+08 | J34: -7.8441846e+08 | K34: -8.1901649e+08 | L34: -1.0501782e+09 | M34: -1.2931471e+09 | N34: -1262000000 | O34: -1366000000 | P34: -1500000000 | Q34: -1545000000 | R34: -1181000000 | S34: -1354000000 | T34: -1484000000 | U34: -1373000000 | V34: -1205000000 | W34: -1304000000 | X34: -1148000000 | Y34: -1420000000 | Z34: -1090000000 | AA34: -1127000000 | AC34: -3.3541304e+09 | AD34: -1650000000 | AE34: -2448000000 | AF34: -4006000000 | AG34: -5673000000 | AH34: -5392000000 | AI34: -5077000000
A35: Additions of assets held for sale | T35: -71000000 | U35: -93000000 | V35: -33000000 | W35: -9000000 | X35: -3000000 | Y35: -1000000 | Z35: -4000000 | AA35: -4000000 | AH35: -269000000 | AI35: -46000000
A36: Contributions and acquisitions of interests in associates and joint ventures | M36: -1419575.8 | N36: -2000000 | O36: -2000000 | P36: 0 | Q36: -1000000 | V36: -71000000 | W36: -11000000 | X36: 0 | Y36: -3000000 | Z36: -34000000 | AA36: -202000000 | AC36: -1.0025724e+08 | AF36: -2000000 | AG36: -5000000 | AH36: -32803.247 | AI36: -85000000
A37: Acquisitions from business combinations net of cash and cash equivalents | V37: -243000000 | W37: 13000000 | X37: -520000000 | Y37: -17000000 | AI37: -767000000
A38: Interests received from financial assets | E38: 37503.157 | F38: 13239780 | G38: 21809428 | H38: 4887257.1 | I38: -19908.295 | J38: 834797.06 | K38: 17242988 | L38: 28907911 | M38: 49092633 | N38: 27000000 | O38: 21000000 | P38: 26000000 | Q38: 11000000 | R38: 17000000 | S38: 15000000 | T38: 2000000 | U38: 0 | V38: 1000000 | W38: 2000000 | X38: 1000000 | Y38: 0 | Z38: 1000000 | AA38: 1000000 | AC38: 22083185 | AD38: 255222.4 | AE38: 41000000 | AF38: 99000000 | AG38: 85000000 | AH38: 34000000 | AI38: 4000000
A39: Proceeds from concessions, assignment agreements and sale of assets | Q39: 1000000 | R39: 2000000 | S39: 2000000 | T39: 63000000 | U39: 75000000 | V39: 71000000 | W39: 0 | X39: 7000000 | Y39: 219000000 | Z39: 514000000 | AA39: 54000000 | AF39: 8000000 | AG39: 15000000 | AH39: 142000000 | AI39: 297000000
A40: Net cash flows used in investing activities | B40: -6.8686402e+08 | C40: -49055943 | D40: -2.7935577e+08 | E40: -5.4013297e+08 | F40: -5.2310688e+08 | G40: -5.3132408e+08 | H40: -7.8851521e+08 | I40: -7.0804848e+08 | J40: -8.376016e+08 | K40: -1.0203542e+09 | L40: -9.9068054e+08 | M40: -1.1051582e+09 | N40: -1189000000 | O40: -1259000000 | P40: -1321000000 | Q40: -1563000000 | R40: -1208000000 | S40: -1464000000 | T40: -1439000000 | U40: -1400000000 | V40: -1383000000 | W40: -1258000000 | X40: -1662000000 | Y40: -1224000000 | Z40: -709000000 | AA40: -2031000000 | AC40: -3.4044875e+09 | AD40: -1517000000 | AE40: -2547000000 | AF40: -4016000000 | AG40: -5332000000 | AH40: -5511000000 | AI40: -5527000000
A41: Payments of loans | B41: -3.4134784e+08 | C41: -8.6044894e+08 | D41: -6.910976e+08 | E41: -5.6561012e+08 | F41: -5.362337e+08 | G41: -5.4337302e+08 | H41: -2.2149049e+08 | I41: -3.7762055e+08 | J41: -4.5723429e+08 | K41: -2.321191e+08 | L41: -66291247 | M41: -58029788 | N41: -133000000 | O41: -371000000 | P41: -571000000 | Q41: -321000000 | R41: -554000000 | S41: -448000000 | T41: -992000000 | U41: -108000000 | V41: -1087000000 | W41: -294000000 | X41: -494000000 | Y41: -996000000 | Z41: -1173000000 | AA41: -400000000 | AC41: -1.9414921e+09 | AD41: -2283000000 | AE41: -1653000000 | AF41: -780000000 | AG41: -1396000000 | AH41: -2102000000 | AI41: -2871000000
A42: Payments of interests | B42: -2.612213e+08 | C42: -2.00608e+08 | D42: -2.5062547e+08 | E42: -1.5926341e+08 | F42: -1.9953433e+08 | G42: -1.307182e+08 | H42: -1.824233e+08 | I42: -1.0730571e+08 | J42: -1.7328136e+08 | K42: -1.2626208e+08 | L42: -1.8272691e+08 | M42: -92476102 | N42: -157000000 | O42: -144000000 | P42: -192000000 | Q42: -130000000 | R42: -202000000 | S42: -124000000 | T42: -275000000 | U42: -106000000 | V42: -221000000 | W42: -100000000 | X42: -217000000 | Y42: -132000000 | Z42: -257000000 | AA42: -115000000 | AC42: -8.6433959e+08 | AD42: -873000000 | AE42: -615000000 | AF42: -543000000 | AG42: -623000000 | AH42: -707000000 | AI42: -670000000
A43: Proceeds from loans (financiación) | B43: 4.1066275e+08 | C43: 8.3488416e+08 | D43: 2.8806771e+08 | E43: 4.5421324e+08 | F43: 2.904731e+08 | G43: 2.2573663e+08 | H43: 2.7643355e+08 | I43: 2.0502558e+08 | J43: 3.5389767e+08 | K43: 8629971.3 | L43: 46618525 | M43: 25904171 | N43: 472000000 | O43: 820000000 | P43: 976000000 | Q43: 399000000 | R43: 1114000000 | S43: 321000000 | T43: 1217000000 | U43: 315000000 | V43: 1767000000 | W43: 514000000 | X43: 1311000000 | Y43: 889000000 | Z43: 769000000 | AA43: 341000000 | AC43: 2.0224084e+09 | AD43: 1803000000 | AE43: 963000000 | AF43: 402000000 | AG43: 2667000000 | AH43: 2967000000 | AI43: 4481000000
A44: Account overdrafts, net | J44: -7447515.3 | K44: 53678761 | L44: -46707041 | M44: 77070619 | N44: -70000000 | O44: 0 | P44: 33000000 | Q44: 34000000 | R44: 56000000 | S44: 143000000 | T44: -247000000 | U44: 0 | Z44: -3000000 | AA44: 0 | AD44: 2000000 | AE44: 8000000 | AF44: 71000000 | AG44: -3000000 | AH44: -48000000 | AI44: 4000000
A45: Repurchase of treasury shares (financiación) | M45: -20960345 | AC45: -5816831.3 | AD45: -6000000 | AF45: -28000000 | AI45: -10000000
A46: Payments of leases | B46: -96653348 | C46: -61068132 | D46: -73887675 | E46: -97758230 | F46: -76625793 | G46: -76604420 | H46: -71930136 | I46: -75203586 | J46: -85121161 | K46: -80280775 | L46: -92831351 | M46: -85359707 | N46: -92000000 | O46: -89000000 | P46: -86000000 | Q46: -92000000 | R46: -101000000 | S46: -97000000 | T46: -100000000 | U46: -102000000 | V46: -105000000 | W46: -99000000 | X46: -102000000 | Y46: -100000000 | Z46: -96000000 | AA46: -98000000 | AC46: -3.1593704e+08 | AD46: -331000000 | AE46: -302000000 | AF46: -341000000 | AG46: -359000000 | AH46: -400000000 | AI46: -406000000
A47: Payments of interests in relation to income tax | B47: -4298599 | C47: -2606837.5 | D47: -2294054.6 | E47: -1100092.6 | F47: -79077.186 | G47: -149015.13 | H47: -267513.02 | I47: -358349.32 | J47: -440847.88 | K47: -2449962.4 | L47: -2426818.8 | M47: -3419325.9 | N47: -3000000 | O47: -2000000 | P47: -2000000 | Q47: -1000000 | R47: -1000000 | S47: -1000000 | T47: -1000000 | U47: 0 | X47: -1000000 | Y47: -9000000 | Z47: -27000000 | AA47: -29000000 | AC47: -12111474 | AD47: -10000000 | AE47: -1000000 | AF47: -8000000 | AG47: -8000000 | AH47: -3000000 | AI47: -11000000
A48: Net cash flows (used in) / from financing activities | B48: -2.9285834e+08 | C48: -2.8984775e+08 | D48: -7.2983709e+08 | E48: -3.7639419e+08 | F48: -5.219998e+08 | G48: -5.2510802e+08 | H48: -1.9967789e+08 | I48: -3.5546261e+08 | J48: -3.696275e+08 | K48: -3.7880318e+08 | L48: -3.5061262e+08 | M48: -1.5727048e+08 | N48: 17000000 | O48: 214000000 | P48: 158000000 | Q48: -111000000 | R48: 312000000 | S48: -206000000 | T48: -398000000 | U48: -1000000 | V48: 354000000 | W48: 20000000 | X48: 497000000 | Y48: -354000000 | Z48: -787000000 | AA48: -328000000 | AC48: -1.1650698e+09 | AD48: -1698000000 | AE48: -1600000000 | AF48: -1227000000 | AG48: 278000000 | AH48: -293000000 | AI48: 517000000
A49: Effect of changes in exchange rates on cash and cash equivalents | J49: 15073246 | K49: 26186622 | L49: 45054739 | M49: 42340390 | N49: -84000000 | O49: -111000000 | P49: -107000000 | Q49: -207000000 | R49: -7000000 | S49: -20000000 | T49: -22000000 | U49: -21000000 | V49: -1000000 | W49: -72000000 | X49: -35000000 | Y49: -26000000 | Z49: 24000000 | AA49: -21000000 | AD49: -156000000 | AE49: -93000000 | AF49: -288000000 | AG49: -509000000 | AH49: -70000000 | AI49: -134000000
A50: Increase / (Decrease) in cash and cash equivalents | B50: 49368758 | C50: 2.1342001e+08 | D50: -3.2635658e+08 | E50: -62792786 | F50: 18729996 | G50: -49036621 | H50: 1.0113021e+08 | I50: 11745894 | J50: 2.3948358e+08 | K50: -39919975 | L50: 2.898315e+08 | M50: 86908896 | N50: 241000000 | O50: 3.7667731e+08 | P50: 4.9223643e+08 | Q50: -173000000 | R50: 186000000 | S50: -268000000 | T50: -164000000 | U50: 241000000 | V50: -180000000 | W50: -164000000 | X50: 25000000 | Y50: 134000000 | Z50: 393000000 | AA50: -8000000 | AC50: 4.1698371e+08 | AD50: -456000000 | AE50: -39000000 | AF50: 162000000 | AG50: 350000000 | AH50: -5000000 | AI50: -185000000
A51: Cash and cash equivalents at the beginning of the fiscal year | B51: 1.1037712e+09 | C51: 1.0749538e+09 | D51: 1.1867834e+09 | E51: 7.8299136e+08 | F51: 6.4913287e+08 | G51: 6.1181001e+08 | H51: 5.3989362e+08 | I51: 6.2282702e+08 | J51: 6.1040707e+08 | K51: 7.9471413e+08 | L51: 6.6687951e+08 | M51: 8.3500904e+08 | N51: 773000000 | O51: 1014000000 | P51: 1167000000 | Q51: 1296000000 | R51: 1123000000 | S51: 1309000000 | T51: 1041000000 | U51: 877000000 | V51: 1118000000 | W51: 938000000 | X51: 774000000 | Y51: 799000000 | Z51: 933000000 | AA51: 1326000000 | AC51: 1.2211933e+09 | AD51: 1106000000 | AE51: 650000000 | AF51: 611000000 | AG51: 773000000 | AH51: 1123000000 | AI51: 1118000000
A52: Cash and cash equivalents at the end of the period | B52: 1.0749538e+09 | C52: 1.1867834e+09 | D52: 7.8299136e+08 | E52: 650000000 | F52: 6.1181001e+08 | G52: 5.3989362e+08 | H52: 6.2282702e+08 | I52: 611000000 | J52: 7.9471413e+08 | K52: 6.6687951e+08 | L52: 8.3500904e+08 | M52: 773000000 | N52: 1014000000 | O52: 1167000000 | P52: 1296000000 | Q52: 1123000000 | R52: 1309000000 | S52: 1041000000 | T52: 877000000 | U52: 1118000000 | V52: 938000000 | W52: 774000000 | X52: 799000000 | Y52: 933000000 | Z52: 1326000000 | AA52: 1318000000 | AC52: 1.1037712e+09 | AD52: 650000000 | AE52: 611000000 | AF52: 773000000 | AG52: 1123000000 | AH52: 1118000000 | AI52: 933000000
A54: Líneas de presentaciones anteriores
A55: Net (loss) / income | B55: 1.0341061e+08 | F55: -25383777 | AC55: -6.9342862e+08 | AD55: -1.0069516e+09
A56: Net loss | D56: -4.8246153e+08 | E56: 5.3769527e+08 | F56: -25383777 | G56: -4.9240985e+08 | H56: 2.3634776e+08 | I56: 2.4616607e+08 | J56: 2.4778465e+08 | K56: 7.9740766e+08 | AC56: -6.9342862e+08 | AD56: -1021000000 | AE56: 16000000 | AF56: 2234000000
A57: Income from equity interest in associates and joint ventures | B57: -23121252 | C57: -34066627 | D57: -61857544
A58: Impairment of property, plant and equipment and intangible assets, net | AE58: 1.1844706e+08 | AF58: 1.4113019e+08 | AG58: 5.5100112e+09
A59: Impairment of property, plant and equipment and intangible assets | AE59: 115000000 | AF59: 123000000 | AG59: 2288000000
A60: Impairment / (Recovery) of property, plant and equipment and intangible assets, net | AC60: 8.6066252e+08 | AD60: 53000000 | AE60: 115000000 | AF60: 123000000
A61: Impairment / (Recovery) of property, plant and equipment | AC61: 8.6066252e+08
A62: (Recovery) / Impairment of property, plant and equipment and intangible assets, net | AC62: 8.6066252e+08 | AD62: -97140482
A63: Effect of changes in exchange rates, interest and other | AD63: 224000000 | AE63: 440000000 | AF63: -73000000
A64: Exchange differences, interest and other | B64: 1.6022051e+08 | C64: -1.1256798e+08 | D64: 91352532 | E64: -72343590 | F64: 43085770 | G64: 1.2107479e+08 | H64: 1.025398e+08 | I64: 83425712 | J64: 7175502.8 | K64: 1.1896305e+08 | L64: -1.4617711e+08 | AC64: -1.2337915e+08 | AD64: 44564667 | AE64: 3.5283714e+08
A65: Share-based benefit plan | B65: 2393538.1 | C65: 2266171.3 | D65: 928545.91
A66: Accrued insurance | B66: -7457418 | C66: -40450417 | D66: 0 | E66: -5675477.8 | AC66: -10345650 | AD66: -51654178
A67: Result from assignment of interest in areas | B67: -1.0349203e+08 | C67: -87047638 | D67: 0
A68: Result from debt exchange | E68: 0 | F68: -20955454 | G68: 0 | H68: 0 | I68: 0 | AD68: 29000000 | AE68: -21000000
A69: Result from sale of assets held for disposal | H69: -24981601 | I69: 0 | AE69: -58381838
A70: Result from the assignment of areas | B70: -1.0349203e+08 | C70: -87047638 | D70: 0 | E70: 0 | H70: -10566764 | I70: -5325469 | AC70: -16162481 | AD70: -1.7345198e+08 | AE70: -21400010
A71: Result from assignment of areas | AE71: -21000000
A72: Result from financial instruments exchange | E72: 0 | AD72: -18000000
A73: Result from the sale of areas | AC73: -16162481
A74: Result from sale of companies | AI74: -335000000
A75: Result from sale of WI of areas | AD75: -192000000 | AE75: -21000000
A76: Decrease in provisions included in liabilities due to payment/use | B76: -21997755 | C76: -4265734.2 | D76: -3823424.3 | E76: -11050930 | F76: -20571365 | G76: -9930793.9 | H76: -14126745 | I76: -40204803 | J76: -30108972 | K76: -31612145 | L76: -47415171 | M76: -57171870 | N76: -49030720 | O76: -60797979 | AC76: -1.0100512e+08 | AD76: -33000000 | AE76: -81000000 | AF76: -159000000
A77: Proceeds from collection of business interruption insurance | B77: 4021795.3 | C77: 11212364 | D77: 27719826
A78: Proceeds from collection of lost profit insurance | B78: 4021795.3 | C78: 11212364 | F78: 135560.89 | G78: 5353900.7 | AC78: 15746993 | AD78: 53256408
A79: Proceeds from sales of financial assets | D79: 37046251 | E79: 93095337 | F79: 1.0456263e+08 | G79: 1.2010619e+08 | H79: 1.0260153e+08 | I79: 80748046 | J79: 32575845 | K79: 1.9481016e+08 | L79: 1.6823977e+08 | M79: 2.5286965e+08 | N79: 128000000 | O79: 199000000 | P79: 224000000 | Q79: 32000000 | R79: 84000000 | S79: 28000000 | T79: 93000000 | U79: 24000000 | V79: 97000000 | W79: 51000000 | X79: 62000000 | Y79: 11000000 | Z79: 49000000 | AC79: 19881099 | AD79: 557000000 | AE79: 406000000 | AF79: 643000000 | AG79: 583000000 | AH79: 229000000 | AI79: 221000000
A80: Payments from purchase of financial assets | D80: -1.2551756e+08 | E80: -2.2403136e+08 | F80: -1.4791952e+08 | G80: -1.9062228e+08 | H80: -2.0870131e+08 | I80: -47003485 | J80: -88253994 | K80: -4.1518809e+08 | L80: -1.3981869e+08 | M80: -96666937 | N80: -82000000 | O80: -121000000 | P80: -73000000 | Q80: -61000000 | R80: -130000000 | S80: -50000000 | T80: -42000000 | U80: -33000000 | Y80: -13000000 | Z80: -145000000 | AD80: -641000000 | AE80: -594000000 | AF80: -740000000 | AG80: -337000000 | AH80: -255000000 | AI80: -74000000
A81: Payments from purchases of financial assets | F81: -1.4791952e+08 | G81: -1.9062228e+08 | H81: -2.0870131e+08 | J81: -88253994 | K81: -4.1518809e+08 | L81: -1.3981869e+08
A82: Proceeds from sales of WI of areas and assets | J82: 1660214.4 | K82: 1797204.2 | L82: 2463700.5 | M82: 1956545.7 | N82: 2000000 | O82: 10000000 | P82: 1952059.9 | R82: 2000000 | S82: 2000000 | AD82: 217000000 | AE82: 48000000 | AF82: 8000000
A83: Sale of interest in areas | B83: 1.0349203e+08 | AC83: 7935819.9 | AD83: 1.966205e+08
A84: Loans with related parties, net | AF84: -18000000
A85: Payment from purchase of financial assets | D85: -1.2551756e+08
A86: Proceeds from sales of assets | H86: 14157612 | J86: 1660214.4 | K86: 1797204.2 | L86: 2463700.5
A87: Proceeds from the sale of areas | AC87: 7935819.9
A88: Proceeds from assignment of interest in areas | B88: 1.0349203e+08 | C88: 1.1124975e+08 | D88: 0
A89: Interest received from financial assets | AE89: 41000000 | AF89: 99000000 | AG89: 85000000
A90: Proceeds from assignment of areas and sale of assets | AE90: 48000000 | AF90: 8000000 | AG90: 15000000
A91: Proceeds from sales of interest in areas and sale of assets | E91: 0 | I91: 14831680 | AC91: 7935819.9 | AD91: 1.966205e+08 | AE91: 47345156
A92: Payment of loans (financiación) | AC92: -1.9414921e+09
A93: Payment of interests in relation to income tax | AC93: -12111474
A94: Payments of interest (financiación) | D94: -2.5062547e+08 | AE94: -615000000 | AF94: -543000000 | AG94: -623000000
A95: Payment of interest in relation to income tax | B95: -4298599 | C95: -2606837.5 | D95: -2294054.6
A96: Translation differences of cash and cash equivalents | B96: 69152083 | C96: 53988198 | D96: 17191754 | F96: 10415595
A97: Dividends paid (financiación) | AC97: -47781115
A98: Payments of interest in relation to income tax | AE98: -1000000 | AF98: -8000000 | AG98: -8000000
A99: Translation differences on cash and cash equivalents | D99: 17191754 | E99: 5300446.2 | F99: 10415595 | G99: 6311855.1 | H99: 3385068.6 | I99: 8490888 | J99: 15073246 | K99: 26186622 | L99: 45054739 | AC99: 4.7565061e+08 | AD99: 1.3576414e+08 | AE99: 28375530
A100: Translation differences provided by cash and cash equivalents | AC100: 4.7565061e+08 | AD100: 1.3576414e+08
A101: Net (Decrease) / Increase in cash and cash equivalents | D101: -3.2635658e+08 | E101: -62792786 | AC101: 4.1698371e+08 | AD101: -1.6280353e+08
A102: Cash and cash equivalents at the end of period | B102: 1.1256468e+09 | C102: 2.1342001e+08 | D102: -3.2635658e+08
...

Sheet Análisis
A1: Análisis
A2: Todo calculado con fórmulas sobre las hojas de estados: se puede seguir cada celda hasta la línea que la origina.
B4: 2020Q1 | C4: 2020Q2 | D4: 2020Q3 | E4: 2020Q4 | F4: 2021Q1 | G4: 2021Q2 | H4: 2021Q3 | I4: 2021Q4 | J4: 2022Q1 | K4: 2022Q2 | L4: 2022Q3 | M4: 2022Q4 | N4: 2023Q1 | O4: 2023Q2 | P4: 2023Q3 | Q4: 2023Q4 | R4: 2024Q1 | S4: 2024Q2 | T4: 2024Q3 | U4: 2024Q4 | V4: 2025Q1 | W4: 2025Q2 | X4: 2025Q3 | Y4: 2025Q4 | Z4: 2026Q1 | AA4: 2026Q2 | AC4: FY19 | AD4: FY20 | AE4: FY21 | AF4: FY22 | AG4: FY23 | AH4: FY24 | AI4: FY25
A5: Rentabilidad
A6: Margen bruto | B6: =IFERROR('Resultados'!B7/'Resultados'!B5,"") | C6: =IFERROR('Resultados'!C7/'Resultados'!C5,"") | D6: =IFERROR('Resultados'!D7/'Resultados'!D5,"") | E6: =IFERROR('Resultados'!E7/'Resultados'!E5,"") | F6: =IFERROR('Resultados'!F7/'Resultados'!F5,"") | G6: =IFERROR('Resultados'!G7/'Resultados'!G5,"") | H6: =IFERROR('Resultados'!H7/'Resultados'!H5,"") | I6: =IFERROR('Resultados'!I7/'Resultados'!I5,"") | ... AA6: =IFERROR('Resultados'!AA7/'Resultados'!AA5,"") | AC6: =IFERROR('Resultados'!AC7/'Resultados'!AC5,"") | AD6: =IFERROR('Resultados'!AD7/'Resultados'!AD5,"") | AE6: =IFERROR('Resultados'!AE7/'Resultados'!AE5,"") | AF6: =IFERROR('Resultados'!AF7/'Resultados'!AF5,"") | AG6: =IFERROR('Resultados'!AG7/'Resultados'!AG5,"") | AH6: =IFERROR('Resultados'!AH7/'Resultados'!AH5,"") | AI6: =IFERROR('Resultados'!AI7/'Resultados'!AI5,"")
A7: Margen operativo | B7: =IFERROR('Resultados'!B13/'Resultados'!B5,"") | C7: =IFERROR('Resultados'!C13/'Resultados'!C5,"") | D7: =IFERROR('Resultados'!D13/'Resultados'!D5,"") | E7: =IFERROR('Resultados'!E13/'Resultados'!E5,"") | F7: =IFERROR('Resultados'!F13/'Resultados'!F5,"") | G7: =IFERROR('Resultados'!G13/'Resultados'!G5,"") | H7: =IFERROR('Resultados'!H13/'Resultados'!H5,"") | I7: =IFERROR('Resultados'!I13/'Resultados'!I5,"") | ... AA7: =IFERROR('Resultados'!AA13/'Resultados'!AA5,"") | AC7: =IFERROR('Resultados'!AC13/'Resultados'!AC5,"") | AD7: =IFERROR('Resultados'!AD13/'Resultados'!AD5,"") | AE7: =IFERROR('Resultados'!AE13/'Resultados'!AE5,"") | AF7: =IFERROR('Resultados'!AF13/'Resultados'!AF5,"") | AG7: =IFERROR('Resultados'!AG13/'Resultados'!AG5,"") | AH7: =IFERROR('Resultados'!AH13/'Resultados'!AH5,"") | AI7: =IFERROR('Resultados'!AI13/'Resultados'!AI5,"")
A8: Margen EBITDA | B8: =IFERROR(('Resultados'!B13+('Flujo de efectivo'!B7+'Flujo de efectivo'!B8+'Flujo de efectivo'!B9))/'Resultados'!B5,"") | C8: =IFERROR(('Resultados'!C13+('Flujo de efectivo'!C7+'Flujo de efectivo'!C8+'Flujo de efectivo'!C9))/'Resultados'!C5,"") | D8: =IFERROR(('Resultados'!D13+('Flujo de efectivo'!D7+'Flujo de efectivo'!D8+'Flujo de efectivo'!D9))/'Resultados'!D5,"") | E8: =IFERROR(('Resultados'!E13+('Flujo de efectivo'!E7+'Flujo de efectivo'!E8+'Flujo de efectivo'!E9))/'Resultados'!E5,"") | F8: =IFERROR(('Resultados'!F13+('Flujo de efectivo'!F7+'Flujo de efectivo'!F8+'Flujo de efectivo'!F9))/'Resultados'!F5,"") | G8: =IFERROR(('Resultados'!G13+('Flujo de efectivo'!G7+'Flujo de efectivo'!G8+'Flujo de efectivo'!G9))/'Resultados'!G5,"") | H8: =IFERROR(('Resultados'!H13+('Flujo de efectivo'!H7+'Flujo de efectivo'!H8+'Flujo de efectivo'!H9))/'Resultados'!H5,"") | I8: =IFERROR(('Resultados'!I13+('Flujo de efectivo'!I7+'Flujo de efectivo'!I8+'Flujo de efectivo'!I9))/'Resultados'!I5,"") | ... AA8: =IFERROR(('Resultados'!AA13+('Flujo de efectivo'!AA7+'Flujo de efectivo'!AA8+'Flujo de efectivo'!AA9))/'Resultados'!AA5,"") | AC8: =IFERROR(('Resultados'!AC13+('Flujo de efectivo'!AC7+'Flujo de efectivo'!AC8+'Flujo de efectivo'!AC9))/'Resultados'!AC5,"") | AD8: =IFERROR(('Resultados'!AD13+('Flujo de efectivo'!AD7+'Flujo de efectivo'!AD8+'Flujo de efectivo'!AD9))/'Resultados'!AD5,"") | AE8: =IFERROR(('Resultados'!AE13+('Flujo de efectivo'!AE7+'Flujo de efectivo'!AE8+'Flujo de efectivo'!AE9))/'Resultados'!AE5,"") | AF8: =IFERROR(('Resultados'!AF13+('Flujo de efectivo'!AF7+'Flujo de efectivo'!AF8+'Flujo de efectivo'!AF9))/'Resultados'!AF5,"") | AG8: =IFERROR(('Resultados'!AG13+('Flujo de efectivo'!AG7+'Flujo de efectivo'!AG8+'Flujo de efectivo'!AG9))/'Resultados'!AG5,"") | AH8: =IFERROR(('Resultados'!AH13+('Flujo de efectivo'!AH7+'Flujo de efectivo'!AH8+'Flujo de efectivo'!AH9))/'Resultados'!AH5,"") | AI8: =IFERROR(('Resultados'!AI13+('Flujo de efectivo'!AI7+'Flujo de efectivo'!AI8+'Flujo de efectivo'!AI9))/'Resultados'!AI5,"")
A9: Margen neto | B9: =IFERROR('Resultados'!B21/'Resultados'!B5,"") | C9: =IFERROR('Resultados'!C21/'Resultados'!C5,"") | D9: =IFERROR('Resultados'!D21/'Resultados'!D5,"") | E9: =IFERROR('Resultados'!E21/'Resultados'!E5,"") | F9: =IFERROR('Resultados'!F21/'Resultados'!F5,"") | G9: =IFERROR('Resultados'!G21/'Resultados'!G5,"") | H9: =IFERROR('Resultados'!H21/'Resultados'!H5,"") | I9: =IFERROR('Resultados'!I21/'Resultados'!I5,"") | ... AA9: =IFERROR('Resultados'!AA21/'Resultados'!AA5,"") | AC9: =IFERROR('Resultados'!AC21/'Resultados'!AC5,"") | AD9: =IFERROR('Resultados'!AD21/'Resultados'!AD5,"") | AE9: =IFERROR('Resultados'!AE21/'Resultados'!AE5,"") | AF9: =IFERROR('Resultados'!AF21/'Resultados'!AF5,"") | AG9: =IFERROR('Resultados'!AG21/'Resultados'!AG5,"") | AH9: =IFERROR('Resultados'!AH21/'Resultados'!AH5,"") | AI9: =IFERROR('Resultados'!AI21/'Resultados'!AI5,"")
A10: Tasa efectiva de impuesto | B10: =IFERROR(-'Resultados'!B20/'Resultados'!B19,"") | C10: =IFERROR(-'Resultados'!C20/'Resultados'!C19,"") | D10: =IFERROR(-'Resultados'!D20/'Resultados'!D19,"") | E10: =IFERROR(-'Resultados'!E20/'Resultados'!E19,"") | F10: =IFERROR(-'Resultados'!F20/'Resultados'!F19,"") | G10: =IFERROR(-'Resultados'!G20/'Resultados'!G19,"") | H10: =IFERROR(-'Resultados'!H20/'Resultados'!H19,"") | I10: =IFERROR(-'Resultados'!I20/'Resultados'!I19,"") | ... AA10: =IFERROR(-'Resultados'!AA20/'Resultados'!AA19,"") | AC10: =IFERROR(-'Resultados'!AC20/'Resultados'!AC19,"") | AD10: =IFERROR(-'Resultados'!AD20/'Resultados'!AD19,"") | AE10: =IFERROR(-'Resultados'!AE20/'Resultados'!AE19,"") | AF10: =IFERROR(-'Resultados'!AF20/'Resultados'!AF19,"") | AG10: =IFERROR(-'Resultados'!AG20/'Resultados'!AG19,"") | AH10: =IFERROR(-'Resultados'!AH20/'Resultados'!AH19,"") | AI10: =IFERROR(-'Resultados'!AI20/'Resultados'!AI19,"") | AK10: Impuesto sobre resultado antes de impuesto. Con resultado negativo, el signo se invierte y el ratio no dice nada.
A12: Absolutos calculados
A13: EBITDA (resultado operativo + D&A) | B13: =('Resultados'!B13+('Flujo de efectivo'!B7+'Flujo de efectivo'!B8+'Flujo de efectivo'!B9)) | C13: =('Resultados'!C13+('Flujo de efectivo'!C7+'Flujo de efectivo'!C8+'Flujo de efectivo'!C9)) | D13: =('Resultados'!D13+('Flujo de efectivo'!D7+'Flujo de efectivo'!D8+'Flujo de efectivo'!D9)) | E13: =('Resultados'!E13+('Flujo de efectivo'!E7+'Flujo de efectivo'!E8+'Flujo de efectivo'!E9)) | F13: =('Resultados'!F13+('Flujo de efectivo'!F7+'Flujo de efectivo'!F8+'Flujo de efectivo'!F9)) | G13: =('Resultados'!G13+('Flujo de efectivo'!G7+'Flujo de efectivo'!G8+'Flujo de efectivo'!G9)) | H13: =('Resultados'!H13+('Flujo de efectivo'!H7+'Flujo de efectivo'!H8+'Flujo de efectivo'!H9)) | I13: =('Resultados'!I13+('Flujo de efectivo'!I7+'Flujo de efectivo'!I8+'Flujo de efectivo'!I9)) | ... AA13: =('Resultados'!AA13+('Flujo de efectivo'!AA7+'Flujo de efectivo'!AA8+'Flujo de efectivo'!AA9)) | AC13: =('Resultados'!AC13+('Flujo de efectivo'!AC7+'Flujo de efectivo'!AC8+'Flujo de efectivo'!AC9)) | AD13: =('Resultados'!AD13+('Flujo de efectivo'!AD7+'Flujo de efectivo'!AD8+'Flujo de efectivo'!AD9)) | AE13: =('Resultados'!AE13+('Flujo de efectivo'!AE7+'Flujo de efectivo'!AE8+'Flujo de efectivo'!AE9)) | AF13: =('Resultados'!AF13+('Flujo de efectivo'!AF7+'Flujo de efectivo'!AF8+'Flujo de efectivo'!AF9)) | AG13: =('Resultados'!AG13+('Flujo de efectivo'!AG7+'Flujo de efectivo'!AG8+'Flujo de efectivo'!AG9)) | AH13: =('Resultados'!AH13+('Flujo de efectivo'!AH7+'Flujo de efectivo'!AH8+'Flujo de efectivo'!AH9)) | AI13: =('Resultados'!AI13+('Flujo de efectivo'!AI7+'Flujo de efectivo'!AI8+'Flujo de efectivo'!AI9))
A14: Depreciaciones y amortizaciones | B14: =('Flujo de efectivo'!B7+'Flujo de efectivo'!B8+'Flujo de efectivo'!B9) | C14: =('Flujo de efectivo'!C7+'Flujo de efectivo'!C8+'Flujo de efectivo'!C9) | D14: =('Flujo de efectivo'!D7+'Flujo de efectivo'!D8+'Flujo de efectivo'!D9) | E14: =('Flujo de efectivo'!E7+'Flujo de efectivo'!E8+'Flujo de efectivo'!E9) | F14: =('Flujo de efectivo'!F7+'Flujo de efectivo'!F8+'Flujo de efectivo'!F9) | G14: =('Flujo de efectivo'!G7+'Flujo de efectivo'!G8+'Flujo de efectivo'!G9) | H14: =('Flujo de efectivo'!H7+'Flujo de efectivo'!H8+'Flujo de efectivo'!H9) | I14: =('Flujo de efectivo'!I7+'Flujo de efectivo'!I8+'Flujo de efectivo'!I9) | ... AA14: =('Flujo de efectivo'!AA7+'Flujo de efectivo'!AA8+'Flujo de efectivo'!AA9) | AC14: =('Flujo de efectivo'!AC7+'Flujo de efectivo'!AC8+'Flujo de efectivo'!AC9) | AD14: =('Flujo de efectivo'!AD7+'Flujo de efectivo'!AD8+'Flujo de efectivo'!AD9) | AE14: =('Flujo de efectivo'!AE7+'Flujo de efectivo'!AE8+'Flujo de efectivo'!AE9) | AF14: =('Flujo de efectivo'!AF7+'Flujo de efectivo'!AF8+'Flujo de efectivo'!AF9) | AG14: =('Flujo de efectivo'!AG7+'Flujo de efectivo'!AG8+'Flujo de efectivo'!AG9) | AH14: =('Flujo de efectivo'!AH7+'Flujo de efectivo'!AH8+'Flujo de efectivo'!AH9) | AI14: =('Flujo de efectivo'!AI7+'Flujo de efectivo'!AI8+'Flujo de efectivo'!AI9)
A15: Flujo de caja libre (operativo − capex) | B15: ='Flujo de efectivo'!B33+'Flujo de efectivo'!B34 | C15: ='Flujo de efectivo'!C33+'Flujo de efectivo'!C34 | D15: ='Flujo de efectivo'!D33+'Flujo de efectivo'!D34 | E15: ='Flujo de efectivo'!E33+'Flujo de efectivo'!E34 | F15: ='Flujo de efectivo'!F33+'Flujo de efectivo'!F34 | G15: ='Flujo de efectivo'!G33+'Flujo de efectivo'!G34 | H15: ='Flujo de efectivo'!H33+'Flujo de efectivo'!H34 | I15: ='Flujo de efectivo'!I33+'Flujo de efectivo'!I34 | ... AA15: ='Flujo de efectivo'!AA33+'Flujo de efectivo'!AA34 | AC15: ='Flujo de efectivo'!AC33+'Flujo de efectivo'!AC34 | AD15: ='Flujo de efectivo'!AD33+'Flujo de efectivo'!AD34 | AE15: ='Flujo de efectivo'!AE33+'Flujo de efectivo'!AE34 | AF15: ='Flujo de efectivo'!AF33+'Flujo de efectivo'!AF34 | AG15: ='Flujo de efectivo'!AG33+'Flujo de efectivo'!AG34 | AH15: ='Flujo de efectivo'!AH33+'Flujo de efectivo'!AH34 | AI15: ='Flujo de efectivo'!AI33+'Flujo de efectivo'!AI34 | AK15: El capex viene con signo negativo en el estado de flujo, así que se suma.
A16: Deuda financiera bruta | B16: =IF(COUNT(('Balance'!B43+'Balance'!B54))=0,"",('Balance'!B43+'Balance'!B54)) | C16: =IF(COUNT(('Balance'!C43+'Balance'!C54))=0,"",('Balance'!C43+'Balance'!C54)) | D16: =IF(COUNT(('Balance'!D43+'Balance'!D54))=0,"",('Balance'!D43+'Balance'!D54)) | E16: =IF(COUNT(('Balance'!E43+'Balance'!E54))=0,"",('Balance'!E43+'Balance'!E54)) | F16: =IF(COUNT(('Balance'!F43+'Balance'!F54))=0,"",('Balance'!F43+'Balance'!F54)) | G16: =IF(COUNT(('Balance'!G43+'Balance'!G54))=0,"",('Balance'!G43+'Balance'!G54)) | H16: =IF(COUNT(('Balance'!H43+'Balance'!H54))=0,"",('Balance'!H43+'Balance'!H54)) | I16: =IF(COUNT(('Balance'!I43+'Balance'!I54))=0,"",('Balance'!I43+'Balance'!I54)) | ... AA16: =IF(COUNT(('Balance'!AA43+'Balance'!AA54))=0,"",('Balance'!AA43+'Balance'!AA54)) | AC16: =IF(COUNT(('Balance'!AC43+'Balance'!AC54))=0,"",('Balance'!AC43+'Balance'!AC54)) | AD16: =IF(COUNT(('Balance'!AD43+'Balance'!AD54))=0,"",('Balance'!AD43+'Balance'!AD54)) | AE16: =IF(COUNT(('Balance'!AE43+'Balance'!AE54))=0,"",('Balance'!AE43+'Balance'!AE54)) | AF16: =IF(COUNT(('Balance'!AF43+'Balance'!AF54))=0,"",('Balance'!AF43+'Balance'!AF54)) | AG16: =IF(COUNT(('Balance'!AG43+'Balance'!AG54))=0,"",('Balance'!AG43+'Balance'!AG54)) | AH16: =IF(COUNT(('Balance'!AH43+'Balance'!AH54))=0,"",('Balance'!AH43+'Balance'!AH54)) | AI16: =IF(COUNT(('Balance'!AI43+'Balance'!AI54))=0,"",('Balance'!AI43+'Balance'!AI54)) | AK16: Préstamos corrientes y no corrientes. No incluye pasivos por arrendamiento.
A17: Deuda financiera neta | B17: =IF(COUNT('Balance'!B19)=0,"",('Balance'!B43+'Balance'!B54)-'Balance'!B19-'Balance'!B18) | C17: =IF(COUNT('Balance'!C19)=0,"",('Balance'!C43+'Balance'!C54)-'Balance'!C19-'Balance'!C18) | D17: =IF(COUNT('Balance'!D19)=0,"",('Balance'!D43+'Balance'!D54)-'Balance'!D19-'Balance'!D18) | E17: =IF(COUNT('Balance'!E19)=0,"",('Balance'!E43+'Balance'!E54)-'Balance'!E19-'Balance'!E18) | F17: =IF(COUNT('Balance'!F19)=0,"",('Balance'!F43+'Balance'!F54)-'Balance'!F19-'Balance'!F18) | G17: =IF(COUNT('Balance'!G19)=0,"",('Balance'!G43+'Balance'!G54)-'Balance'!G19-'Balance'!G18) | H17: =IF(COUNT('Balance'!H19)=0,"",('Balance'!H43+'Balance'!H54)-'Balance'!H19-'Balance'!H18) | I17: =IF(COUNT('Balance'!I19)=0,"",('Balance'!I43+'Balance'!I54)-'Balance'!I19-'Balance'!I18) | ... AA17: =IF(COUNT('Balance'!AA19)=0,"",('Balance'!AA43+'Balance'!AA54)-'Balance'!AA19-'Balance'!AA18) | AC17: =IF(COUNT('Balance'!AC19)=0,"",('Balance'!AC43+'Balance'!AC54)-'Balance'!AC19-'Balance'!AC18) | AD17: =IF(COUNT('Balance'!AD19)=0,"",('Balance'!AD43+'Balance'!AD54)-'Balance'!AD19-'Balance'!AD18) | AE17: =IF(COUNT('Balance'!AE19)=0,"",('Balance'!AE43+'Balance'!AE54)-'Balance'!AE19-'Balance'!AE18) | AF17: =IF(COUNT('Balance'!AF19)=0,"",('Balance'!AF43+'Balance'!AF54)-'Balance'!AF19-'Balance'!AF18) | AG17: =IF(COUNT('Balance'!AG19)=0,"",('Balance'!AG43+'Balance'!AG54)-'Balance'!AG19-'Balance'!AG18) | AH17: =IF(COUNT('Balance'!AH19)=0,"",('Balance'!AH43+'Balance'!AH54)-'Balance'!AH19-'Balance'!AH18) | AI17: =IF(COUNT('Balance'!AI19)=0,"",('Balance'!AI43+'Balance'!AI54)-'Balance'!AI19-'Balance'!AI18) | AK17: Neta de caja y de inversiones financieras corrientes.
A18: Deuda financiera neta + arrendamientos | B18: =IF(COUNT('Balance'!B19)=0,"",('Balance'!B43+'Balance'!B54)+('Balance'!B42+'Balance'!B53)-'Balance'!B19-'Balance'!B18) | C18: =IF(COUNT('Balance'!C19)=0,"",('Balance'!C43+'Balance'!C54)+('Balance'!C42+'Balance'!C53)-'Balance'!C19-'Balance'!C18) | D18: =IF(COUNT('Balance'!D19)=0,"",('Balance'!D43+'Balance'!D54)+('Balance'!D42+'Balance'!D53)-'Balance'!D19-'Balance'!D18) | E18: =IF(COUNT('Balance'!E19)=0,"",('Balance'!E43+'Balance'!E54)+('Balance'!E42+'Balance'!E53)-'Balance'!E19-'Balance'!E18) | F18: =IF(COUNT('Balance'!F19)=0,"",('Balance'!F43+'Balance'!F54)+('Balance'!F42+'Balance'!F53)-'Balance'!F19-'Balance'!F18) | G18: =IF(COUNT('Balance'!G19)=0,"",('Balance'!G43+'Balance'!G54)+('Balance'!G42+'Balance'!G53)-'Balance'!G19-'Balance'!G18) | H18: =IF(COUNT('Balance'!H19)=0,"",('Balance'!H43+'Balance'!H54)+('Balance'!H42+'Balance'!H53)-'Balance'!H19-'Balance'!H18) | I18: =IF(COUNT('Balance'!I19)=0,"",('Balance'!I43+'Balance'!I54)+('Balance'!I42+'Balance'!I53)-'Balance'!I19-'Balance'!I18) | ... AA18: =IF(COUNT('Balance'!AA19)=0,"",('Balance'!AA43+'Balance'!AA54)+('Balance'!AA42+'Balance'!AA53)-'Balance'!AA19-'Balance'!AA18) | AC18: =IF(COUNT('Balance'!AC19)=0,"",('Balance'!AC43+'Balance'!AC54)+('Balance'!AC42+'Balance'!AC53)-'Balance'!AC19-'Balance'!AC18) | AD18: =IF(COUNT('Balance'!AD19)=0,"",('Balance'!AD43+'Balance'!AD54)+('Balance'!AD42+'Balance'!AD53)-'Balance'!AD19-'Balance'!AD18) | AE18: =IF(COUNT('Balance'!AE19)=0,"",('Balance'!AE43+'Balance'!AE54)+('Balance'!AE42+'Balance'!AE53)-'Balance'!AE19-'Balance'!AE18) | AF18: =IF(COUNT('Balance'!AF19)=0,"",('Balance'!AF43+'Balance'!AF54)+('Balance'!AF42+'Balance'!AF53)-'Balance'!AF19-'Balance'!AF18) | AG18: =IF(COUNT('Balance'!AG19)=0,"",('Balance'!AG43+'Balance'!AG54)+('Balance'!AG42+'Balance'!AG53)-'Balance'!AG19-'Balance'!AG18) | AH18: =IF(COUNT('Balance'!AH19)=0,"",('Balance'!AH43+'Balance'!AH54)+('Balance'!AH42+'Balance'!AH53)-'Balance'!AH19-'Balance'!AH18) | AI18: =IF(COUNT('Balance'!AI19)=0,"",('Balance'!AI43+'Balance'!AI54)+('Balance'!AI42+'Balance'!AI53)-'Balance'!AI19-'Balance'!AI18)
A19: Capital invertido (deuda neta + patrimonio) | B19: =IF(COUNT('Balance'!B19)=0,"",('Balance'!B43+'Balance'!B54)-'Balance'!B19-'Balance'!B18+'Balance'!B35) | C19: =IF(COUNT('Balance'!C19)=0,"",('Balance'!C43+'Balance'!C54)-'Balance'!C19-'Balance'!C18+'Balance'!C35) | D19: =IF(COUNT('Balance'!D19)=0,"",('Balance'!D43+'Balance'!D54)-'Balance'!D19-'Balance'!D18+'Balance'!D35) | E19: =IF(COUNT('Balance'!E19)=0,"",('Balance'!E43+'Balance'!E54)-'Balance'!E19-'Balance'!E18+'Balance'!E35) | F19: =IF(COUNT('Balance'!F19)=0,"",('Balance'!F43+'Balance'!F54)-'Balance'!F19-'Balance'!F18+'Balance'!F35) | G19: =IF(COUNT('Balance'!G19)=0,"",('Balance'!G43+'Balance'!G54)-'Balance'!G19-'Balance'!G18+'Balance'!G35) | H19: =IF(COUNT('Balance'!H19)=0,"",('Balance'!H43+'Balance'!H54)-'Balance'!H19-'Balance'!H18+'Balance'!H35) | I19: =IF(COUNT('Balance'!I19)=0,"",('Balance'!I43+'Balance'!I54)-'Balance'!I19-'Balance'!I18+'Balance'!I35) | ... AA19: =IF(COUNT('Balance'!AA19)=0,"",('Balance'!AA43+'Balance'!AA54)-'Balance'!AA19-'Balance'!AA18+'Balance'!AA35) | AC19: =IF(COUNT('Balance'!AC19)=0,"",('Balance'!AC43+'Balance'!AC54)-'Balance'!AC19-'Balance'!AC18+'Balance'!AC35) | AD19: =IF(COUNT('Balance'!AD19)=0,"",('Balance'!AD43+'Balance'!AD54)-'Balance'!AD19-'Balance'!AD18+'Balance'!AD35) | AE19: =IF(COUNT('Balance'!AE19)=0,"",('Balance'!AE43+'Balance'!AE54)-'Balance'!AE19-'Balance'!AE18+'Balance'!AE35) | AF19: =IF(COUNT('Balance'!AF19)=0,"",('Balance'!AF43+'Balance'!AF54)-'Balance'!AF19-'Balance'!AF18+'Balance'!AF35) | AG19: =IF(COUNT('Balance'!AG19)=0,"",('Balance'!AG43+'Balance'!AG54)-'Balance'!AG19-'Balance'!AG18+'Balance'!AG35) | AH19: =IF(COUNT('Balance'!AH19)=0,"",('Balance'!AH43+'Balance'!AH54)-'Balance'!AH19-'Balance'!AH18+'Balance'!AH35) | AI19: =IF(COUNT('Balance'!AI19)=0,"",('Balance'!AI43+'Balance'!AI54)-'Balance'!AI19-'Balance'!AI18+'Balance'!AI35)
A21: Últimos doce meses
A22: EBITDA UDM | E22: =('Resultados'!E13+('Flujo de efectivo'!E7+'Flujo de efectivo'!E8+'Flujo de efectivo'!E9))+('Resultados'!D13+('Flujo de efectivo'!D7+'Flujo de efectivo'!D8+'Flujo de efectivo'!D9))+('Resultados'!C13+('Flujo de efectivo'!C7+'Flujo de efectivo'!C8+'Flujo de efectivo'!C9))+('Resultados'!B13+('Flujo de efectivo'!B7+'Flujo de efectivo'!B8+'Flujo de efectivo'!B9)) | F22: =('Resultados'!F13+('Flujo de efectivo'!F7+'Flujo de efectivo'!F8+'Flujo de efectivo'!F9))+('Resultados'!E13+('Flujo de efectivo'!E7+'Flujo de efectivo'!E8+'Flujo de efectivo'!E9))+('Resultados'!D13+('Flujo de efectivo'!D7+'Flujo de efectivo'!D8+'Flujo de efectivo'!D9))+('Resultados'!C13+('Flujo de efectivo'!C7+'Flujo de efectivo'!C8+'Flujo de efectivo'!C9)) | G22: =('Resultados'!G13+('Flujo de efectivo'!G7+'Flujo de efectivo'!G8+'Flujo de efectivo'!G9))+('Resultados'!F13+('Flujo de efectivo'!F7+'Flujo de efectivo'!F8+'Flujo de efectivo'!F9))+('Resultados'!E13+('Flujo de efectivo'!E7+'Flujo de efectivo'!E8+'Flujo de efectivo'!E9))+('Resultados'!D13+('Flujo de efectivo'!D7+'Flujo de efectivo'!D8+'Flujo de efectivo'!D9)) | H22: =('Resultados'!H13+('Flujo de efectivo'!H7+'Flujo de efectivo'!H8+'Flujo de efectivo'!H9))+('Resultados'!G13+('Flujo de efectivo'!G7+'Flujo de efectivo'!G8+'Flujo de efectivo'!G9))+('Resultados'!F13+('Flujo de efectivo'!F7+'Flujo de efectivo'!F8+'Flujo de efectivo'!F9))+('Resultados'!E13+('Flujo de efectivo'!E7+'Flujo de efectivo'!E8+'Flujo de efectivo'!E9)) | I22: =('Resultados'!I13+('Flujo de efectivo'!I7+'Flujo de efectivo'!I8+'Flujo de efectivo'!I9))+('Resultados'!H13+('Flujo de efectivo'!H7+'Flujo de efectivo'!H8+'Flujo de efectivo'!H9))+('Resultados'!G13+('Flujo de efectivo'!G7+'Flujo de efectivo'!G8+'Flujo de efectivo'!G9))+('Resultados'!F13+('Flujo de efectivo'!F7+'Flujo de efectivo'!F8+'Flujo de efectivo'!F9)) | J22: =('Resultados'!J13+('Flujo de efectivo'!J7+'Flujo de efectivo'!J8+'Flujo de efectivo'!J9))+('Resultados'!I13+('Flujo de efectivo'!I7+'Flujo de efectivo'!I8+'Flujo de efectivo'!I9))+('Resultados'!H13+('Flujo de efectivo'!H7+'Flujo de efectivo'!H8+'Flujo de efectivo'!H9))+('Resultados'!G13+('Flujo de efectivo'!G7+'Flujo de efectivo'!G8+'Flujo de efectivo'!G9)) | K22: =('Resultados'!K13+('Flujo de efectivo'!K7+'Flujo de efectivo'!K8+'Flujo de efectivo'!K9))+('Resultados'!J13+('Flujo de efectivo'!J7+'Flujo de efectivo'!J8+'Flujo de efectivo'!J9))+('Resultados'!I13+('Flujo de efectivo'!I7+'Flujo de efectivo'!I8+'Flujo de efectivo'!I9))+('Resultados'!H13+('Flujo de efectivo'!H7+'Flujo de efectivo'!H8+'Flujo de efectivo'!H9)) | L22: =('Resultados'!L13+('Flujo de efectivo'!L7+'Flujo de efectivo'!L8+'Flujo de efectivo'!L9))+('Resultados'!K13+('Flujo de efectivo'!K7+'Flujo de efectivo'!K8+'Flujo de efectivo'!K9))+('Resultados'!J13+('Flujo de efectivo'!J7+'Flujo de efectivo'!J8+'Flujo de efectivo'!J9))+('Resultados'!I13+('Flujo de efectivo'!I7+'Flujo de efectivo'!I8+'Flujo de efectivo'!I9)) | ... AA22: =('Resultados'!AA13+('Flujo de efectivo'!AA7+'Flujo de efectivo'!AA8+'Flujo de efectivo'!AA9))+('Resultados'!Z13+('Flujo de efectivo'!Z7+'Flujo de efectivo'!Z8+'Flujo de efectivo'!Z9))+('Resultados'!Y13+('Flujo de efectivo'!Y7+'Flujo de efectivo'!Y8+'Flujo de efectivo'!Y9))+('Resultados'!X13+('Flujo de efectivo'!X7+'Flujo de efectivo'!X8+'Flujo de efectivo'!X9))
A23: Resultado neto UDM | E23: ='Resultados'!E21+'Resultados'!D21+'Resultados'!C21+'Resultados'!B21 | F23: ='Resultados'!F21+'Resultados'!E21+'Resultados'!D21+'Resultados'!C21 | G23: ='Resultados'!G21+'Resultados'!F21+'Resultados'!E21+'Resultados'!D21 | H23: ='Resultados'!H21+'Resultados'!G21+'Resultados'!F21+'Resultados'!E21 | I23: ='Resultados'!I21+'Resultados'!H21+'Resultados'!G21+'Resultados'!F21 | J23: ='Resultados'!J21+'Resultados'!I21+'Resultados'!H21+'Resultados'!G21 | K23: ='Resultados'!K21+'Resultados'!J21+'Resultados'!I21+'Resultados'!H21 | L23: ='Resultados'!L21+'Resultados'!K21+'Resultados'!J21+'Resultados'!I21 | ... AA23: ='Resultados'!AA21+'Resultados'!Z21+'Resultados'!Y21+'Resultados'!X21
A24: Flujo operativo UDM | E24: ='Flujo de efectivo'!E33+'Flujo de efectivo'!D33+'Flujo de efectivo'!C33+'Flujo de efectivo'!B33 | F24: ='Flujo de efectivo'!F33+'Flujo de efectivo'!E33+'Flujo de efectivo'!D33+'Flujo de efectivo'!C33 | G24: ='Flujo de efectivo'!G33+'Flujo de efectivo'!F33+'Flujo de efectivo'!E33+'Flujo de efectivo'!D33 | H24: ='Flujo de efectivo'!H33+'Flujo de efectivo'!G33+'Flujo de efectivo'!F33+'Flujo de efectivo'!E33 | I24: ='Flujo de efectivo'!I33+'Flujo de efectivo'!H33+'Flujo de efectivo'!G33+'Flujo de efectivo'!F33 | J24: ='Flujo de efectivo'!J33+'Flujo de efectivo'!I33+'Flujo de efectivo'!H33+'Flujo de efectivo'!G33 | K24: ='Flujo de efectivo'!K33+'Flujo de efectivo'!J33+'Flujo de efectivo'!I33+'Flujo de efectivo'!H33 | L24: ='Flujo de efectivo'!L33+'Flujo de efectivo'!K33+'Flujo de efectivo'!J33+'Flujo de efectivo'!I33 | ... AA24: ='Flujo de efectivo'!AA33+'Flujo de efectivo'!Z33+'Flujo de efectivo'!Y33+'Flujo de efectivo'!X33
A25: Ingresos UDM | E25: ='Resultados'!E5+'Resultados'!D5+'Resultados'!C5+'Resultados'!B5 | F25: ='Resultados'!F5+'Resultados'!E5+'Resultados'!D5+'Resultados'!C5 | G25: ='Resultados'!G5+'Resultados'!F5+'Resultados'!E5+'Resultados'!D5 | H25: ='Resultados'!H5+'Resultados'!G5+'Resultados'!F5+'Resultados'!E5 | I25: ='Resultados'!I5+'Resultados'!H5+'Resultados'!G5+'Resultados'!F5 | J25: ='Resultados'!J5+'Resultados'!I5+'Resultados'!H5+'Resultados'!G5 | K25: ='Resultados'!K5+'Resultados'!J5+'Resultados'!I5+'Resultados'!H5 | L25: ='Resultados'!L5+'Resultados'!K5+'Resultados'!J5+'Resultados'!I5 | ... AA25: ='Resultados'!AA5+'Resultados'!Z5+'Resultados'!Y5+'Resultados'!X5
A26: Resultado operativo UDM | E26: ='Resultados'!E13+'Resultados'!D13+'Resultados'!C13+'Resultados'!B13 | F26: ='Resultados'!F13+'Resultados'!E13+'Resultados'!D13+'Resultados'!C13 | G26: ='Resultados'!G13+'Resultados'!F13+'Resultados'!E13+'Resultados'!D13 | H26: ='Resultados'!H13+'Resultados'!G13+'Resultados'!F13+'Resultados'!E13 | I26: ='Resultados'!I13+'Resultados'!H13+'Resultados'!G13+'Resultados'!F13 | J26: ='Resultados'!J13+'Resultados'!I13+'Resultados'!H13+'Resultados'!G13 | K26: ='Resultados'!K13+'Resultados'!J13+'Resultados'!I13+'Resultados'!H13 | L26: ='Resultados'!L13+'Resultados'!K13+'Resultados'!J13+'Resultados'!I13 | ... AA26: ='Resultados'!AA13+'Resultados'!Z13+'Resultados'!Y13+'Resultados'!X13
A27: Resultado antes de impuesto UDM | E27: ='Resultados'!E19+'Resultados'!D19+'Resultados'!C19+'Resultados'!B19 | F27: ='Resultados'!F19+'Resultados'!E19+'Resultados'!D19+'Resultados'!C19 | G27: ='Resultados'!G19+'Resultados'!F19+'Resultados'!E19+'Resultados'!D19 | H27: ='Resultados'!H19+'Resultados'!G19+'Resultados'!F19+'Resultados'!E19 | I27: ='Resultados'!I19+'Resultados'!H19+'Resultados'!G19+'Resultados'!F19 | J27: ='Resultados'!J19+'Resultados'!I19+'Resultados'!H19+'Resultados'!G19 | K27: ='Resultados'!K19+'Resultados'!J19+'Resultados'!I19+'Resultados'!H19 | L27: ='Resultados'!L19+'Resultados'!K19+'Resultados'!J19+'Resultados'!I19 | ... AA27: ='Resultados'!AA19+'Resultados'!Z19+'Resultados'!Y19+'Resultados'!X19
A28: Impuesto a las ganancias UDM | E28: ='Resultados'!E20+'Resultados'!D20+'Resultados'!C20+'Resultados'!B20 | F28: ='Resultados'!F20+'Resultados'!E20+'Resultados'!D20+'Resultados'!C20 | G28: ='Resultados'!G20+'Resultados'!F20+'Resultados'!E20+'Resultados'!D20 | H28: ='Resultados'!H20+'Resultados'!G20+'Resultados'!F20+'Resultados'!E20 | I28: ='Resultados'!I20+'Resultados'!H20+'Resultados'!G20+'Resultados'!F20 | J28: ='Resultados'!J20+'Resultados'!I20+'Resultados'!H20+'Resultados'!G20 | K28: ='Resultados'!K20+'Resultados'!J20+'Resultados'!I20+'Resultados'!H20 | L28: ='Resultados'!L20+'Resultados'!K20+'Resultados'!J20+'Resultados'!I20 | ... AA28: ='Resultados'!AA20+'Resultados'!Z20+'Resultados'!Y20+'Resultados'!X20
A29: Capex UDM | E29: ='Flujo de efectivo'!E34+'Flujo de efectivo'!D34+'Flujo de efectivo'!C34+'Flujo de efectivo'!B34 | F29: ='Flujo de efectivo'!F34+'Flujo de efectivo'!E34+'Flujo de efectivo'!D34+'Flujo de efectivo'!C34 | G29: ='Flujo de efectivo'!G34+'Flujo de efectivo'!F34+'Flujo de efectivo'!E34+'Flujo de efectivo'!D34 | H29: ='Flujo de efectivo'!H34+'Flujo de efectivo'!G34+'Flujo de efectivo'!F34+'Flujo de efectivo'!E34 | I29: ='Flujo de efectivo'!I34+'Flujo de efectivo'!H34+'Flujo de efectivo'!G34+'Flujo de efectivo'!F34 | J29: ='Flujo de efectivo'!J34+'Flujo de efectivo'!I34+'Flujo de efectivo'!H34+'Flujo de efectivo'!G34 | K29: ='Flujo de efectivo'!K34+'Flujo de efectivo'!J34+'Flujo de efectivo'!I34+'Flujo de efectivo'!H34 | L29: ='Flujo de efectivo'!L34+'Flujo de efectivo'!K34+'Flujo de efectivo'!J34+'Flujo de efectivo'!I34 | ... AA29: ='Flujo de efectivo'!AA34+'Flujo de efectivo'!Z34+'Flujo de efectivo'!Y34+'Flujo de efectivo'!X34
A30: Costos financieros UDM | E30: ='Resultados'!E16+'Resultados'!D16+'Resultados'!C16+'Resultados'!B16 | F30: ='Resultados'!F16+'Resultados'!E16+'Resultados'!D16+'Resultados'!C16 | G30: ='Resultados'!G16+'Resultados'!F16+'Resultados'!E16+'Resultados'!D16 | H30: ='Resultados'!H16+'Resultados'!G16+'Resultados'!F16+'Resultados'!E16 | I30: ='Resultados'!I16+'Resultados'!H16+'Resultados'!G16+'Resultados'!F16 | J30: ='Resultados'!J16+'Resultados'!I16+'Resultados'!H16+'Resultados'!G16 | K30: ='Resultados'!K16+'Resultados'!J16+'Resultados'!I16+'Resultados'!H16 | L30: ='Resultados'!L16+'Resultados'!K16+'Resultados'!J16+'Resultados'!I16 | ... AA30: ='Resultados'!AA16+'Resultados'!Z16+'Resultados'!Y16+'Resultados'!X16
A32: Retornos
A33: ROE (UDM sobre patrimonio promedio) | F33: =IF(COUNT('Balance'!F35,'Balance'!B35)<2,"",IFERROR(F23/AVERAGE('Balance'!F35,'Balance'!B35),"")) | G33: =IF(COUNT('Balance'!G35,'Balance'!C35)<2,"",IFERROR(G23/AVERAGE('Balance'!G35,'Balance'!C35),"")) | H33: =IF(COUNT('Balance'!H35,'Balance'!D35)<2,"",IFERROR(H23/AVERAGE('Balance'!H35,'Balance'!D35),"")) | I33: =IF(COUNT('Balance'!I35,'Balance'!E35)<2,"",IFERROR(I23/AVERAGE('Balance'!I35,'Balance'!E35),"")) | J33: =IF(COUNT('Balance'!J35,'Balance'!F35)<2,"",IFERROR(J23/AVERAGE('Balance'!J35,'Balance'!F35),"")) | K33: =IF(COUNT('Balance'!K35,'Balance'!G35)<2,"",IFERROR(K23/AVERAGE('Balance'!K35,'Balance'!G35),"")) | L33: =IF(COUNT('Balance'!L35,'Balance'!H35)<2,"",IFERROR(L23/AVERAGE('Balance'!L35,'Balance'!H35),"")) | M33: =IF(COUNT('Balance'!M35,'Balance'!I35)<2,"",IFERROR(M23/AVERAGE('Balance'!M35,'Balance'!I35),"")) | ... AA33: =IF(COUNT('Balance'!AA35,'Balance'!W35)<2,"",IFERROR(AA23/AVERAGE('Balance'!AA35,'Balance'!W35),""))
A34: ROA (UDM sobre activo promedio) | F34: =IF(COUNT('Balance'!F21,'Balance'!B21)<2,"",IFERROR(F23/AVERAGE('Balance'!F21,'Balance'!B21),"")) | G34: =IF(COUNT('Balance'!G21,'Balance'!C21)<2,"",IFERROR(G23/AVERAGE('Balance'!G21,'Balance'!C21),"")) | H34: =IF(COUNT('Balance'!H21,'Balance'!D21)<2,"",IFERROR(H23/AVERAGE('Balance'!H21,'Balance'!D21),"")) | I34: =IF(COUNT('Balance'!I21,'Balance'!E21)<2,"",IFERROR(I23/AVERAGE('Balance'!I21,'Balance'!E21),"")) | J34: =IF(COUNT('Balance'!J21,'Balance'!F21)<2,"",IFERROR(J23/AVERAGE('Balance'!J21,'Balance'!F21),"")) | K34: =IF(COUNT('Balance'!K21,'Balance'!G21)<2,"",IFERROR(K23/AVERAGE('Balance'!K21,'Balance'!G21),"")) | L34: =IF(COUNT('Balance'!L21,'Balance'!H21)<2,"",IFERROR(L23/AVERAGE('Balance'!L21,'Balance'!H21),"")) | M34: =IF(COUNT('Balance'!M21,'Balance'!I21)<2,"",IFERROR(M23/AVERAGE('Balance'!M21,'Balance'!I21),"")) | ... AA34: =IF(COUNT('Balance'!AA21,'Balance'!W21)<2,"",IFERROR(AA23/AVERAGE('Balance'!AA21,'Balance'!W21),""))
A35: ROIC (NOPAT UDM sobre capital invertido promedio) | F35: =IF(COUNT(F19,B19)<2,"",IFERROR(F26*(1-MIN(MAX(IF(F27<=0,0.35,-F28/F27),0),0.6))/AVERAGE(F19,B19),"")) | G35: =IF(COUNT(G19,C19)<2,"",IFERROR(G26*(1-MIN(MAX(IF(G27<=0,0.35,-G28/G27),0),0.6))/AVERAGE(G19,C19),"")) | H35: =IF(COUNT(H19,D19)<2,"",IFERROR(H26*(1-MIN(MAX(IF(H27<=0,0.35,-H28/H27),0),0.6))/AVERAGE(H19,D19),"")) | I35: =IF(COUNT(I19,E19)<2,"",IFERROR(I26*(1-MIN(MAX(IF(I27<=0,0.35,-I28/I27),0),0.6))/AVERAGE(I19,E19),"")) | J35: =IF(COUNT(J19,F19)<2,"",IFERROR(J26*(1-MIN(MAX(IF(J27<=0,0.35,-J28/J27),0),0.6))/AVERAGE(J19,F19),"")) | K35: =IF(COUNT(K19,G19)<2,"",IFERROR(K26*(1-MIN(MAX(IF(K27<=0,0.35,-K28/K27),0),0.6))/AVERAGE(K19,G19),"")) | L35: =IF(COUNT(L19,H19)<2,"",IFERROR(L26*(1-MIN(MAX(IF(L27<=0,0.35,-L28/L27),0),0.6))/AVERAGE(L19,H19),"")) | M35: =IF(COUNT(M19,I19)<2,"",IFERROR(M26*(1-MIN(MAX(IF(M27<=0,0.35,-M28/M27),0),0.6))/AVERAGE(M19,I19),"")) | ... AA35: =IF(COUNT(AA19,W19)<2,"",IFERROR(AA26*(1-MIN(MAX(IF(AA27<=0,0.35,-AA28/AA27),0),0.6))/AVERAGE(AA19,W19),"")) | AK35: Tasa efectiva de los últimos doce meses, acotada entre 0% y 60%. Con resultado antes de impuesto negativo se usa 35%, la tasa societaria argentina.
A37: Estructura de capital
A38: Deuda neta / EBITDA UDM | E38: =IFERROR((('Balance'!E43+'Balance'!E54)-'Balance'!E19-'Balance'!E18)/E22,"") | F38: =IFERROR((('Balance'!F43+'Balance'!F54)-'Balance'!F19-'Balance'!F18)/F22,"") | G38: =IFERROR((('Balance'!G43+'Balance'!G54)-'Balance'!G19-'Balance'!G18)/G22,"") | H38: =IFERROR((('Balance'!H43+'Balance'!H54)-'Balance'!H19-'Balance'!H18)/H22,"") | I38: =IFERROR((('Balance'!I43+'Balance'!I54)-'Balance'!I19-'Balance'!I18)/I22,"") | J38: =IFERROR((('Balance'!J43+'Balance'!J54)-'Balance'!J19-'Balance'!J18)/J22,"") | K38: =IFERROR((('Balance'!K43+'Balance'!K54)-'Balance'!K19-'Balance'!K18)/K22,"") | L38: =IFERROR((('Balance'!L43+'Balance'!L54)-'Balance'!L19-'Balance'!L18)/L22,"") | ... AA38: =IFERROR((('Balance'!AA43+'Balance'!AA54)-'Balance'!AA19-'Balance'!AA18)/AA22,"")
A39: Deuda bruta / patrimonio | B39: =IFERROR(('Balance'!B43+'Balance'!B54)/'Balance'!B35,"") | C39: =IFERROR(('Balance'!C43+'Balance'!C54)/'Balance'!C35,"") | D39: =IFERROR(('Balance'!D43+'Balance'!D54)/'Balance'!D35,"") | E39: =IFERROR(('Balance'!E43+'Balance'!E54)/'Balance'!E35,"") | F39: =IFERROR(('Balance'!F43+'Balance'!F54)/'Balance'!F35,"") | G39: =IFERROR(('Balance'!G43+'Balance'!G54)/'Balance'!G35,"") | H39: =IFERROR(('Balance'!H43+'Balance'!H54)/'Balance'!H35,"") | I39: =IFERROR(('Balance'!I43+'Balance'!I54)/'Balance'!I35,"") | ... AA39: =IFERROR(('Balance'!AA43+'Balance'!AA54)/'Balance'!AA35,"") | AC39: =IFERROR(('Balance'!AC43+'Balance'!AC54)/'Balance'!AC35,"") | AD39: =IFERROR(('Balance'!AD43+'Balance'!AD54)/'Balance'!AD35,"") | AE39: =IFERROR(('Balance'!AE43+'Balance'!AE54)/'Balance'!AE35,"") | AF39: =IFERROR(('Balance'!AF43+'Balance'!AF54)/'Balance'!AF35,"") | AG39: =IFERROR(('Balance'!AG43+'Balance'!AG54)/'Balance'!AG35,"") | AH39: =IFERROR(('Balance'!AH43+'Balance'!AH54)/'Balance'!AH35,"") | AI39: =IFERROR(('Balance'!AI43+'Balance'!AI54)/'Balance'!AI35,"")
A40: Pasivo / activo | B40: =IFERROR('Balance'!B58/'Balance'!B21,"") | C40: =IFERROR('Balance'!C58/'Balance'!C21,"") | D40: =IFERROR('Balance'!D58/'Balance'!D21,"") | E40: =IFERROR('Balance'!E58/'Balance'!E21,"") | F40: =IFERROR('Balance'!F58/'Balance'!F21,"") | G40: =IFERROR('Balance'!G58/'Balance'!G21,"") | H40: =IFERROR('Balance'!H58/'Balance'!H21,"") | I40: =IFERROR('Balance'!I58/'Balance'!I21,"") | ... AA40: =IFERROR('Balance'!AA58/'Balance'!AA21,"") | AC40: =IFERROR('Balance'!AC58/'Balance'!AC21,"") | AD40: =IFERROR('Balance'!AD58/'Balance'!AD21,"") | AE40: =IFERROR('Balance'!AE58/'Balance'!AE21,"") | AF40: =IFERROR('Balance'!AF58/'Balance'!AF21,"") | AG40: =IFERROR('Balance'!AG58/'Balance'!AG21,"") | AH40: =IFERROR('Balance'!AH58/'Balance'!AH21,"") | AI40: =IFERROR('Balance'!AI58/'Balance'!AI21,"")
A41: Cobertura de intereses (EBIT / costos financieros) | B41: =IFERROR('Resultados'!B13/-'Resultados'!B16,"") | C41: =IFERROR('Resultados'!C13/-'Resultados'!C16,"") | D41: =IFERROR('Resultados'!D13/-'Resultados'!D16,"") | E41: =IFERROR('Resultados'!E13/-'Resultados'!E16,"") | F41: =IFERROR('Resultados'!F13/-'Resultados'!F16,"") | G41: =IFERROR('Resultados'!G13/-'Resultados'!G16,"") | H41: =IFERROR('Resultados'!H13/-'Resultados'!H16,"") | I41: =IFERROR('Resultados'!I13/-'Resultados'!I16,"") | ... AA41: =IFERROR('Resultados'!AA13/-'Resultados'!AA16,"") | AC41: =IFERROR('Resultados'!AC13/-'Resultados'!AC16,"") | AD41: =IFERROR('Resultados'!AD13/-'Resultados'!AD16,"") | AE41: =IFERROR('Resultados'!AE13/-'Resultados'!AE16,"") | AF41: =IFERROR('Resultados'!AF13/-'Resultados'!AF16,"") | AG41: =IFERROR('Resultados'!AG13/-'Resultados'!AG16,"") | AH41: =IFERROR('Resultados'!AH13/-'Resultados'!AH16,"") | AI41: =IFERROR('Resultados'!AI13/-'Resultados'!AI16,"") | AK41: Costos financieros totales del estado de resultados, no solo intereses de deuda.
A43: Liquidez y capital de trabajo
A44: Liquidez corriente | B44: =IFERROR('Balance'!B20/'Balance'!B57,"") | C44: =IFERROR('Balance'!C20/'Balance'!C57,"") | D44: =IFERROR('Balance'!D20/'Balance'!D57,"") | E44: =IFERROR('Balance'!E20/'Balance'!E57,"") | F44: =IFERROR('Balance'!F20/'Balance'!F57,"") | G44: =IFERROR('Balance'!G20/'Balance'!G57,"") | H44: =IFERROR('Balance'!H20/'Balance'!H57,"") | I44: =IFERROR('Balance'!I20/'Balance'!I57,"") | ... AA44: =IFERROR('Balance'!AA20/'Balance'!AA57,"") | AC44: =IFERROR('Balance'!AC20/'Balance'!AC57,"") | AD44: =IFERROR('Balance'!AD20/'Balance'!AD57,"") | AE44: =IFERROR('Balance'!AE20/'Balance'!AE57,"") | AF44: =IFERROR('Balance'!AF20/'Balance'!AF57,"") | AG44: =IFERROR('Balance'!AG20/'Balance'!AG57,"") | AH44: =IFERROR('Balance'!AH20/'Balance'!AH57,"") | AI44: =IFERROR('Balance'!AI20/'Balance'!AI57,"")
A45: Prueba ácida | B45: =IFERROR(('Balance'!B20-'Balance'!B14)/'Balance'!B57,"") | C45: =IFERROR(('Balance'!C20-'Balance'!C14)/'Balance'!C57,"") | D45: =IFERROR(('Balance'!D20-'Balance'!D14)/'Balance'!D57,"") | E45: =IFERROR(('Balance'!E20-'Balance'!E14)/'Balance'!E57,"") | F45: =IFERROR(('Balance'!F20-'Balance'!F14)/'Balance'!F57,"") | G45: =IFERROR(('Balance'!G20-'Balance'!G14)/'Balance'!G57,"") | H45: =IFERROR(('Balance'!H20-'Balance'!H14)/'Balance'!H57,"") | I45: =IFERROR(('Balance'!I20-'Balance'!I14)/'Balance'!I57,"") | ... AA45: =IFERROR(('Balance'!AA20-'Balance'!AA14)/'Balance'!AA57,"") | AC45: =IFERROR(('Balance'!AC20-'Balance'!AC14)/'Balance'!AC57,"") | AD45: =IFERROR(('Balance'!AD20-'Balance'!AD14)/'Balance'!AD57,"") | AE45: =IFERROR(('Balance'!AE20-'Balance'!AE14)/'Balance'!AE57,"") | AF45: =IFERROR(('Balance'!AF20-'Balance'!AF14)/'Balance'!AF57,"") | AG45: =IFERROR(('Balance'!AG20-'Balance'!AG14)/'Balance'!AG57,"") | AH45: =IFERROR(('Balance'!AH20-'Balance'!AH14)/'Balance'!AH57,"") | AI45: =IFERROR(('Balance'!AI20-'Balance'!AI14)/'Balance'!AI57,"")
A46: Días de cobranza (DSO) | B46: =IFERROR('Balance'!B17*91.25/'Resultados'!B5,"") | C46: =IFERROR('Balance'!C17*91.25/'Resultados'!C5,"") | D46: =IFERROR('Balance'!D17*91.25/'Resultados'!D5,"") | E46: =IFERROR('Balance'!E17*91.25/'Resultados'!E5,"") | F46: =IFERROR('Balance'!F17*91.25/'Resultados'!F5,"") | G46: =IFERROR('Balance'!G17*91.25/'Resultados'!G5,"") | H46: =IFERROR('Balance'!H17*91.25/'Resultados'!H5,"") | I46: =IFERROR('Balance'!I17*91.25/'Resultados'!I5,"") | ... AA46: =IFERROR('Balance'!AA17*91.25/'Resultados'!AA5,"") | AC46: =IFERROR('Balance'!AC17*91.25/'Resultados'!AC5,"") | AD46: =IFERROR('Balance'!AD17*91.25/'Resultados'!AD5,"") | AE46: =IFERROR('Balance'!AE17*91.25/'Resultados'!AE5,"") | AF46: =IFERROR('Balance'!AF17*91.25/'Resultados'!AF5,"") | AG46: =IFERROR('Balance'!AG17*91.25/'Resultados'!AG5,"") | AH46: =IFERROR('Balance'!AH17*91.25/'Resultados'!AH5,"") | AI46: =IFERROR('Balance'!AI17*91.25/'Resultados'!AI5,"") | AK46: Sobre los ingresos del trimestre anualizados a 365 días.
A47: Días de inventario (DIO) | B47: =IFERROR('Balance'!B14*91.25/-'Resultados'!B6,"") | C47: =IFERROR('Balance'!C14*91.25/-'Resultados'!C6,"") | D47: =IFERROR('Balance'!D14*91.25/-'Resultados'!D6,"") | E47: =IFERROR('Balance'!E14*91.25/-'Resultados'!E6,"") | F47: =IFERROR('Balance'!F14*91.25/-'Resultados'!F6,"") | G47: =IFERROR('Balance'!G14*91.25/-'Resultados'!G6,"") | H47: =IFERROR('Balance'!H14*91.25/-'Resultados'!H6,"") | I47: =IFERROR('Balance'!I14*91.25/-'Resultados'!I6,"") | ... AA47: =IFERROR('Balance'!AA14*91.25/-'Resultados'!AA6,"") | AC47: =IFERROR('Balance'!AC14*91.25/-'Resultados'!AC6,"") | AD47: =IFERROR('Balance'!AD14*91.25/-'Resultados'!AD6,"") | AE47: =IFERROR('Balance'!AE14*91.25/-'Resultados'!AE6,"") | AF47: =IFERROR('Balance'!AF14*91.25/-'Resultados'!AF6,"") | AG47: =IFERROR('Balance'!AG14*91.25/-'Resultados'!AG6,"") | AH47: =IFERROR('Balance'!AH14*91.25/-'Resultados'!AH6,"") | AI47: =IFERROR('Balance'!AI14*91.25/-'Resultados'!AI6,"")
A48: Días de pago (DPO) | B48: =IFERROR('Balance'!B56*91.25/-'Resultados'!B6,"") | C48: =IFERROR('Balance'!C56*91.25/-'Resultados'!C6,"") | D48: =IFERROR('Balance'!D56*91.25/-'Resultados'!D6,"") | E48: =IFERROR('Balance'!E56*91.25/-'Resultados'!E6,"") | F48: =IFERROR('Balance'!F56*91.25/-'Resultados'!F6,"") | G48: =IFERROR('Balance'!G56*91.25/-'Resultados'!G6,"") | H48: =IFERROR('Balance'!H56*91.25/-'Resultados'!H6,"") | I48: =IFERROR('Balance'!I56*91.25/-'Resultados'!I6,"") | ... AA48: =IFERROR('Balance'!AA56*91.25/-'Resultados'!AA6,"") | AC48: =IFERROR('Balance'!AC56*91.25/-'Resultados'!AC6,"") | AD48: =IFERROR('Balance'!AD56*91.25/-'Resultados'!AD6,"") | AE48: =IFERROR('Balance'!AE56*91.25/-'Resultados'!AE6,"") | AF48: =IFERROR('Balance'!AF56*91.25/-'Resultados'!AF6,"") | AG48: =IFERROR('Balance'!AG56*91.25/-'Resultados'!AG6,"") | AH48: =IFERROR('Balance'!AH56*91.25/-'Resultados'!AH6,"") | AI48: =IFERROR('Balance'!AI56*91.25/-'Resultados'!AI6,"")
A50: Generación de caja
A51: Flujo operativo / ingresos | B51: =IFERROR('Flujo de efectivo'!B33/'Resultados'!B5,"") | C51: =IFERROR('Flujo de efectivo'!C33/'Resultados'!C5,"") | D51: =IFERROR('Flujo de efectivo'!D33/'Resultados'!D5,"") | E51: =IFERROR('Flujo de efectivo'!E33/'Resultados'!E5,"") | F51: =IFERROR('Flujo de efectivo'!F33/'Resultados'!F5,"") | G51: =IFERROR('Flujo de efectivo'!G33/'Resultados'!G5,"") | H51: =IFERROR('Flujo de efectivo'!H33/'Resultados'!H5,"") | I51: =IFERROR('Flujo de efectivo'!I33/'Resultados'!I5,"") | ... AA51: =IFERROR('Flujo de efectivo'!AA33/'Resultados'!AA5,"") | AC51: =IFERROR('Flujo de efectivo'!AC33/'Resultados'!AC5,"") | AD51: =IFERROR('Flujo de efectivo'!AD33/'Resultados'!AD5,"") | AE51: =IFERROR('Flujo de efectivo'!AE33/'Resultados'!AE5,"") | AF51: =IFERROR('Flujo de efectivo'!AF33/'Resultados'!AF5,"") | AG51: =IFERROR('Flujo de efectivo'!AG33/'Resultados'!AG5,"") | AH51: =IFERROR('Flujo de efectivo'!AH33/'Resultados'!AH5,"") | AI51: =IFERROR('Flujo de efectivo'!AI33/'Resultados'!AI5,"")
A52: Capex / D&A | B52: =IFERROR(-'Flujo de efectivo'!B34/('Flujo de efectivo'!B7+'Flujo de efectivo'!B8+'Flujo de efectivo'!B9),"") | C52: =IFERROR(-'Flujo de efectivo'!C34/('Flujo de efectivo'!C7+'Flujo de efectivo'!C8+'Flujo de efectivo'!C9),"") | D52: =IFERROR(-'Flujo de efectivo'!D34/('Flujo de efectivo'!D7+'Flujo de efectivo'!D8+'Flujo de efectivo'!D9),"") | E52: =IFERROR(-'Flujo de efectivo'!E34/('Flujo de efectivo'!E7+'Flujo de efectivo'!E8+'Flujo de efectivo'!E9),"") | F52: =IFERROR(-'Flujo de efectivo'!F34/('Flujo de efectivo'!F7+'Flujo de efectivo'!F8+'Flujo de efectivo'!F9),"") | G52: =IFERROR(-'Flujo de efectivo'!G34/('Flujo de efectivo'!G7+'Flujo de efectivo'!G8+'Flujo de efectivo'!G9),"") | H52: =IFERROR(-'Flujo de efectivo'!H34/('Flujo de efectivo'!H7+'Flujo de efectivo'!H8+'Flujo de efectivo'!H9),"") | I52: =IFERROR(-'Flujo de efectivo'!I34/('Flujo de efectivo'!I7+'Flujo de efectivo'!I8+'Flujo de efectivo'!I9),"") | ... AA52: =IFERROR(-'Flujo de efectivo'!AA34/('Flujo de efectivo'!AA7+'Flujo de efectivo'!AA8+'Flujo de efectivo'!AA9),"") | AC52: =IFERROR(-'Flujo de efectivo'!AC34/('Flujo de efectivo'!AC7+'Flujo de efectivo'!AC8+'Flujo de efectivo'!AC9),"") | AD52: =IFERROR(-'Flujo de efectivo'!AD34/('Flujo de efectivo'!AD7+'Flujo de efectivo'!AD8+'Flujo de efectivo'!AD9),"") | AE52: =IFERROR(-'Flujo de efectivo'!AE34/('Flujo de efectivo'!AE7+'Flujo de efectivo'!AE8+'Flujo de efectivo'!AE9),"") | AF52: =IFERROR(-'Flujo de efectivo'!AF34/('Flujo de efectivo'!AF7+'Flujo de efectivo'!AF8+'Flujo de efectivo'!AF9),"") | AG52: =IFERROR(-'Flujo de efectivo'!AG34/('Flujo de efectivo'!AG7+'Flujo de efectivo'!AG8+'Flujo de efectivo'!AG9),"") | AH52: =IFERROR(-'Flujo de efectivo'!AH34/('Flujo de efectivo'!AH7+'Flujo de efectivo'!AH8+'Flujo de efectivo'!AH9),"") | AI52: =IFERROR(-'Flujo de efectivo'!AI34/('Flujo de efectivo'!AI7+'Flujo de efectivo'!AI8+'Flujo de efectivo'!AI9),"") | AK52: Arriba de 1 la compañía está invirtiendo más de lo que consume su base de activos.
A53: Flujo de caja libre / EBITDA | B53: =IFERROR(('Flujo de efectivo'!B33+'Flujo de efectivo'!B34)/('Resultados'!B13+('Flujo de efectivo'!B7+'Flujo de efectivo'!B8+'Flujo de efectivo'!B9)),"") | C53: =IFERROR(('Flujo de efectivo'!C33+'Flujo de efectivo'!C34)/('Resultados'!C13+('Flujo de efectivo'!C7+'Flujo de efectivo'!C8+'Flujo de efectivo'!C9)),"") | D53: =IFERROR(('Flujo de efectivo'!D33+'Flujo de efectivo'!D34)/('Resultados'!D13+('Flujo de efectivo'!D7+'Flujo de efectivo'!D8+'Flujo de efectivo'!D9)),"") | E53: =IFERROR(('Flujo de efectivo'!E33+'Flujo de efectivo'!E34)/('Resultados'!E13+('Flujo de efectivo'!E7+'Flujo de efectivo'!E8+'Flujo de efectivo'!E9)),"") | F53: =IFERROR(('Flujo de efectivo'!F33+'Flujo de efectivo'!F34)/('Resultados'!F13+('Flujo de efectivo'!F7+'Flujo de efectivo'!F8+'Flujo de efectivo'!F9)),"") | G53: =IFERROR(('Flujo de efectivo'!G33+'Flujo de efectivo'!G34)/('Resultados'!G13+('Flujo de efectivo'!G7+'Flujo de efectivo'!G8+'Flujo de efectivo'!G9)),"") | H53: =IFERROR(('Flujo de efectivo'!H33+'Flujo de efectivo'!H34)/('Resultados'!H13+('Flujo de efectivo'!H7+'Flujo de efectivo'!H8+'Flujo de efectivo'!H9)),"") | I53: =IFERROR(('Flujo de efectivo'!I33+'Flujo de efectivo'!I34)/('Resultados'!I13+('Flujo de efectivo'!I7+'Flujo de efectivo'!I8+'Flujo de efectivo'!I9)),"") | ... AA53: =IFERROR(('Flujo de efectivo'!AA33+'Flujo de efectivo'!AA34)/('Resultados'!AA13+('Flujo de efectivo'!AA7+'Flujo de efectivo'!AA8+'Flujo de efectivo'!AA9)),"") | AC53: =IFERROR(('Flujo de efectivo'!AC33+'Flujo de efectivo'!AC34)/('Resultados'!AC13+('Flujo de efectivo'!AC7+'Flujo de efectivo'!AC8+'Flujo de efectivo'!AC9)),"") | AD53: =IFERROR(('Flujo de efectivo'!AD33+'Flujo de efectivo'!AD34)/('Resultados'!AD13+('Flujo de efectivo'!AD7+'Flujo de efectivo'!AD8+'Flujo de efectivo'!AD9)),"") | AE53: =IFERROR(('Flujo de efectivo'!AE33+'Flujo de efectivo'!AE34)/('Resultados'!AE13+('Flujo de efectivo'!AE7+'Flujo de efectivo'!AE8+'Flujo de efectivo'!AE9)),"") | AF53: =IFERROR(('Flujo de efectivo'!AF33+'Flujo de efectivo'!AF34)/('Resultados'!AF13+('Flujo de efectivo'!AF7+'Flujo de efectivo'!AF8+'Flujo de efectivo'!AF9)),"") | AG53: =IFERROR(('Flujo de efectivo'!AG33+'Flujo de efectivo'!AG34)/('Resultados'!AG13+('Flujo de efectivo'!AG7+'Flujo de efectivo'!AG8+'Flujo de efectivo'!AG9)),"") | AH53: =IFERROR(('Flujo de efectivo'!AH33+'Flujo de efectivo'!AH34)/('Resultados'!AH13+('Flujo de efectivo'!AH7+'Flujo de efectivo'!AH8+'Flujo de efectivo'!AH9)),"") | AI53: =IFERROR(('Flujo de efectivo'!AI33+'Flujo de efectivo'!AI34)/('Resultados'!AI13+('Flujo de efectivo'!AI7+'Flujo de efectivo'!AI8+'Flujo de efectivo'!AI9)),"")
A55: Crecimiento interanual
A56: Ingresos | F56: =IFERROR('Resultados'!F5/'Resultados'!B5-1,"") | G56: =IFERROR('Resultados'!G5/'Resultados'!C5-1,"") | H56: =IFERROR('Resultados'!H5/'Resultados'!D5-1,"") | I56: =IFERROR('Resultados'!I5/'Resultados'!E5-1,"") | J56: =IFERROR('Resultados'!J5/'Resultados'!F5-1,"") | K56: =IFERROR('Resultados'!K5/'Resultados'!G5-1,"") | L56: =IFERROR('Resultados'!L5/'Resultados'!H5-1,"") | M56: =IFERROR('Resultados'!M5/'Resultados'!I5-1,"") | ... AA56: =IFERROR('Resultados'!AA5/'Resultados'!W5-1,"")
A57: EBITDA | F57: =IFERROR(('Resultados'!F13+('Flujo de efectivo'!F7+'Flujo de efectivo'!F8+'Flujo de efectivo'!F9))/('Resultados'!B13+('Flujo de efectivo'!B7+'Flujo de efectivo'!B8+'Flujo de efectivo'!B9))-1,"") | G57: =IFERROR(('Resultados'!G13+('Flujo de efectivo'!G7+'Flujo de efectivo'!G8+'Flujo de efectivo'!G9))/('Resultados'!C13+('Flujo de efectivo'!C7+'Flujo de efectivo'!C8+'Flujo de efectivo'!C9))-1,"") | H57: =IFERROR(('Resultados'!H13+('Flujo de efectivo'!H7+'Flujo de efectivo'!H8+'Flujo de efectivo'!H9))/('Resultados'!D13+('Flujo de efectivo'!D7+'Flujo de efectivo'!D8+'Flujo de efectivo'!D9))-1,"") | I57: =IFERROR(('Resultados'!I13+('Flujo de efectivo'!I7+'Flujo de efectivo'!I8+'Flujo de efectivo'!I9))/('Resultados'!E13+('Flujo de efectivo'!E7+'Flujo de efectivo'!E8+'Flujo de efectivo'!E9))-1,"") | J57: =IFERROR(('Resultados'!J13+('Flujo de efectivo'!J7+'Flujo de efectivo'!J8+'Flujo de efectivo'!J9))/('Resultados'!F13+('Flujo de efectivo'!F7+'Flujo de efectivo'!F8+'Flujo de efectivo'!F9))-1,"") | K57: =IFERROR(('Resultados'!K13+('Flujo de efectivo'!K7+'Flujo de efectivo'!K8+'Flujo de efectivo'!K9))/('Resultados'!G13+('Flujo de efectivo'!G7+'Flujo de efectivo'!G8+'Flujo de efectivo'!G9))-1,"") | L57: =IFERROR(('Resultados'!L13+('Flujo de efectivo'!L7+'Flujo de efectivo'!L8+'Flujo de efectivo'!L9))/('Resultados'!H13+('Flujo de efectivo'!H7+'Flujo de efectivo'!H8+'Flujo de efectivo'!H9))-1,"") | M57: =IFERROR(('Resultados'!M13+('Flujo de efectivo'!M7+'Flujo de efectivo'!M8+'Flujo de efectivo'!M9))/('Resultados'!I13+('Flujo de efectivo'!I7+'Flujo de efectivo'!I8+'Flujo de efectivo'!I9))-1,"") | ... AA57: =IFERROR(('Resultados'!AA13+('Flujo de efectivo'!AA7+'Flujo de efectivo'!AA8+'Flujo de efectivo'!AA9))/('Resultados'!W13+('Flujo de efectivo'!W7+'Flujo de efectivo'!W8+'Flujo de efectivo'!W9))-1,"")
A58: Flujo operativo | F58: =IFERROR('Flujo de efectivo'!F33/'Flujo de efectivo'!B33-1,"") | G58: =IFERROR('Flujo de efectivo'!G33/'Flujo de efectivo'!C33-1,"") | H58: =IFERROR('Flujo de efectivo'!H33/'Flujo de efectivo'!D33-1,"") | I58: =IFERROR('Flujo de efectivo'!I33/'Flujo de efectivo'!E33-1,"") | J58: =IFERROR('Flujo de efectivo'!J33/'Flujo de efectivo'!F33-1,"") | K58: =IFERROR('Flujo de efectivo'!K33/'Flujo de efectivo'!G33-1,"") | L58: =IFERROR('Flujo de efectivo'!L33/'Flujo de efectivo'!H33-1,"") | M58: =IFERROR('Flujo de efectivo'!M33/'Flujo de efectivo'!I33-1,"") | ... AA58: =IFERROR('Flujo de efectivo'!AA33/'Flujo de efectivo'!W33-1,"")
A60: Estructura del resultado (sobre ingresos)
A61: Costos | B61: =IFERROR('Resultados'!B6/'Resultados'!B5,"") | C61: =IFERROR('Resultados'!C6/'Resultados'!C5,"") | D61: =IFERROR('Resultados'!D6/'Resultados'!D5,"") | E61: =IFERROR('Resultados'!E6/'Resultados'!E5,"") | F61: =IFERROR('Resultados'!F6/'Resultados'!F5,"") | G61: =IFERROR('Resultados'!G6/'Resultados'!G5,"") | H61: =IFERROR('Resultados'!H6/'Resultados'!H5,"") | I61: =IFERROR('Resultados'!I6/'Resultados'!I5,"") | ... AA61: =IFERROR('Resultados'!AA6/'Resultados'!AA5,"") | AC61: =IFERROR('Resultados'!AC6/'Resultados'!AC5,"") | AD61: =IFERROR('Resultados'!AD6/'Resultados'!AD5,"") | AE61: =IFERROR('Resultados'!AE6/'Resultados'!AE5,"") | AF61: =IFERROR('Resultados'!AF6/'Resultados'!AF5,"") | AG61: =IFERROR('Resultados'!AG6/'Resultados'!AG5,"") | AH61: =IFERROR('Resultados'!AH6/'Resultados'!AH5,"") | AI61: =IFERROR('Resultados'!AI6/'Resultados'!AI5,"")
A62: Gastos de comercialización | B62: =IFERROR('Resultados'!B8/'Resultados'!B5,"") | C62: =IFERROR('Resultados'!C8/'Resultados'!C5,"") | D62: =IFERROR('Resultados'!D8/'Resultados'!D5,"") | E62: =IFERROR('Resultados'!E8/'Resultados'!E5,"") | F62: =IFERROR('Resultados'!F8/'Resultados'!F5,"") | G62: =IFERROR('Resultados'!G8/'Resultados'!G5,"") | H62: =IFERROR('Resultados'!H8/'Resultados'!H5,"") | I62: =IFERROR('Resultados'!I8/'Resultados'!I5,"") | ... AA62: =IFERROR('Resultados'!AA8/'Resultados'!AA5,"") | AC62: =IFERROR('Resultados'!AC8/'Resultados'!AC5,"") | AD62: =IFERROR('Resultados'!AD8/'Resultados'!AD5,"") | AE62: =IFERROR('Resultados'!AE8/'Resultados'!AE5,"") | AF62: =IFERROR('Resultados'!AF8/'Resultados'!AF5,"") | AG62: =IFERROR('Resultados'!AG8/'Resultados'!AG5,"") | AH62: =IFERROR('Resultados'!AH8/'Resultados'!AH5,"") | AI62: =IFERROR('Resultados'!AI8/'Resultados'!AI5,"")
A63: Gastos de administración | B63: =IFERROR('Resultados'!B9/'Resultados'!B5,"") | C63: =IFERROR('Resultados'!C9/'Resultados'!C5,"") | D63: =IFERROR('Resultados'!D9/'Resultados'!D5,"") | E63: =IFERROR('Resultados'!E9/'Resultados'!E5,"") | F63: =IFERROR('Resultados'!F9/'Resultados'!F5,"") | G63: =IFERROR('Resultados'!G9/'Resultados'!G5,"") | H63: =IFERROR('Resultados'!H9/'Resultados'!H5,"") | I63: =IFERROR('Resultados'!I9/'Resultados'!I5,"") | ... AA63: =IFERROR('Resultados'!AA9/'Resultados'!AA5,"") | AC63: =IFERROR('Resultados'!AC9/'Resultados'!AC5,"") | AD63: =IFERROR('Resultados'!AD9/'Resultados'!AD5,"") | AE63: =IFERROR('Resultados'!AE9/'Resultados'!AE5,"") | AF63: =IFERROR('Resultados'!AF9/'Resultados'!AF5,"") | AG63: =IFERROR('Resultados'!AG9/'Resultados'!AG5,"") | AH63: =IFERROR('Resultados'!AH9/'Resultados'!AH5,"") | AI63: =IFERROR('Resultados'!AI9/'Resultados'!AI5,"")
A64: Gastos de exploración | B64: =IFERROR('Resultados'!B10/'Resultados'!B5,"") | C64: =IFERROR('Resultados'!C10/'Resultados'!C5,"") | D64: =IFERROR('Resultados'!D10/'Resultados'!D5,"") | E64: =IFERROR('Resultados'!E10/'Resultados'!E5,"") | F64: =IFERROR('Resultados'!F10/'Resultados'!F5,"") | G64: =IFERROR('Resultados'!G10/'Resultados'!G5,"") | H64: =IFERROR('Resultados'!H10/'Resultados'!H5,"") | I64: =IFERROR('Resultados'!I10/'Resultados'!I5,"") | ... AA64: =IFERROR('Resultados'!AA10/'Resultados'!AA5,"") | AC64: =IFERROR('Resultados'!AC10/'Resultados'!AC5,"") | AD64: =IFERROR('Resultados'!AD10/'Resultados'!AD5,"") | AE64: =IFERROR('Resultados'!AE10/'Resultados'!AE5,"") | AF64: =IFERROR('Resultados'!AF10/'Resultados'!AF5,"") | AG64: =IFERROR('Resultados'!AG10/'Resultados'!AG5,"") | AH64: =IFERROR('Resultados'!AH10/'Resultados'!AH5,"") | AI64: =IFERROR('Resultados'!AI10/'Resultados'!AI5,"")
A65: Otros resultados operativos | B65: =IFERROR('Resultados'!B12/'Resultados'!B5,"") | C65: =IFERROR('Resultados'!C12/'Resultados'!C5,"") | D65: =IFERROR('Resultados'!D12/'Resultados'!D5,"") | E65: =IFERROR('Resultados'!E12/'Resultados'!E5,"") | F65: =IFERROR('Resultados'!F12/'Resultados'!F5,"") | G65: =IFERROR('Resultados'!G12/'Resultados'!G5,"") | H65: =IFERROR('Resultados'!H12/'Resultados'!H5,"") | I65: =IFERROR('Resultados'!I12/'Resultados'!I5,"") | ... AA65: =IFERROR('Resultados'!AA12/'Resultados'!AA5,"") | AC65: =IFERROR('Resultados'!AC12/'Resultados'!AC5,"") | AD65: =IFERROR('Resultados'!AD12/'Resultados'!AD5,"") | AE65: =IFERROR('Resultados'!AE12/'Resultados'!AE5,"") | AF65: =IFERROR('Resultados'!AF12/'Resultados'!AF5,"") | AG65: =IFERROR('Resultados'!AG12/'Resultados'!AG5,"") | AH65: =IFERROR('Resultados'!AH12/'Resultados'!AH5,"") | AI65: =IFERROR('Resultados'!AI12/'Resultados'!AI5,"")
A66: Resultados financieros netos | B66: =IFERROR('Resultados'!B18/'Resultados'!B5,"") | C66: =IFERROR('Resultados'!C18/'Resultados'!C5,"") | D66: =IFERROR('Resultados'!D18/'Resultados'!D5,"") | E66: =IFERROR('Resultados'!E18/'Resultados'!E5,"") | F66: =IFERROR('Resultados'!F18/'Resultados'!F5,"") | G66: =IFERROR('Resultados'!G18/'Resultados'!G5,"") | H66: =IFERROR('Resultados'!H18/'Resultados'!H5,"") | I66: =IFERROR('Resultados'!I18/'Resultados'!I5,"") | ... AA66: =IFERROR('Resultados'!AA18/'Resultados'!AA5,"") | AC66: =IFERROR('Resultados'!AC18/'Resultados'!AC5,"") | AD66: =IFERROR('Resultados'!AD18/'Resultados'!AD5,"") | AE66: =IFERROR('Resultados'!AE18/'Resultados'!AE5,"") | AF66: =IFERROR('Resultados'!AF18/'Resultados'!AF5,"") | AG66: =IFERROR('Resultados'!AG18/'Resultados'!AG5,"") | AH66: =IFERROR('Resultados'!AH18/'Resultados'!AH5,"") | AI66: =IFERROR('Resultados'!AI18/'Resultados'!AI5,"")
A67: Impuesto a las ganancias | B67: =IFERROR('Resultados'!B20/'Resultados'!B5,"") | C67: =IFERROR('Resultados'!C20/'Resultados'!C5,"") | D67: =IFERROR('Resultados'!D20/'Resultados'!D5,"") | E67: =IFERROR('Resultados'!E20/'Resultados'!E5,"") | F67: =IFERROR('Resultados'!F20/'Resultados'!F5,"") | G67: =IFERROR('Resultados'!G20/'Resultados'!G5,"") | H67: =IFERROR('Resultados'!H20/'Resultados'!H5,"") | I67: =IFERROR('Resultados'!I20/'Resultados'!I5,"") | ... AA67: =IFERROR('Resultados'!AA20/'Resultados'!AA5,"") | AC67: =IFERROR('Resultados'!AC20/'Resultados'!AC5,"") | AD67: =IFERROR('Resultados'!AD20/'Resultados'!AD5,"") | AE67: =IFERROR('Resultados'!AE20/'Resultados'!AE5,"") | AF67: =IFERROR('Resultados'!AF20/'Resultados'!AF5,"") | AG67: =IFERROR('Resultados'!AG20/'Resultados'!AG5,"") | AH67: =IFERROR('Resultados'!AH20/'Resultados'!AH5,"") | AI67: =IFERROR('Resultados'!AI20/'Resultados'!AI5,"")
A69: Puente al EBITDA ajustado de la compañía | AK69: El EBITDA ajustado del earnings release no es el de los estados: excluye partidas que la compañía considera no recurrentes. Este bloque muestra de qué está hecha la diferencia en vez de dejarla como una discrepancia sin explicar.
A70: Resultado operativo | B70: ='Resultados'!B13 | C70: ='Resultados'!C13 | D70: ='Resultados'!D13 | E70: ='Resultados'!E13 | F70: ='Resultados'!F13 | G70: ='Resultados'!G13 | H70: ='Resultados'!H13 | I70: ='Resultados'!I13 | ... AA70: ='Resultados'!AA13 | AC70: ='Resultados'!AC13 | AD70: ='Resultados'!AD13 | AE70: ='Resultados'!AE13 | AF70: ='Resultados'!AF13 | AG70: ='Resultados'!AG13 | AH70: ='Resultados'!AH13 | AI70: ='Resultados'!AI13
A71: Depreciaciones y amortizaciones | B71: =('Flujo de efectivo'!B7+'Flujo de efectivo'!B8+'Flujo de efectivo'!B9) | C71: =('Flujo de efectivo'!C7+'Flujo de efectivo'!C8+'Flujo de efectivo'!C9) | D71: =('Flujo de efectivo'!D7+'Flujo de efectivo'!D8+'Flujo de efectivo'!D9) | E71: =('Flujo de efectivo'!E7+'Flujo de efectivo'!E8+'Flujo de efectivo'!E9) | F71: =('Flujo de efectivo'!F7+'Flujo de efectivo'!F8+'Flujo de efectivo'!F9) | G71: =('Flujo de efectivo'!G7+'Flujo de efectivo'!G8+'Flujo de efectivo'!G9) | H71: =('Flujo de efectivo'!H7+'Flujo de efectivo'!H8+'Flujo de efectivo'!H9) | I71: =('Flujo de efectivo'!I7+'Flujo de efectivo'!I8+'Flujo de efectivo'!I9) | ... AA71: =('Flujo de efectivo'!AA7+'Flujo de efectivo'!AA8+'Flujo de efectivo'!AA9) | AC71: =('Flujo de efectivo'!AC7+'Flujo de efectivo'!AC8+'Flujo de efectivo'!AC9) | AD71: =('Flujo de efectivo'!AD7+'Flujo de efectivo'!AD8+'Flujo de efectivo'!AD9) | AE71: =('Flujo de efectivo'!AE7+'Flujo de efectivo'!AE8+'Flujo de efectivo'!AE9) | AF71: =('Flujo de efectivo'!AF7+'Flujo de efectivo'!AF8+'Flujo de efectivo'!AF9) | AG71: =('Flujo de efectivo'!AG7+'Flujo de efectivo'!AG8+'Flujo de efectivo'!AG9) | AH71: =('Flujo de efectivo'!AH7+'Flujo de efectivo'!AH8+'Flujo de efectivo'!AH9) | AI71: =('Flujo de efectivo'!AI7+'Flujo de efectivo'!AI8+'Flujo de efectivo'!AI9)
A72: EBITDA de los estados | B72: =('Resultados'!B13+('Flujo de efectivo'!B7+'Flujo de efectivo'!B8+'Flujo de efectivo'!B9)) | C72: =('Resultados'!C13+('Flujo de efectivo'!C7+'Flujo de efectivo'!C8+'Flujo de efectivo'!C9)) | D72: =('Resultados'!D13+('Flujo de efectivo'!D7+'Flujo de efectivo'!D8+'Flujo de efectivo'!D9)) | E72: =('Resultados'!E13+('Flujo de efectivo'!E7+'Flujo de efectivo'!E8+'Flujo de efectivo'!E9)) | F72: =('Resultados'!F13+('Flujo de efectivo'!F7+'Flujo de efectivo'!F8+'Flujo de efectivo'!F9)) | G72: =('Resultados'!G13+('Flujo de efectivo'!G7+'Flujo de efectivo'!G8+'Flujo de efectivo'!G9)) | H72: =('Resultados'!H13+('Flujo de efectivo'!H7+'Flujo de efectivo'!H8+'Flujo de efectivo'!H9)) | I72: =('Resultados'!I13+('Flujo de efectivo'!I7+'Flujo de efectivo'!I8+'Flujo de efectivo'!I9)) | ... AA72: =('Resultados'!AA13+('Flujo de efectivo'!AA7+'Flujo de efectivo'!AA8+'Flujo de efectivo'!AA9)) | AC72: =('Resultados'!AC13+('Flujo de efectivo'!AC7+'Flujo de efectivo'!AC8+'Flujo de efectivo'!AC9)) | AD72: =('Resultados'!AD13+('Flujo de efectivo'!AD7+'Flujo de efectivo'!AD8+'Flujo de efectivo'!AD9)) | AE72: =('Resultados'!AE13+('Flujo de efectivo'!AE7+'Flujo de efectivo'!AE8+'Flujo de efectivo'!AE9)) | AF72: =('Resultados'!AF13+('Flujo de efectivo'!AF7+'Flujo de efectivo'!AF8+'Flujo de efectivo'!AF9)) | AG72: =('Resultados'!AG13+('Flujo de efectivo'!AG7+'Flujo de efectivo'!AG8+'Flujo de efectivo'!AG9)) | AH72: =('Resultados'!AH13+('Flujo de efectivo'!AH7+'Flujo de efectivo'!AH8+'Flujo de efectivo'!AH9)) | AI72: =('Resultados'!AI13+('Flujo de efectivo'!AI7+'Flujo de efectivo'!AI8+'Flujo de efectivo'!AI9))
A73: EBITDA ajustado publicado | B73: 851000000 | C73: 28000000 | D73: 392000000 | E73: 183000000 | F73: 767000000 | G73: 1084000000 | H73: 1154000000 | I73: 834000000 | J73: 972000000 | K73: 1500000000 | L73: 1498000000 | M73: 933000000 | N73: 1044000000 | O73: 1005000000 | P73: 926000000 | Q73: 1082000000 | R73: 1245000000 | S73: 1204000000 | T73: 1366000000 | U73: 839000000 | V73: 1245000000 | W73: 1124000000 | X73: 1357000000 | Y73: 1283000000 | Z73: 1594000000 | AA73: 2804000000
A74: Diferencia (ajustes de la compañía) | B74: =IF(COUNT(B73)=0,"",B73-B72) | C74: =IF(COUNT(C73)=0,"",C73-C72) | D74: =IF(COUNT(D73)=0,"",D73-D72) | E74: =IF(COUNT(E73)=0,"",E73-E72) | F74: =IF(COUNT(F73)=0,"",F73-F72) | G74: =IF(COUNT(G73)=0,"",G73-G72) | H74: =IF(COUNT(H73)=0,"",H73-H72) | I74: =IF(COUNT(I73)=0,"",I73-I72) | ... AA74: =IF(COUNT(AA73)=0,"",AA73-AA72) | AC74: =IF(COUNT(AC73)=0,"",AC73-AC72) | AD74: =IF(COUNT(AD73)=0,"",AD73-AD72) | AE74: =IF(COUNT(AE73)=0,"",AE73-AE72) | AF74: =IF(COUNT(AF73)=0,"",AF73-AF72) | AG74: =IF(COUNT(AG73)=0,"",AG73-AG72) | AH74: =IF(COUNT(AH73)=0,"",AH73-AH72) | AI74: =IF(COUNT(AI73)=0,"",AI73-AI72)
A75: Memo: deterioro y reversión de bienes de uso | B75: ='Resultados'!B11 | C75: ='Resultados'!C11 | D75: ='Resultados'!D11 | E75: ='Resultados'!E11 | F75: ='Resultados'!F11 | G75: ='Resultados'!G11 | H75: ='Resultados'!H11 | I75: ='Resultados'!I11 | ... AA75: ='Resultados'!AA11 | AC75: ='Resultados'!AC11 | AD75: ='Resultados'!AD11 | AE75: ='Resultados'!AE11 | AF75: ='Resultados'!AF11 | AG75: ='Resultados'!AG11 | AH75: ='Resultados'!AH11 | AI75: ='Resultados'!AI11
A76: Memo: resultado de participaciones en asociadas | B76: ='Resultados'!B14 | C76: ='Resultados'!C14 | D76: ='Resultados'!D14 | E76: ='Resultados'!E14 | F76: ='Resultados'!F14 | G76: ='Resultados'!G14 | H76: ='Resultados'!H14 | I76: ='Resultados'!I14 | ... AA76: ='Resultados'!AA14 | AC76: ='Resultados'!AC14 | AD76: ='Resultados'!AD14 | AE76: ='Resultados'!AE14 | AF76: ='Resultados'!AF14 | AG76: ='Resultados'!AG14 | AH76: ='Resultados'!AH14 | AI76: ='Resultados'!AI14
A78: Otros números del release
A79: Capex publicado | B79: 598000000 | C79: 162000000 | D79: 257000000 | E79: 538000000 | F79: 487000000 | G79: 580000000 | H79: 696000000 | I79: 908000000 | J79: 748000000 | K79: 932000000 | L79: 1186000000 | M79: 1421000000 | N79: 1298000000 | O79: 1374000000 | P79: 1546000000 | Q79: 1466000000 | R79: 1252000000 | S79: 1200000000 | T79: 1353000000 | U79: 1320000000 | V79: 1214000000 | W79: 1160000000 | X79: 1017000000 | Y79: 1086000000 | Z79: 980000000 | AA79: 1340000000
A80: Flujo de caja libre publicado | B80: -85000000 | C80: 61000000 | D80: 150000000 | E80: 182000000 | F80: 284000000 | G80: 311000000 | H80: 144000000 | I80: 143000000 | J80: 391000000 | K80: 318000000 | L80: 262000000 | M80: -188000000 | N80: -17000000 | O80: -284000000 | P80: -379000000 | Q80: -60000000 | R80: -394000000 | S80: -257000000 | T80: -173000000 | U80: 64000000 | V80: -957000000 | W80: -365000000 | X80: -759000000 | Y80: 265000000 | Z80: 871000000 | AA80: 824000000

Sheet Segmentos
A1: Segmentos
A2: De la nota de segmentos de cada 6-K. La compañía la publica acumulada, así que el trimestre sale por diferencia; cuando cambió la apertura, el trimestre del cambio queda vacío.
A4: En dólares | B4: 2020Q1 | C4: 2020Q2 | D4: 2020Q3 | E4: 2020Q4 | F4: 2021Q1 | G4: 2021Q2 | H4: 2021Q3 | I4: 2021Q4 | J4: 2022Q1 | K4: 2022Q2 | L4: 2022Q3 | M4: 2022Q4 | N4: 2023Q1 | O4: 2023Q2 | P4: 2023Q3 | Q4: 2023Q4 | R4: 2024Q1 | S4: 2024Q2 | T4: 2024Q3 | U4: 2024Q4 | V4: 2025Q1 | W4: 2025Q2 | X4: 2025Q3 | Y4: 2025Q4 | Z4: 2026Q1 | AA4: 2026Q2 | AC4: FY19 | AD4: FY20 | AE4: FY21 | AF4: FY22 | AG4: FY23 | AH4: FY24 | AI4: FY25
A5: Ingresos
A6: Upstream | B6: 1.316104e+09 | C6: 8.0195802e+08 | D6: 1.0782193e+09 | E6: 9.7390699e+08 | F6: 1.2467648e+09 | G6: 1.3858407e+09 | H6: 1.6028763e+09 | I6: 1.5201079e+09 | J6: 1598000000 | K6: 1810000000 | L6: 2087000000 | N6: 1828000000 | O6: 1896000000 | P6: 1920000000 | Q6: 1710000000 | R6: 1947000000 | S6: 2172000000 | T6: 2150000000 | U6: 1969000000 | V6: 2067000000 | W6: 1895000000 | X6: 1967000000 | Y6: 1646000000 | Z6: 2021000000 | AA6: 2741000000 | AC6: 5.9961352e+09 | AD6: 4255000000 | AE6: 5967000000 | AF6: 7185000000 | AG6: 7243000000 | AH6: 8275000000 | AI6: 7575000000
A7: Midstream y Downstream | R7: 3790000000 | U7: 4071000000 | V7: 3930000000 | W7: 3741000000 | X7: 3721000000 | Y7: 3958000000 | Z7: 4257000000 | AA7: 5682000000 | AG7: 15113000000 | AH7: 16023000000 | AI7: 15338000000
A8: Downstream | B8: 2.3566255e+09 | C8: 1.5541047e+09 | D8: 1.8334002e+09 | E8: 1.9519143e+09 | F8: 2.274531e+09 | G8: 2.7778655e+09 | H8: 2.8663918e+09 | I8: 3.0986864e+09 | N8: 3753000000 | O8: 3654000000 | Q8: 3920000000 | S8: 3957000000 | T8: 4127000000 | AC8: 1.1117855e+10 | AD8: 7862000000 | AE8: 11284000000 | AF8: 16125000000
A9: Industrialización | J9: 2564000000 | K9: 3267000000 | L9: 3478000000 | P9: 2770000000
A10: Comercialización | J10: 3577000000 | K10: 4713000000 | L10: 5027000000 | P10: 4209000000
A11: Gas y energía | B11: 4.7670486e+08 | C11: 4.486871e+08 | D11: 5.4481066e+08 | E11: 3.8560746e+08 | F11: 3.7240836e+08 | G11: 5.8304298e+08 | H11: 7.5182477e+08 | I11: 5.3924604e+08 | J11: 149000000 | K11: 269000000 | L11: 284000000 | N11: 506000000 | O11: 728000000 | P11: 290000000 | Q11: 318000000 | S11: 862000000 | T11: 1057000000 | AC11: 2.9032636e+09 | AD11: 1772000000 | AE11: 2230000000 | AF11: 2695000000
A12: GNL y gas integrado | R12: 366000000 | U12: 361000000 | V12: 400000000 | W12: 565000000 | X12: 662000000 | Y12: 338000000 | Z12: 371000000 | AA12: 582000000 | AG12: 1814000000 | AH12: 1927000000 | AI12: 1965000000
A13: Nuevas energías | R13: 78000000 | U13: 207000000 | V13: 192000000 | W13: 229000000 | X13: 234000000 | Y13: 188000000 | Z13: 206000000 | AA13: 237000000 | AG13: 428000000 | AH13: 904000000 | AI13: 843000000
A14: Administración central y otros | B14: 1.771381e+08 | C14: 1.0305895e+08 | D14: 1.3715169e+08 | E14: 1.876908e+08 | F14: 1.4676726e+08 | G14: 1.8593895e+08 | H14: 2.3225275e+08 | I14: 2.728631e+08 | J14: 207000000 | K14: 259000000 | L14: 300000000 | N14: 310000000 | O14: 335000000 | P14: 361000000 | Q14: 38000000 | R14: 362000000 | S14: 413000000 | T14: 625000000 | U14: 496000000 | V14: 482000000 | W14: 482000000 | X14: 422000000 | Y14: 449000000 | Z14: 459000000 | AA14: 502000000 | AC14: 9.8148642e+08 | AD14: 555000000 | AE14: 730000000 | AF14: 1165000000 | AG14: 1137000000 | AH14: 1852000000 | AI14: 1846000000
A15: Ajustes de consolidación | B15: -1.4824956e+09 | C15: -9.2960419e+08 | D15: -1.2246292e+09 | E15: -1.1555098e+09 | F15: -1.38698e+09 | G15: -1.5705556e+09 | H15: -1.8156006e+09 | I15: -1.7776416e+09 | J15: -4335000000 | K15: -5323000000 | L15: -5819000000 | N15: -2159000000 | O15: -2238000000 | P15: -5046000000 | Q15: -1792000000 | R15: -2233000000 | S15: -2469000000 | T15: -2662000000 | U15: -2353000000 | V15: -2463000000 | W15: -2271000000 | X15: -2363000000 | Y15: -2023000000 | Z15: -2368000000 | AA15: -3170000000 | AC15: -6.901338e+09 | AD15: -4754000000 | AE15: -6529000000 | AF15: -8413000000 | AG15: -8424000000 | AH15: -9688000000 | AI15: -9119000000
A16: Total | B16: 2.8440769e+09 | C16: 1.9782046e+09 | D16: 2.3689528e+09 | E16: 2.3436098e+09 | F16: 2.6534915e+09 | G16: 3.3621325e+09 | H16: 3.637745e+09 | I16: 3.6532618e+09 | J16: 3760000000 | K16: 4995000000 | L16: 5357000000 | M16: 4645000000 | N16: 4238000000 | O16: 4375000000 | P16: 4504000000 | Q16: 4194000000 | R16: 4310000000 | S16: 4935000000 | T16: 5297000000 | U16: 4751000000 | V16: 4608000000 | W16: 4641000000 | X16: 4643000000 | Y16: 4556000000 | Z16: 4946000000 | AA16: 6574000000 | AC16: 1.4097402e+10 | AD16: 9690000000 | AE16: 13682000000 | AF16: 18757000000 | AG16: 17311000000 | AH16: 19293000000 | AI16: 18448000000
A17: Suma de segmentos − total | B17: =IF(COUNT(B16)=1,SUM(B6,B7,B8,B9,B10,B11,B12,B13,B14,B15)-B16,"") | C17: =IF(COUNT(C16)=1,SUM(C6,C7,C8,C9,C10,C11,C12,C13,C14,C15)-C16,"") | D17: =IF(COUNT(D16)=1,SUM(D6,D7,D8,D9,D10,D11,D12,D13,D14,D15)-D16,"") | E17: =IF(COUNT(E16)=1,SUM(E6,E7,E8,E9,E10,E11,E12,E13,E14,E15)-E16,"") | F17: =IF(COUNT(F16)=1,SUM(F6,F7,F8,F9,F10,F11,F12,F13,F14,F15)-F16,"") | G17: =IF(COUNT(G16)=1,SUM(G6,G7,G8,G9,G10,G11,G12,G13,G14,G15)-G16,"") | H17: =IF(COUNT(H16)=1,SUM(H6,H7,H8,H9,H10,H11,H12,H13,H14,H15)-H16,"") | I17: =IF(COUNT(I16)=1,SUM(I6,I7,I8,I9,I10,I11,I12,I13,I14,I15)-I16,"") | ... AA17: =IF(COUNT(AA16)=1,SUM(AA6,AA7,AA8,AA9,AA10,AA11,AA12,AA13,AA14,AA15)-AA16,"") | AC17: =IF(COUNT(AC16)=1,SUM(AC6,AC7,AC8,AC9,AC10,AC11,AC12,AC13,AC14,AC15)-AC16,"") | AD17: =IF(COUNT(AD16)=1,SUM(AD6,AD7,AD8,AD9,AD10,AD11,AD12,AD13,AD14,AD15)-AD16,"") | AE17: =IF(COUNT(AE16)=1,SUM(AE6,AE7,AE8,AE9,AE10,AE11,AE12,AE13,AE14,AE15)-AE16,"") | AF17: =IF(COUNT(AF16)=1,SUM(AF6,AF7,AF8,AF9,AF10,AF11,AF12,AF13,AF14,AF15)-AF16,"") | AG17: =IF(COUNT(AG16)=1,SUM(AG6,AG7,AG8,AG9,AG10,AG11,AG12,AG13,AG14,AG15)-AG16,"") | AH17: =IF(COUNT(AH16)=1,SUM(AH6,AH7,AH8,AH9,AH10,AH11,AH12,AH13,AH14,AH15)-AH16,"") | AI17: =IF(COUNT(AI16)=1,SUM(AI6,AI7,AI8,AI9,AI10,AI11,AI12,AI13,AI14,AI15)-AI16,"") | AK17: Da cero cuando la apertura está completa. Donde un segmento no se publicó —el 4T22, que es cuando la compañía cambió la apertura— la diferencia es ese hueco.
A19: Resultado operativo
A20: Upstream | B20: 10811628 | C20: -1.0929759e+09 | D20: -1.7833544e+08 | E20: 7.5393847e+08 | F20: 18436281 | G20: -11889278 | H20: 2.2175801e+08 | I20: -2.0286553e+08 | J20: 232000000 | K20: 350000000 | L20: 319000000 | N20: 144000000 | O20: 75000000 | P20: -436000000 | Q20: -1706000000 | R20: 400000000 | S20: 362000000 | T20: 333000000 | U20: -580000000 | V20: -103000000 | W20: 176000000 | X20: 415000000 | Y20: -62000000 | Z20: 616000000 | AA20: 955000000 | AC20: -1.0219757e+09 | AD20: -444000000 | AE20: 80000000 | AF20: 1306000000 | AG20: -1915000000 | AH20: 515000000 | AI20: 410000000
A21: Midstream y Downstream | R21: 560000000 | S21: 301000000 | T21: 295000000 | U21: 200000000 | V21: 422000000 | W21: 286000000 | X21: 158000000 | Y21: 341000000 | Z21: 1085000000 | AA21: 707000000 | AG21: 939000000 | AH21: 1356000000 | AI21: 1167000000
A22: Downstream | B22: 67295870 | C22: 2754953.3 | D22: -1.1243599e+08 | E22: 1.0943421e+08 | F22: 1.9883394e+08 | G22: 3.432457e+08 | H22: 2.3547319e+08 | I22: 1.3697903e+08 | N22: 254000000 | O22: 197000000 | Q22: 455000000 | AC22: 8.4454159e+08 | AD22: 89000000 | AE22: 945000000 | AF22: 1523000000
A23: Industrialización | J23: 220000000 | K23: 525000000 | L23: 286000000 | P23: -93000000
A24: Comercialización | J24: 103000000 | K24: 120000000 | L24: 108000000 | P24: 88000000
A25: Gas y energía | B25: -17910829 | C25: -1.3041593e+08 | D25: 20701112 | E25: -1.3257366e+08 | F25: -31935886 | G25: 10462991 | H25: 28510715 | I25: 4041384 | J25: -4000000 | K25: 32000000 | L25: 35000000 | N25: -23000000 | O25: 26000000 | P25: 29000000 | Q25: -40000000 | AC25: 61159827 | AD25: -272000000 | AE25: 10000000 | AF25: 90000000
A26: GNL y gas integrado | R26: -33000000 | S26: -22000000 | T26: 10000000 | U26: -4000000 | V26: -5000000 | W26: 0 | X26: -6000000 | Y26: 3000000 | Z26: -1000000 | AA26: -35000000 | AG26: -1000000 | AH26: -49000000 | AI26: -8000000
A27: Nuevas energías | R27: -25000000 | S27: 29000000 | T27: 79000000 | U27: 23000000 | V27: 24000000 | W27: 24000000 | X27: 38000000 | Y27: 346000000 | Z27: 13000000 | AA27: 27000000 | AG27: -64000000 | AH27: 106000000 | AI27: 432000000
A28: Administración central y otros | B28: -56207439 | C28: -1.0031881e+08 | D28: -74556775 | E28: -82756967 | F28: -41831831 | G28: -36189388 | H28: -36937375 | I28: -78956300 | J28: -56000000 | K28: -82000000 | L28: -87000000 | N28: -64000000 | O28: -90000000 | P28: -94000000 | Q28: -26000000 | R28: -26000000 | S28: -68000000 | T28: -76000000 | U28: -162000000 | V28: -115000000 | W28: -69000000 | X28: -81000000 | Y28: -127000000 | Z28: -170000000 | AA28: -177000000 | AC28: -3.2960659e+08 | AD28: -290000000 | AE28: -198000000 | AF28: -401000000 | AG28: -262000000 | AH28: -332000000 | AI28: -336000000
A29: Ajustes de consolidación | B29: 2.3696027e+08 | C29: -63097318 | D29: 23882747 | E29: -1.0127103e+08 | F29: -66074637 | G29: 4544961.4 | H29: -20413301 | I29: -52916249 | J29: -91000000 | K29: -60000000 | L29: 90000000 | N29: 24000000 | O29: 13000000 | P29: 119000000 | Q29: -100000000 | R29: -210000000 | S29: -12000000 | T29: 113000000 | U29: -7000000 | V29: -31000000 | W29: -5000000 | X29: 28000000 | Y29: 83000000 | Z29: -665000000 | AA29: 336000000 | AC29: 9369253.3 | AD29: 113000000 | AE29: -138000000 | AF29: -36000000 | AG29: 55000000 | AH29: -116000000 | AI29: 75000000
A30: Total | B30: 2.409495e+08 | C30: -1.384053e+09 | D30: -3.2074434e+08 | E30: 5.4677103e+08 | F30: 77427862 | G30: 3.1017499e+08 | H30: 4.2839124e+08 | I30: -1.9371767e+08 | J30: 404000000 | K30: 885000000 | L30: 751000000 | M30: 442000000 | N30: 335000000 | O30: 221000000 | P30: -387000000 | Q30: -1417000000 | R30: 666000000 | S30: 590000000 | T30: 754000000 | U30: -530000000 | V30: 192000000 | W30: 412000000 | X30: 552000000 | Y30: 584000000 | Z30: 878000000 | AA30: 1813000000 | AC30: -4.3651164e+08 | AD30: -804000000 | AE30: 699000000 | AF30: 2482000000 | AG30: -1248000000 | AH30: 1480000000 | AI30: 1740000000
A31: Suma de segmentos − total | B31: =IF(COUNT(B30)=1,SUM(B20,B21,B22,B23,B24,B25,B26,B27,B28,B29)-B30,"") | C31: =IF(COUNT(C30)=1,SUM(C20,C21,C22,C23,C24,C25,C26,C27,C28,C29)-C30,"") | D31: =IF(COUNT(D30)=1,SUM(D20,D21,D22,D23,D24,D25,D26,D27,D28,D29)-D30,"") | E31: =IF(COUNT(E30)=1,SUM(E20,E21,E22,E23,E24,E25,E26,E27,E28,E29)-E30,"") | F31: =IF(COUNT(F30)=1,SUM(F20,F21,F22,F23,F24,F25,F26,F27,F28,F29)-F30,"") | G31: =IF(COUNT(G30)=1,SUM(G20,G21,G22,G23,G24,G25,G26,G27,G28,G29)-G30,"") | H31: =IF(COUNT(H30)=1,SUM(H20,H21,H22,H23,H24,H25,H26,H27,H28,H29)-H30,"") | I31: =IF(COUNT(I30)=1,SUM(I20,I21,I22,I23,I24,I25,I26,I27,I28,I29)-I30,"") | ... AA31: =IF(COUNT(AA30)=1,SUM(AA20,AA21,AA22,AA23,AA24,AA25,AA26,AA27,AA28,AA29)-AA30,"") | AC31: =IF(COUNT(AC30)=1,SUM(AC20,AC21,AC22,AC23,AC24,AC25,AC26,AC27,AC28,AC29)-AC30,"") | AD31: =IF(COUNT(AD30)=1,SUM(AD20,AD21,AD22,AD23,AD24,AD25,AD26,AD27,AD28,AD29)-AD30,"") | AE31: =IF(COUNT(AE30)=1,SUM(AE20,AE21,AE22,AE23,AE24,AE25,AE26,AE27,AE28,AE29)-AE30,"") | AF31: =IF(COUNT(AF30)=1,SUM(AF20,AF21,AF22,AF23,AF24,AF25,AF26,AF27,AF28,AF29)-AF30,"") | AG31: =IF(COUNT(AG30)=1,SUM(AG20,AG21,AG22,AG23,AG24,AG25,AG26,AG27,AG28,AG29)-AG30,"") | AH31: =IF(COUNT(AH30)=1,SUM(AH20,AH21,AH22,AH23,AH24,AH25,AH26,AH27,AH28,AH29)-AH30,"") | AI31: =IF(COUNT(AI30)=1,SUM(AI20,AI21,AI22,AI23,AI24,AI25,AI26,AI27,AI28,AI29)-AI30,"") | AK31: Da cero cuando la apertura está completa. Donde un segmento no se publicó —el 4T22, que es cuando la compañía cambió la apertura— la diferencia es ese hueco.
A33: Capex en bienes de uso
A34: Upstream | J34: 599000000 | K34: 712000000 | L34: 833000000 | N34: 1015000000 | O34: 1017000000 | P34: 1150000000 | Q34: 1587000000 | R34: 1009000000 | S34: 939000000 | T34: 1071000000 | U34: 1154000000 | V34: 1060000000 | W34: 939000000 | X34: 846000000 | Y34: 852000000 | Z34: 828000000 | AA34: 1484000000 | AD34: 886000000 | AE34: 2168000000 | AF34: 3378000000 | AG34: 4717000000 | AH34: 4177000000 | AI34: 3697000000
A35: Midstream y Downstream | R35: 214000000 | U35: 345000000 | V35: 213000000 | W35: 287000000 | X35: 249000000 | Y35: 275000000 | Z35: 169000000 | AA35: 241000000 | AG35: 1285000000 | AH35: 1233000000 | AI35: 1024000000
A36: Downstream | N36: 214000000 | O36: 281000000 | Q36: 323000000 | S36: 317000000 | T36: 320000000 | AD36: 319000000 | AE36: 406000000 | AF36: 837000000
A37: Industrialización | J37: 97000000 | K37: 146000000 | L37: 202000000 | P37: 301000000
A38: Comercialización | J38: 6000000 | K38: 20000000 | L38: 20000000 | P38: 21000000
A39: Gas y energía | J39: 5000000 | K39: 11000000 | L39: 27000000 | N39: 52000000 | O39: 45000000 | P39: 39000000 | Q39: 42000000 | S39: 17000000 | T39: 45000000 | AD39: 58000000 | AE39: 27000000 | AF39: 78000000
A40: GNL y gas integrado | U40: 18000000 | V40: 3000000 | W40: 14000000 | X40: 9000000 | Y40: 16000000 | Z40: 18000000 | AA40: 23000000 | AG40: 14000000 | AH40: 26000000 | AI40: 42000000
A41: Nuevas energías | R41: 5000000 | U41: 14000000 | V41: 10000000 | W41: 8000000 | X41: 7000000 | Y41: 13000000 | Z41: 9000000 | AA41: 8000000 | AG41: 24000000 | AH41: 37000000 | AI41: 38000000
A42: Administración central y otros | J42: 23000000 | K42: 15000000 | L42: 55000000 | N42: 17000000 | O42: 31000000 | P42: 35000000 | Q42: 21000000 | R42: 24000000 | S42: 21000000 | T42: 30000000 | U42: 57000000 | V42: 20000000 | W42: 26000000 | X42: 33000000 | Y42: 29000000 | Z42: 12000000 | AA42: 32000000 | AD42: 62000000 | AE42: 65000000 | AF42: 166000000 | AG42: 151000000 | AH42: 127000000 | AI42: 108000000
A43: Total | J43: 730000000 | K43: 904000000 | L43: 1137000000 | M43: 1688000000 | N43: 1298000000 | O43: 1374000000 | P43: 1546000000 | Q43: 1973000000 | R43: 1252000000 | S43: 1294000000 | T43: 1466000000 | U43: 1588000000 | V43: 1306000000 | W43: 1274000000 | X43: 1144000000 | Y43: 1185000000 | Z43: 1036000000 | AA43: 1788000000 | AD43: 1325000000 | AE43: 2666000000 | AF43: 4459000000 | AG43: 6191000000 | AH43: 5600000000 | AI43: 4909000000
A44: Suma de segmentos − total | B44: =IF(COUNT(B43)=1,SUM(B34,B35,B36,B37,B38,B39,B40,B41,B42)-B43,"") | C44: =IF(COUNT(C43)=1,SUM(C34,C35,C36,C37,C38,C39,C40,C41,C42)-C43,"") | D44: =IF(COUNT(D43)=1,SUM(D34,D35,D36,D37,D38,D39,D40,D41,D42)-D43,"") | E44: =IF(COUNT(E43)=1,SUM(E34,E35,E36,E37,E38,E39,E40,E41,E42)-E43,"") | F44: =IF(COUNT(F43)=1,SUM(F34,F35,F36,F37,F38,F39,F40,F41,F42)-F43,"") | G44: =IF(COUNT(G43)=1,SUM(G34,G35,G36,G37,G38,G39,G40,G41,G42)-G43,"") | H44: =IF(COUNT(H43)=1,SUM(H34,H35,H36,H37,H38,H39,H40,H41,H42)-H43,"") | I44: =IF(COUNT(I43)=1,SUM(I34,I35,I36,I37,I38,I39,I40,I41,I42)-I43,"") | ... AA44: =IF(COUNT(AA43)=1,SUM(AA34,AA35,AA36,AA37,AA38,AA39,AA40,AA41,AA42)-AA43,"") | AC44: =IF(COUNT(AC43)=1,SUM(AC34,AC35,AC36,AC37,AC38,AC39,AC40,AC41,AC42)-AC43,"") | AD44: =IF(COUNT(AD43)=1,SUM(AD34,AD35,AD36,AD37,AD38,AD39,AD40,AD41,AD42)-AD43,"") | AE44: =IF(COUNT(AE43)=1,SUM(AE34,AE35,AE36,AE37,AE38,AE39,AE40,AE41,AE42)-AE43,"") | AF44: =IF(COUNT(AF43)=1,SUM(AF34,AF35,AF36,AF37,AF38,AF39,AF40,AF41,AF42)-AF43,"") | AG44: =IF(COUNT(AG43)=1,SUM(AG34,AG35,AG36,AG37,AG38,AG39,AG40,AG41,AG42)-AG43,"") | AH44: =IF(COUNT(AH43)=1,SUM(AH34,AH35,AH36,AH37,AH38,AH39,AH40,AH41,AH42)-AH43,"") | AI44: =IF(COUNT(AI43)=1,SUM(AI34,AI35,AI36,AI37,AI38,AI39,AI40,AI41,AI42)-AI43,"") | AK44: Da cero cuando la apertura está completa. Donde un segmento no se publicó —el 4T22, que es cuando la compañía cambió la apertura— la diferencia es ese hueco.
A46: Depreciación de bienes de uso
A47: Upstream | B47: 5.7306512e+08 | C47: 4.7591078e+08 | D47: 4.7381786e+08 | E47: 3.2636498e+08 | F47: 5.5017387e+08 | G47: 6.3087683e+08 | H47: 5.7222064e+08 | I47: 4.9678165e+08 | J47: 446000000 | K47: 475000000 | L47: 508000000 | N47: 568000000 | O47: 636000000 | P47: 661000000 | Q47: 583000000 | R47: 431000000 | S47: 415000000 | T47: 428000000 | U47: 530000000 | V47: 561000000 | W47: 548000000 | X47: 582000000 | Y47: 508000000 | Z47: 480000000 | AA47: 590000000 | AC47: 2.4892091e+09 | AD47: 1854000000 | AE47: 2259000000 | AF47: 1935000000 | AG47: 2437000000 | AH47: 1809000000 | AI47: 2199000000
A48: Midstream y Downstream | R48: 118000000 | U48: 151000000 | V48: 125000000 | W48: 127000000 | X48: 140000000 | Y48: 147000000 | Z48: 137000000 | AA48: 141000000 | AG48: 486000000 | AH48: 516000000 | AI48: 539000000
A49: Downstream | B49: 1.1396172e+08 | C49: 1.1428613e+08 | D49: 1.4273662e+08 | E49: 1.1409711e+08 | F49: 1.1087751e+08 | G49: 1.1434782e+08 | H49: 1.1480424e+08 | I49: 1.1643367e+08 | N49: 114000000 | O49: 118000000 | Q49: 118000000 | S49: 115000000 | T49: 119000000 | AC49: 4.3221134e+08 | AD49: 484000000 | AE49: 456000000 | AF49: 477000000
A50: Industrialización | J50: 99000000 | K50: 102000000 | L50: 104000000 | P50: 101000000
A51: Comercialización | J51: 13000000 | K51: 14000000 | L51: 14000000 | P51: 13000000
A52: Gas y energía | B52: 6594441.7 | C52: 6591151.7 | D52: 6513476.5 | E52: 6638058.8 | F52: 6597296.7 | G52: 7056930.7 | H52: 7706432.9 | I52: 8102676.2 | J52: 14000000 | K52: 12000000 | L52: 11000000 | N52: 12000000 | O52: 20000000 | P52: 8000000 | Q52: 4000000 | S52: 14000000 | T52: 15000000 | AC52: 28627120 | AD52: 23000000 | AE52: 28000000 | AF52: 48000000
A53: GNL y gas integrado | U53: 1000000 | V53: 1000000 | W53: 0 | X53: 1000000 | Y53: 0 | Z53: 1000000 | AA53: 33000000 | AG53: 10000000 | AH53: 2000000 | AI53: 2000000
A54: Nuevas energías | R54: 8000000 | U54: 8000000 | V54: 10000000 | W54: 8000000 | X54: 7000000 | Y54: 9000000 | Z54: 11000000 | AA54: 6000000 | AG54: 15000000 | AH54: 32000000 | AI54: 34000000
A55: Administración central y otros | B55: 16885027 | C55: 39161809 | D55: 23841782 | E55: 21751831 | F55: 20040418 | G55: 19957383 | H55: 20845438 | I55: 22824861 | J55: 17000000 | K55: 26000000 | L55: 20000000 | N55: 15000000 | O55: 17000000 | P55: 15000000 | Q55: 13000000 | R55: 19000000 | S55: 17000000 | T55: 33000000 | U55: 24000000 | V55: 21000000 | W55: 21000000 | X55: 20000000 | Y55: 21000000 | Z55: 24000000 | AA55: 18000000 | AC55: 80812407 | AD55: 99000000 | AE55: 73000000 | AF55: 91000000 | AG55: 68000000 | AH55: 87000000 | AI55: 83000000
A56: Total | B56: 7.1050631e+08 | C56: 6.3594987e+08 | D56: 6.4690974e+08 | E56: 4.6885197e+08 | F56: 6.876891e+08 | G56: 7.7223897e+08 | H56: 7.1557676e+08 | I56: 6.4414285e+08 | J56: 589000000 | K56: 629000000 | L56: 657000000 | M56: 676000000 | N56: 709000000 | O56: 791000000 | P56: 798000000 | Q56: 718000000 | R56: 576000000 | S56: 561000000 | T56: 595000000 | U56: 714000000 | V56: 718000000 | W56: 704000000 | X56: 750000000 | Y56: 685000000 | Z56: 653000000 | AA56: 788000000 | AC56: 3.03086e+09 | AD56: 2460000000 | AE56: 2816000000 | AF56: 2551000000 | AG56: 3016000000 | AH56: 2446000000 | AI56: 2857000000
A57: Suma de segmentos − total | B57: =IF(COUNT(B56)=1,SUM(B47,B48,B49,B50,B51,B52,B53,B54,B55)-B56,"") | C57: =IF(COUNT(C56)=1,SUM(C47,C48,C49,C50,C51,C52,C53,C54,C55)-C56,"") | D57: =IF(COUNT(D56)=1,SUM(D47,D48,D49,D50,D51,D52,D53,D54,D55)-D56,"") | E57: =IF(COUNT(E56)=1,SUM(E47,E48,E49,E50,E51,E52,E53,E54,E55)-E56,"") | F57: =IF(COUNT(F56)=1,SUM(F47,F48,F49,F50,F51,F52,F53,F54,F55)-F56,"") | G57: =IF(COUNT(G56)=1,SUM(G47,G48,G49,G50,G51,G52,G53,G54,G55)-G56,"") | H57: =IF(COUNT(H56)=1,SUM(H47,H48,H49,H50,H51,H52,H53,H54,H55)-H56,"") | I57: =IF(COUNT(I56)=1,SUM(I47,I48,I49,I50,I51,I52,I53,I54,I55)-I56,"") | ... AA57: =IF(COUNT(AA56)=1,SUM(AA47,AA48,AA49,AA50,AA51,AA52,AA53,AA54,AA55)-AA56,"") | AC57: =IF(COUNT(AC56)=1,SUM(AC47,AC48,AC49,AC50,AC51,AC52,AC53,AC54,AC55)-AC56,"") | AD57: =IF(COUNT(AD56)=1,SUM(AD47,AD48,AD49,AD50,AD51,AD52,AD53,AD54,AD55)-AD56,"") | AE57: =IF(COUNT(AE56)=1,SUM(AE47,AE48,AE49,AE50,AE51,AE52,AE53,AE54,AE55)-AE56,"") | AF57: =IF(COUNT(AF56)=1,SUM(AF47,AF48,AF49,AF50,AF51,AF52,AF53,AF54,AF55)-AF56,"") | AG57: =IF(COUNT(AG56)=1,SUM(AG47,AG48,AG49,AG50,AG51,AG52,AG53,AG54,AG55)-AG56,"") | AH57: =IF(COUNT(AH56)=1,SUM(AH47,AH48,AH49,AH50,AH51,AH52,AH53,AH54,AH55)-AH56,"") | AI57: =IF(COUNT(AI56)=1,SUM(AI47,AI48,AI49,AI50,AI51,AI52,AI53,AI54,AI55)-AI56,"") | AK57: Da cero cuando la apertura está completa. Donde un segmento no se publicó —el 4T22, que es cuando la compañía cambió la apertura— la diferencia es ese hueco.
A59: Activos
A60: Upstream | B60: 1.4886455e+10 | C60: 0 | D60: 0 | E60: 0 | F60: 1.2149679e+10 | G60: 0 | H60: 2.3561724e+08 | I60: 1.0474084e+10 | J60: 1.0738942e+10 | K60: 1.5985623e+09 | L60: 1.0773121e+10 | M60: 11528000000 | N60: 12121000000 | O60: 12309000000 | P60: 12275000000 | Q60: 10869000000 | R60: 11909000000 | S60: 12487000000 | T60: 12684000000 | U60: 12795000000 | V60: 13072000000 | W60: 12621000000 | X60: 13300000000 | Y60: 13167000000 | Z60: 13578000000 | AA60: 14142000000 | AC60: 1.5432261e+10 | AD60: 10876000000 | AE60: 10681000000 | AF60: 11317000000 | AG60: 10869000000 | AH60: 12795000000 | AI60: 13167000000
A61: Midstream y Downstream | U61: 10735000000 | V61: 10982000000 | W61: 11163000000 | X61: 11194000000 | Y61: 11093000000 | Z61: 12019000000 | AA61: 11932000000 | AG61: 9734000000 | AH61: 10758000000 | AI61: 11093000000
A62: Downstream | B62: 1.0528132e+10 | C62: 0 | D62: 0 | E62: 0 | F62: 9.9409625e+09 | G62: 0 | H62: 5.7092424e+08 | I62: 8.5699778e+09 | J62: 9.1004604e+09 | K62: 1.3592205e+09 | L62: 9.4384181e+09 | Q62: 9916000000 | R62: 9627000000 | S62: 9940000000 | T62: 10252000000 | AC62: 1.0553934e+10 | AD62: 7694000000 | AE62: 8321000000 | AF62: 9530000000
A63: Industrialización | M63: 6732000000 | N63: 7078000000 | O63: 7139000000 | P63: 7081000000
A64: Comercialización | M64: 3216000000 | N64: 2425000000 | O64: 2481000000 | P64: 2612000000
A65: Gas y energía | B65: 3.4067211e+09 | C65: 0 | D65: 0 | E65: 0 | F65: 3.0055657e+09 | G65: 0 | H65: 1.9525364e+08 | I65: 2.5910601e+09 | J65: 2.7812249e+09 | K65: 5.3265912e+08 | L65: 3.0566677e+09 | M65: 2797000000 | N65: 2781000000 | O65: 2811000000 | P65: 2882000000 | Q65: 2282000000 | R65: 3253000000 | S65: 3401000000 | T65: 3811000000 | AC65: 4.1415216e+09 | AD65: 2490000000 | AE65: 2846000000 | AF65: 3215000000
A66: GNL y gas integrado | U66: 743000000 | V66: 757000000 | W66: 936000000 | X66: 953000000 | Y66: 735000000 | Z66: 746000000 | AA66: 901000000 | AG66: 651000000 | AH66: 720000000 | AI66: 735000000
A67: Nuevas energías | U67: 2524000000 | V67: 2629000000 | W67: 2460000000 | X67: 2458000000 | Y67: 2502000000 | Z67: 2320000000 | AA67: 2423000000 | AG67: 1877000000 | AH67: 2524000000 | AI67: 2502000000
A68: Administración central y otros | B68: 2.4882375e+09 | C68: 0 | D68: 0 | E68: 0 | F68: 2.0580402e+09 | G68: 0 | H68: 1.5790471e+08 | I68: 1.7742104e+09 | J68: 2.1408417e+09 | K68: 2.9943796e+08 | L68: 2.239781e+09 | M68: 1807000000 | N68: 2033000000 | O68: 2399000000 | P68: 2019000000 | Q68: 2086000000 | R68: 2187000000 | S68: 2047000000 | T68: 2233000000 | U68: 2822000000 | V68: 2532000000 | W68: 2099000000 | X68: 1899000000 | Y68: 2094000000 | Z68: 2513000000 | AA68: 3477000000 | AC68: 2.6867736e+09 | AD68: 1818000000 | AE68: 1575000000 | AF68: 2018000000 | AG68: 2022000000 | AH68: 2822000000 | AI68: 2094000000
A69: Ajustes de consolidación | B69: 5503509.3 | C69: 0 | D69: 0 | E69: 0 | F69: -1.5426829e+08 | G69: 0 | H69: -21267285 | I69: -1.3299274e+08 | J69: -2.3066662e+08 | K69: -87011813 | L69: -1.9242343e+08 | M69: -168000000 | N69: -146000000 | O69: -134000000 | P69: -22000000 | Q69: -118000000 | R69: -327000000 | S69: -336000000 | T69: -222000000 | U69: -228000000 | V69: -258000000 | W69: -264000000 | X69: -235000000 | Y69: -152000000 | Z69: -818000000 | AA69: -482000000 | AC69: -1.3035935e+08 | AD69: 4000000 | AE69: -133000000 | AF69: -168000000 | AG69: -118000000 | AH69: -228000000 | AI69: -152000000
A70: Total | B70: 3.131505e+10 | C70: 0 | D70: 0 | E70: 0 | F70: 2.6999979e+10 | G70: 0 | H70: 1.1384325e+09 | I70: 2.327634e+10 | J70: 2.4530802e+10 | K70: 3.7028681e+09 | L70: 2.5315565e+10 | M70: 25912000000 | N70: 26292000000 | O70: 27005000000 | P70: 26847000000 | Q70: 25035000000 | R70: 26649000000 | S70: 27539000000 | T70: 28758000000 | U70: 29391000000 | V70: 29714000000 | W70: 29015000000 | X70: 29569000000 | Y70: 29439000000 | Z70: 30358000000 | AA70: 32393000000 | AC70: 3.2684131e+10 | AD70: 22882000000 | AE70: 23290000000 | AF70: 25912000000 | AG70: 25035000000 | AH70: 29391000000 | AI70: 29439000000
